Workbook

Sheet Start Here
A1: UB College Tracker | Class of 2027
A2: University Bridges | DeKalb County Department of Youth Services | Tracker for Aaliyah Hilton
B4: HOW IT WORKS
B5: 1. Explore | C5: Browse about 200 colleges. Each one is labeled Likely, Target or Reach for you, based on your GPA and SAT. Use the filter arrows to sort and narrow.
B6: 2. My Colleges | C6: Pick a college from the dropdown (or type one that is not listed) and choose your round. Deadlines, fees and requirements fill in by themselves.
B7: 3. Next Steps | C7: Every college you add gets its own checklist with due dates counted back from its real deadline. Check each step off as you finish it.
B8: 4. This Week | C8: Your UB plan for every Thursday session, plus your next 10 college steps in date order.
B9: 5. Essays | C9: Your personal statement, your two main essays, and every extra essay prompt from your colleges, pulled in automatically.
B10: 6. Money | C10: Scholarships, and in spring, comparing award letters.
B11: 7. Me | C11: Your profile, account usernames and recommenders.
B13: COLORS
B14: White cells | C14: Type here or use the dropdown.
B15: Gray cells | C15: Fill in automatically. Do not type over them.
B16: Red row | C16: Past due and not done.
B17: Orange row | C17: Due in the next 7 days.
B19: RULES THAT DO NOT BEND
B20: Earliest date wins | C20: If a college's scholarship deadline is earlier than its application deadline, the scholarship date is your real deadline. The tracker uses it automatically.
B21: Early Decision is binding | C21: If admitted Early Decision you must attend and withdraw every other application. Only one Early Decision can be active at a time.
B22: Verify every date | C22: Deadline Verified stays No until you check the date on the college's own website. Some dates in the list are last year's pattern.
B23: Personal statement first | C23: Get your personal statement to a near-final draft before you start any college's extra essays.
B24: Never delete or reorder | C24: To drop a college, set On Final List to No. Deleting or moving rows mixes up your checklists.
B25: No passwords | C25: Never type a password anywhere in this tracker.
B26: Every Sunday | C26: Check off what you finished and type the date in the Last updated box on This Week.

Sheet This Week
A1: This Week
A2: Top: your next 10 college steps, in date order, pulled from Next Steps (check them off there). Bottom: your UB plan, one block per Thursday session. Every Sunday: check off what you finished and type today's date in Last updated.
A4: College steps overdue | B4: College steps due in 7 days | C4: UB tasks overdue | D4: UB tasks due in 7 days | F4: LAST UPDATED: type today's date every Sunday
A5: ='Next Steps'!A5 -> 0 | B5: ='Next Steps'!C5 -> 0 | C5: =SUMPRODUCT(ISNUMBER($A$22:$A$78)*($A$22:$A$78<TODAY())*($E$22:$E$78<>TRUE())*($D$22:$D$78<>"")) -> 0 | D5: =SUMPRODUCT(ISNUMBER($A$22:$A$78)*($A$22:$A$78>=TODAY())*($A$22:$A$78<=TODAY()+7)*($E$22:$E$78<>TRUE())*($D$22:$D$78<>"")) -> 12
A8: Due | B8: Days Out | C8: College | D8: Step
A9: =IF($H9="","",INT($H9)) | B9: =IF($A9="","",$A9-TODAY()) | C9: =IF($H9="","",INDEX('Next Steps'!$A$8:$A$27,SUMPRODUCT(('Next Steps'!$AE$8:$AP$27=$H9)*(ROW('Next Steps'!$AE$8:$AP$27)-7)))) | D9: =IF($H9="","",INDEX('Next Steps'!$AE$6:$AP$6,SUMPRODUCT(('Next Steps'!$AE$8:$AP$27=$H9)*(COLUMN('Next Steps'!$AE$8:$AP$27)-COLUMN('Next Steps'!$AE$6)+1)))) | H9: =IFERROR(SMALL('Next Steps'!$AE$8:$AP$27,1),"")
A10: =IF($H10="","",INT($H10)) | B10: =IF($A10="","",$A10-TODAY()) | C10: =IF($H10="","",INDEX('Next Steps'!$A$8:$A$27,SUMPRODUCT(('Next Steps'!$AE$8:$AP$27=$H10)*(ROW('Next Steps'!$AE$8:$AP$27)-7)))) | D10: =IF($H10="","",INDEX('Next Steps'!$AE$6:$AP$6,SUMPRODUCT(('Next Steps'!$AE$8:$AP$27=$H10)*(COLUMN('Next Steps'!$AE$8:$AP$27)-COLUMN('Next Steps'!$AE$6)+1)))) | H10: =IFERROR(SMALL('Next Steps'!$AE$8:$AP$27,2),"")
A11: =IF($H11="","",INT($H11)) | B11: =IF($A11="","",$A11-TODAY()) | C11: =IF($H11="","",INDEX('Next Steps'!$A$8:$A$27,SUMPRODUCT(('Next Steps'!$AE$8:$AP$27=$H11)*(ROW('Next Steps'!$AE$8:$AP$27)-7)))) | D11: =IF($H11="","",INDEX('Next Steps'!$AE$6:$AP$6,SUMPRODUCT(('Next Steps'!$AE$8:$AP$27=$H11)*(COLUMN('Next Steps'!$AE$8:$AP$27)-COLUMN('Next Steps'!$AE$6)+1)))) | H11: =IFERROR(SMALL('Next Steps'!$AE$8:$AP$27,3),"")
A12: =IF($H12="","",INT($H12)) | B12: =IF($A12="","",$A12-TODAY()) | C12: =IF($H12="","",INDEX('Next Steps'!$A$8:$A$27,SUMPRODUCT(('Next Steps'!$AE$8:$AP$27=$H12)*(ROW('Next Steps'!$AE$8:$AP$27)-7)))) | D12: =IF($H12="","",INDEX('Next Steps'!$AE$6:$AP$6,SUMPRODUCT(('Next Steps'!$AE$8:$AP$27=$H12)*(COLUMN('Next Steps'!$AE$8:$AP$27)-COLUMN('Next Steps'!$AE$6)+1)))) | H12: =IFERROR(SMALL('Next Steps'!$AE$8:$AP$27,4),"")
A13: =IF($H13="","",INT($H13)) | B13: =IF($A13="","",$A13-TODAY()) | C13: =IF($H13="","",INDEX('Next Steps'!$A$8:$A$27,SUMPRODUCT(('Next Steps'!$AE$8:$AP$27=$H13)*(ROW('Next Steps'!$AE$8:$AP$27)-7)))) | D13: =IF($H13="","",INDEX('Next Steps'!$AE$6:$AP$6,SUMPRODUCT(('Next Steps'!$AE$8:$AP$27=$H13)*(COLUMN('Next Steps'!$AE$8:$AP$27)-COLUMN('Next Steps'!$AE$6)+1)))) | H13: =IFERROR(SMALL('Next Steps'!$AE$8:$AP$27,5),"")
A14: =IF($H14="","",INT($H14)) | B14: =IF($A14="","",$A14-TODAY()) | C14: =IF($H14="","",INDEX('Next Steps'!$A$8:$A$27,SUMPRODUCT(('Next Steps'!$AE$8:$AP$27=$H14)*(ROW('Next Steps'!$AE$8:$AP$27)-7)))) | D14: =IF($H14="","",INDEX('Next Steps'!$AE$6:$AP$6,SUMPRODUCT(('Next Steps'!$AE$8:$AP$27=$H14)*(COLUMN('Next Steps'!$AE$8:$AP$27)-COLUMN('Next Steps'!$AE$6)+1)))) | H14: =IFERROR(SMALL('Next Steps'!$AE$8:$AP$27,6),"")
A15: =IF($H15="","",INT($H15)) | B15: =IF($A15="","",$A15-TODAY()) | C15: =IF($H15="","",INDEX('Next Steps'!$A$8:$A$27,SUMPRODUCT(('Next Steps'!$AE$8:$AP$27=$H15)*(ROW('Next Steps'!$AE$8:$AP$27)-7)))) | D15: =IF($H15="","",INDEX('Next Steps'!$AE$6:$AP$6,SUMPRODUCT(('Next Steps'!$AE$8:$AP$27=$H15)*(COLUMN('Next Steps'!$AE$8:$AP$27)-COLUMN('Next Steps'!$AE$6)+1)))) | H15: =IFERROR(SMALL('Next Steps'!$AE$8:$AP$27,7),"")
A16: =IF($H16="","",INT($H16)) | B16: =IF($A16="","",$A16-TODAY()) | C16: =IF($H16="","",INDEX('Next Steps'!$A$8:$A$27,SUMPRODUCT(('Next Steps'!$AE$8:$AP$27=$H16)*(ROW('Next Steps'!$AE$8:$AP$27)-7)))) | D16: =IF($H16="","",INDEX('Next Steps'!$AE$6:$AP$6,SUMPRODUCT(('Next Steps'!$AE$8:$AP$27=$H16)*(COLUMN('Next Steps'!$AE$8:$AP$27)-COLUMN('Next Steps'!$AE$6)+1)))) | H16: =IFERROR(SMALL('Next Steps'!$AE$8:$AP$27,8),"")
A17: =IF($H17="","",INT($H17)) | B17: =IF($A17="","",$A17-TODAY()) | C17: =IF($H17="","",INDEX('Next Steps'!$A$8:$A$27,SUMPRODUCT(('Next Steps'!$AE$8:$AP$27=$H17)*(ROW('Next Steps'!$AE$8:$AP$27)-7)))) | D17: =IF($H17="","",INDEX('Next Steps'!$AE$6:$AP$6,SUMPRODUCT(('Next Steps'!$AE$8:$AP$27=$H17)*(COLUMN('Next Steps'!$AE$8:$AP$27)-COLUMN('Next Steps'!$AE$6)+1)))) | H17: =IFERROR(SMALL('Next Steps'!$AE$8:$AP$27,9),"")
A18: =IF($H18="","",INT($H18)) | B18: =IF($A18="","",$A18-TODAY()) | C18: =IF($H18="","",INDEX('Next Steps'!$A$8:$A$27,SUMPRODUCT(('Next Steps'!$AE$8:$AP$27=$H18)*(ROW('Next Steps'!$AE$8:$AP$27)-7)))) | D18: =IF($H18="","",INDEX('Next Steps'!$AE$6:$AP$6,SUMPRODUCT(('Next Steps'!$AE$8:$AP$27=$H18)*(COLUMN('Next Steps'!$AE$8:$AP$27)-COLUMN('Next Steps'!$AE$6)+1)))) | H18: =IFERROR(SMALL('Next Steps'!$AE$8:$AP$27,10),"")
A19: Check these off on the Next Steps tab.
A21: Session | B21: Track | C21: Owner | D21: Deliverable | E21: Done | G21: Notes
A22: Getting started | due Thursday October 15
A23: 46310 | B23: Foundation | C23: Student | D23: Fill in the Me tab: GPA, SAT/ACT, accounts, recommenders | E23: =FALSE() -> FALSE
A24: 46310 | B24: Foundation | C24: Student | D24: Create Common App and GAfutures accounts | E24: =FALSE() -> FALSE
A25: 46310 | B25: Foundation | C25: Parent | D25: Create StudentAID.gov accounts (FSA ID): one for you, one for a parent | E25: =FALSE() -> FALSE
A26: 46310 | B26: Applications | C26: Student | D26: Explore: add 6 to 10 colleges to My Colleges (about 2 Likely, 3 to 4 Target, 2 Reach) and pick a round for each | E26: =FALSE() -> FALSE
A27: UB Session | Thursday October 8
A28: 46303 | B28: Applications | C28: Student | D28: Personal statement: topic locked and full Draft 1 (about 650 words) | E28: =FALSE() -> FALSE
A29: 46303 | B29: Applications | C29: Student | D29: Close the early list: every college due on or before November 1 confirmed in or out | E29: =FALSE() -> FALSE
A30: 46303 | B30: Applications | C30: Student | D30: Ask two teachers and your school counselor for recommendations. Give them your brag sheet and deadline list | E30: =FALSE() -> FALSE
A31: 46303 | B31: Foundation | C31: Parent | D31: Gather FAFSA documents: 2025 tax returns and W-2s | E31: =FALSE() -> FALSE
A32: Getting started | due Thursday October 15
A33: 46310 | B33: Applications | C33: Student | D33: UGA and Georgia Tech Early Action due today, if on your list | E33: =FALSE() -> FALSE
A34: 46310 | B34: Applications | C34: Student | D34: Personal statement Draft 2, near-final | E34: =FALSE() -> FALSE
A35: 46310 | B35: Foundation | C35: Parent | D35: Submit the 2027-28 FAFSA together (student and parent sections) | E35: =FALSE() -> FALSE
A36: 46310 | B36: Scholarships | C36: Student | D36: Add at least ten scholarships to Money, local ones first | E36: =FALSE() -> FALSE
A37: UB Session | Thursday October 22
A38: 46317 | B38: Applications | C38: Student | D38: Personal statement final | E38: =FALSE() -> FALSE
A39: 46317 | B39: Applications | C39: Student | D39: Extra essays done for every college due November 1 | E39: =FALSE() -> FALSE
A40: 46317 | B40: Foundation | C40: Student | D40: Georgia Match: log into GAfutures and claim your spot at up to three colleges | E40: =FALSE() -> FALSE
A41: 46317 | B41: Scholarships | C41: Student | D41: Two scholarship submissions | E41: =FALSE() -> FALSE
A42: UB Session | Thursday October 29
A43: 46324 | B43: Applications | C43: Student | D43: Submit every November 1 application. Confirm transcript and scores were sent | E43: =FALSE() -> FALSE
A44: 46324 | B44: Foundation | C44: Parent | D44: CSS Profile, only if a college on your list requires it | E44: =FALSE() -> FALSE
A45: 46324 | B45: Scholarships | C45: Student | D45: Two scholarship submissions | E45: =FALSE() -> FALSE
A46: UB Session | Thursday November 5
A47: 46331 | B47: Applications | C47: Student | D47: Close the full list. Any college added after today must replace one | E47: =FALSE() -> FALSE
A48: 46331 | B48: Applications | C48: Student | D48: Apply to College Month: submit Georgia applications while fees are waived | E48: =FALSE() -> FALSE
A49: 46331 | B49: Foundation | C49: Parent | D49: Open your FAFSA Submission Summary and fix any errors | E49: =FALSE() -> FALSE
A50: UB Session | Thursday November 12
A51: 46338 | B51: Applications | C51: Student | D51: Log into every portal: confirm early applications show everything received | E51: =FALSE() -> FALSE
A52: 46338 | B52: Applications | C52: Student | D52: Draft extra essays for Regular Decision colleges | E52: =FALSE() -> FALSE
A53: 46338 | B53: Scholarships | C53: Student | D53: Two scholarship submissions | E53: =FALSE() -> FALSE
A54: UB Session | Thursday November 19
A55: 46345 | B55: Applications | C55: Student | D55: Submit any college scholarship (merit) application due December 1 | E55: =FALSE() -> FALSE
A56: 46345 | B56: Applications | C56: Student | D56: Regular Decision essays near-final | E56: =FALSE() -> FALSE
A57: 46345 | B57: Foundation | C57: Student | D57: Thank-you notes to every recommender | E57: =FALSE() -> FALSE
A58: UB Session | Thursday December 3
A59: 46359 | B59: Applications | C59: Student | D59: Regular Decision essays final | E59: =FALSE() -> FALSE
A60: 46359 | B60: Scholarships | C60: Student | D60: Two scholarship submissions | E60: =FALSE() -> FALSE
A61: UB Session | Thursday December 10
A62: 46366 | B62: Applications | C62: Student | D62: Record early decisions. If deferred, send a short update letter | E62: =FALSE() -> FALSE
A63: 46366 | B63: Applications | C63: Student | D63: Submit Regular Decision applications | E63: =FALSE() -> FALSE
A64: UB Session | Thursday December 17
A65: 46373 | B65: Applications | C65: Student | D65: Every remaining application submitted before winter break | E65: =FALSE() -> FALSE
A66: 46373 | B66: Applications | C66: Student | D66: If admitted Early Decision: accept and withdraw every other application | E66: =FALSE() -> FALSE
A67: UB Session | Thursday January 7
A68: 46394 | B68: Applications | C68: Student | D68: Ask your school counselor to send your mid-year report | E68: =FALSE() -> FALSE
A69: 46394 | B69: Applications | C69: Student | D69: Confirm every Regular Decision application shows complete | E69: =FALSE() -> FALSE
A70: UB Session | Thursday January 14
A71: 46401 | B71: Scholarships | C71: Student | D71: Two scholarship submissions | E71: =FALSE() -> FALSE
A72: 46401 | B72: Applications | C72: Student | D72: Check every portal for missing items | E72: =FALSE() -> FALSE
A73: UB Session | Thursday January 21
A74: 46408 | B74: Foundation | C74: Parent | D74: FAFSA check: submitted, signed by both, no open verification requests | E74: =FALSE() -> FALSE
A75: 46408 | B75: Foundation | C75: Student | D75: Check your HOPE GPA in GAfutures | E75: =FALSE() -> FALSE
A76: UB Session | Thursday January 28
A77: 46415 | B77: Scholarships | C77: Student | D77: Two scholarship submissions | E77: =FALSE() -> FALSE
A78: 46415 | B78: Foundation | C78: Student | D78: Spring plan: watch for decisions and award letters (Money tab) | E78: =FALSE() -> FALSE
A79: No sessions November 26, December 24 or December 31.

Sheet Explore
A1: Explore Colleges
A2: Every college in the UB database, labeled for you. Use the filter arrows on the header row to sort or narrow (for example Fit = Likely, or Category = HBCU). To add a college, pick it on My Colleges.
B4: Colleges in database | C4: Likely for me | D4: Target for me | E4: Reach for me | I4: Based on | X4: =IF(ISNUMBER(Me!$B$13),Me!$B$13,IF(ISNUMBER(Me!$B$14),30*Me!$B$14+490,"")) -> 850 | Y4: =IF(ISNUMBER(Me!$B$11),Me!$B$11,IF(ISNUMBER(Me!$B$10),Me!$B$10,"")) -> 3.5
B5: =COUNTIF(B8:B406,"?*") -> 205 | C5: =COUNTIF(E8:E406,"Likely") -> 22 | D5: =COUNTIF(E8:E406,"Target") -> 48 | E5: =COUNTIF(E8:E406,"Reach") -> 106 | I5: =IF(AND(NOT(ISNUMBER($X$4)),NOT(ISNUMBER($Y$4))),"Add your GPA and SAT/ACT on Me",IF(ISNUMBER(Me!$B$13),"SAT "&Me!$B$13,IF(ISNUMBER(Me!$B$14),"ACT "&Me!$B$14,"no test"))&" and GPA "&IF(ISNUMBER($Y$4),$Y$4,"missing")) -> SAT 850 and GPA 3.5
B6: Labels are estimates. Each college is judged on both your test score and your GPA, and the weaker of the two counts. Colleges admitting under 15% are always Reach.
A7: On My List | B7: College | C7: Category | D7: Location | E7: Fit for Me | F7: Admit Rate | G7: SAT Middle 50% | H7: Avg HS GPA | I7: Earliest Deadline | J7: Earliest Round | K7: Regular Deadline | L7: How to Apply | M7: App Fee | N7: Test Policy | O7: Extra Essays | P7: CSS Profile | Q7: Net Price (income under $30k) | R7: 6-Yr Grad Rate | S7: Data Status | T7: Admissions Page | U7: sat score | V7: gpa score | W7: combined
A8: =IF(B8="","",IF(COUNTIF('My Colleges'!$B$8:$B$27,B8)>0,"On list","")) | B8: =IF(DB_Colleges!A2="","",DB_Colleges!A2) -> University of Georgia | C8: =IF(B8="","",DB_Colleges!B2) -> Georgia Public (USG) | D8: =IF(B8="","",DB_Colleges!C2&", "&DB_Colleges!D2) -> Athens, GA | E8: =IF(B8="","",IF(AND(NOT(ISNUMBER($X$4)),NOT(ISNUMBER($Y$4))),"Add scores",IF(NOT(ISNUMBER(DB_Colleges!Y2)),IF(OR(C8="Ivy League",C8="Highly Selective"),"Reach",IF(COUNT(U8:V8)=0,"No data",CHOOSE(W8+2,"Reach","Target","Likely"))),IF(DB_Colleges!Y2<0.15,"Reach",IF(DB_Colleges!Y2>=0.75,IF(W8>=0,"Likely","Target"),IF(DB_Colleges!Y2>=0.4,CHOOSE(W8+2,"Reach","Target","Likely"),IF(W8=1,"Target","Reach"))))))) -> Reach | F8: =IF(OR(B8="",NOT(ISNUMBER(DB_Colleges!Y2))),"",DB_Colleges!Y2) -> 0.3 | G8: =IF(OR(B8="",NOT(ISNUMBER(DB_Colleges!Z2))),"",DB_Colleges!Z2&"-"&DB_Colleges!AA2) -> 1360-1500 | H8: =IF(OR(B8="",NOT(ISNUMBER(DB_Colleges!AD2))),"",DB_Colleges!AD2) -> 4.27 | I8: =IF(B8="","",IF(COUNT(DB_Colleges!I2:O2)=0,IF(DB_Colleges!P2="Yes","Rolling","Check site"),MIN(DB_Colleges!I2:O2))) -> 46310 | J8: =IF(OR(B8="",COUNT(DB_Colleges!I2:O2)=0),"",INDEX({"ED","ED II","EA","EA II","REA","RD","Priority"},MATCH(MIN(DB_Colleges!I2:O2),DB_Colleges!I2:O2,0))) -> EA | K8: =IF(OR(B8="",NOT(ISNUMBER(DB_Colleges!N2))),"",DB_Colleges!N2) -> 46388 | L8: =IF(B8="","",DB_Colleges!G2&"") -> Common App | M8: =IF(OR(B8="",NOT(ISNUMBER(DB_Colleges!S2))),"",DB_Colleges!S2) -> 70 | N8: =IF(B8="","",DB_Colleges!U2&"") -> Required | O8: =IF(B8="","",IF(ISNUMBER(DB_Colleges!AH2),DB_Colleges!AH2,"Check")) -> 0 | P8: =IF(B8="","",DB_Colleges!W2&"") -> Not required | Q8: =IF(OR(B8="",NOT(ISNUMBER(DB_Colleges!AF2))),"",DB_Colleges!AF2) | R8: =IF(OR(B8="",NOT(ISNUMBER(DB_Colleges!AG2))),"",DB_Colleges!AG2) -> 0.9 | S8: =IF(B8="","",DB_Colleges!AK2&"") -> Official 2026-27 | T8: =IF(B8="","",DB_Colleges!AI2&"") -> https://admissions.uga.edu/apply/first-year-applicants/ | U8: =IF(AND(ISNUMBER($X$4),ISNUMBER(DB_Colleges!Z2),ISNUMBER(DB_Colleges!AA2)),IF($X$4>=DB_Colleges!AA2,1,IF($X$4<DB_Colleges!Z2,-1,0)),"") -> -1 | V8: =IF(AND(ISNUMBER($Y$4),ISNUMBER(DB_Colleges!AD2)),IF($Y$4>=DB_Colleges!AD2+0.15,1,IF($Y$4<DB_Colleges!AD2-0.2,-1,0)),"") -> -1 | W8: =IF(COUNT(U8:V8)=0,0,MIN(U8:V8)) -> -1
A9: =IF(B9="","",IF(COUNTIF('My Colleges'!$B$8:$B$27,B9)>0,"On list","")) | B9: =IF(DB_Colleges!A3="","",DB_Colleges!A3) -> Georgia Institute of Technology | C9: =IF(B9="","",DB_Colleges!B3) -> Georgia Public (USG) | D9: =IF(B9="","",DB_Colleges!C3&", "&DB_Colleges!D3) -> Atlanta, GA | E9: =IF(B9="","",IF(AND(NOT(ISNUMBER($X$4)),NOT(ISNUMBER($Y$4))),"Add scores",IF(NOT(ISNUMBER(DB_Colleges!Y3)),IF(OR(C9="Ivy League",C9="Highly Selective"),"Reach",IF(COUNT(U9:V9)=0,"No data",CHOOSE(W9+2,"Reach","Target","Likely"))),IF(DB_Colleges!Y3<0.15,"Reach",IF(DB_Colleges!Y3>=0.75,IF(W9>=0,"Likely","Target"),IF(DB_Colleges!Y3>=0.4,CHOOSE(W9+2,"Reach","Target","Likely"),IF(W9=1,"Target","Reach"))))))) -> Reach | F9: =IF(OR(B9="",NOT(ISNUMBER(DB_Colleges!Y3))),"",DB_Colleges!Y3) -> 0.133 | G9: =IF(OR(B9="",NOT(ISNUMBER(DB_Colleges!Z3))),"",DB_Colleges!Z3&"-"&DB_Colleges!AA3) -> 1370-1530 | H9: =IF(OR(B9="",NOT(ISNUMBER(DB_Colleges!AD3))),"",DB_Colleges!AD3) -> 4.17 | I9: =IF(B9="","",IF(COUNT(DB_Colleges!I3:O3)=0,IF(DB_Colleges!P3="Yes","Rolling","Check site"),MIN(DB_Colleges!I3:O3))) -> 46310 | J9: =IF(OR(B9="",COUNT(DB_Colleges!I3:O3)=0),"",INDEX({"ED","ED II","EA","EA II","REA","RD","Priority"},MATCH(MIN(DB_Colleges!I3:O3),DB_Colleges!I3:O3,0))) -> EA | K9: =IF(OR(B9="",NOT(ISNUMBER(DB_Colleges!N3))),"",DB_Colleges!N3) -> 46393 | L9: =IF(B9="","",DB_Colleges!G3&"") -> Common App | M9: =IF(OR(B9="",NOT(ISNUMBER(DB_Colleges!S3))),"",DB_Colleges!S3) -> 75 | N9: =IF(B9="","",DB_Colleges!U3&"") -> Required | O9: =IF(B9="","",IF(ISNUMBER(DB_Colleges!AH3),DB_Colleges!AH3,"Check")) -> Check | P9: =IF(B9="","",DB_Colleges!W3&"") -> Not required | Q9: =IF(OR(B9="",NOT(ISNUMBER(DB_Colleges!AF3))),"",DB_Colleges!AF3) | R9: =IF(OR(B9="",NOT(ISNUMBER(DB_Colleges!AG3))),"",DB_Colleges!AG3) -> 0.94 | S9: =IF(B9="","",DB_Colleges!AK3&"") -> Mixed | T9: =IF(B9="","",DB_Colleges!AI3&"") -> https://admission.gatech.edu/first-year/ | U9: =IF(AND(ISNUMBER($X$4),ISNUMBER(DB_Colleges!Z3),ISNUMBER(DB_Colleges!AA3)),IF($X$4>=DB_Colleges!AA3,1,IF($X$4<DB_Colleges!Z3,-1,0)),"") -> -1 | V9: =IF(AND(ISNUMBER($Y$4),ISNUMBER(DB_Colleges!AD3)),IF($Y$4>=DB_Colleges!AD3+0.15,1,IF($Y$4<DB_Colleges!AD3-0.2,-1,0)),"") -> -1 | W9: =IF(COUNT(U9:V9)=0,0,MIN(U9:V9)) -> -1
A10: =IF(B10="","",IF(COUNTIF('My Colleges'!$B$8:$B$27,B10)>0,"On list","")) | B10: =IF(DB_Colleges!A4="","",DB_Colleges!A4) -> Georgia State University | C10: =IF(B10="","",DB_Colleges!B4) -> Georgia Public (USG) | D10: =IF(B10="","",DB_Colleges!C4&", "&DB_Colleges!D4) -> Atlanta, GA | E10: =IF(B10="","",IF(AND(NOT(ISNUMBER($X$4)),NOT(ISNUMBER($Y$4))),"Add scores",IF(NOT(ISNUMBER(DB_Colleges!Y4)),IF(OR(C10="Ivy League",C10="Highly Selective"),"Reach",IF(COUNT(U10:V10)=0,"No data",CHOOSE(W10+2,"Reach","Target","Likely"))),IF(DB_Colleges!Y4<0.15,"Reach",IF(DB_Colleges!Y4>=0.75,IF(W10>=0,"Likely","Target"),IF(DB_Colleges!Y4>=0.4,CHOOSE(W10+2,"Reach","Target","Likely"),IF(W10=1,"Target","Reach"))))))) -> Target | F10: =IF(OR(B10="",NOT(ISNUMBER(DB_Colleges!Y4))),"",DB_Colleges!Y4) -> 0.57 | G10: =IF(OR(B10="",NOT(ISNUMBER(DB_Colleges!Z4))),"",DB_Colleges!Z4&"-"&DB_Colleges!AA4) | H10: =IF(OR(B10="",NOT(ISNUMBER(DB_Colleges!AD4))),"",DB_Colleges!AD4) | I10: =IF(B10="","",IF(COUNT(DB_Colleges!I4:O4)=0,IF(DB_Colleges!P4="Yes","Rolling","Check site"),MIN(DB_Colleges!I4:O4))) -> 46341 | J10: =IF(OR(B10="",COUNT(DB_Colleges!I4:O4)=0),"",INDEX({"ED","ED II","EA","EA II","REA","RD","Priority"},MATCH(MIN(DB_Colleges!I4:O4),DB_Colleges!I4:O4,0))) -> EA | K10: =IF(OR(B10="",NOT(ISNUMBER(DB_Colleges!N4))),"",DB_Colleges!N4) -> 46508 | L10: =IF(B10="","",DB_Colleges!G4&"") -> Common App | M10: =IF(OR(B10="",NOT(ISNUMBER(DB_Colleges!S4))),"",DB_Colleges!S4) -> 60 | N10: =IF(B10="","",DB_Colleges!U4&"") -> Required | O10: =IF(B10="","",IF(ISNUMBER(DB_Colleges!AH4),DB_Colleges!AH4,"Check")) -> Check | P10: =IF(B10="","",DB_Colleges!W4&"") -> Not required | Q10: =IF(OR(B10="",NOT(ISNUMBER(DB_Colleges!AF4))),"",DB_Colleges!AF4) | R10: =IF(OR(B10="",NOT(ISNUMBER(DB_Colleges!AG4))),"",DB_Colleges!AG4) | S10: =IF(B10="","",DB_Colleges!AK4&"") -> Mixed | T10: =IF(B10="","",DB_Colleges!AI4&"") -> https://admissions.gsu.edu/bachelors-degree/apply/ | U10: =IF(AND(ISNUMBER($X$4),ISNUMBER(DB_Colleges!Z4),ISNUMBER(DB_Colleges!AA4)),IF($X$4>=DB_Colleges!AA4,1,IF($X$4<DB_Colleges!Z4,-1,0)),"") | V10: =IF(AND(ISNUMBER($Y$4),ISNUMBER(DB_Colleges!AD4)),IF($Y$4>=DB_Colleges!AD4+0.15,1,IF($Y$4<DB_Colleges!AD4-0.2,-1,0)),"") | W10: =IF(COUNT(U10:V10)=0,0,MIN(U10:V10)) -> 0
A11: =IF(B11="","",IF(COUNTIF('My Colleges'!$B$8:$B$27,B11)>0,"On list","")) | B11: =IF(DB_Colleges!A5="","",DB_Colleges!A5) -> Kennesaw State University | C11: =IF(B11="","",DB_Colleges!B5) -> Georgia Public (USG) | D11: =IF(B11="","",DB_Colleges!C5&", "&DB_Colleges!D5) -> Kennesaw, GA | E11: =IF(B11="","",IF(AND(NOT(ISNUMBER($X$4)),NOT(ISNUMBER($Y$4))),"Add scores",IF(NOT(ISNUMBER(DB_Colleges!Y5)),IF(OR(C11="Ivy League",C11="Highly Selective"),"Reach",IF(COUNT(U11:V11)=0,"No data",CHOOSE(W11+2,"Reach","Target","Likely"))),IF(DB_Colleges!Y5<0.15,"Reach",IF(DB_Colleges!Y5>=0.75,IF(W11>=0,"Likely","Target"),IF(DB_Colleges!Y5>=0.4,CHOOSE(W11+2,"Reach","Target","Likely"),IF(W11=1,"Target","Reach"))))))) -> Target | F11: =IF(OR(B11="",NOT(ISNUMBER(DB_Colleges!Y5))),"",DB_Colleges!Y5) -> 0.79 | G11: =IF(OR(B11="",NOT(ISNUMBER(DB_Colleges!Z5))),"",DB_Colleges!Z5&"-"&DB_Colleges!AA5) -> 990-1230 | H11: =IF(OR(B11="",NOT(ISNUMBER(DB_Colleges!AD5))),"",DB_Colleges!AD5) -> 3.5 | I11: =IF(B11="","",IF(COUNT(DB_Colleges!I5:O5)=0,IF(DB_Colleges!P5="Yes","Rolling","Check site"),MIN(DB_Colleges!I5:O5))) -> 46328 | J11: =IF(OR(B11="",COUNT(DB_Colleges!I5:O5)=0),"",INDEX({"ED","ED II","EA","EA II","REA","RD","Priority"},MATCH(MIN(DB_Colleges!I5:O5),DB_Colleges!I5:O5,0))) -> Priority | K11: =IF(OR(B11="",NOT(ISNUMBER(DB_Colleges!N5))),"",DB_Colleges!N5) -> 46569 | L11: =IF(B11="","",DB_Colleges!G5&"") -> Common App; School portal | M11: =IF(OR(B11="",NOT(ISNUMBER(DB_Colleges!S5))),"",DB_Colleges!S5) -> 40 | N11: =IF(B11="","",DB_Colleges!U5&"") -> Required | O11: =IF(B11="","",IF(ISNUMBER(DB_Colleges!AH5),DB_Colleges!AH5,"Check")) -> Check | P11: =IF(B11="","",DB_Colleges!W5&"") -> Not required | Q11: =IF(OR(B11="",NOT(ISNUMBER(DB_Colleges!AF5))),"",DB_Colleges!AF5) | R11: =IF(OR(B11="",NOT(ISNUMBER(DB_Colleges!AG5))),"",DB_Colleges!AG5) | S11: =IF(B11="","",DB_Colleges!AK5&"") -> Mixed | T11: =IF(B11="","",DB_Colleges!AI5&"") -> https://www.kennesaw.edu/admissions/undergraduate/admission-requirements/freshman.php | U11: =IF(AND(ISNUMBER($X$4),ISNUMBER(DB_Colleges!Z5),ISNUMBER(DB_Colleges!AA5)),IF($X$4>=DB_Colleges!AA5,1,IF($X$4<DB_Colleges!Z5,-1,0)),"") -> -1 | V11: =IF(AND(ISNUMBER($Y$4),ISNUMBER(DB_Colleges!AD5)),IF($Y$4>=DB_Colleges!AD5+0.15,1,IF($Y$4<DB_Colleges!AD5-0.2,-1,0)),"") -> 0 | W11: =IF(COUNT(U11:V11)=0,0,MIN(U11:V11)) -> -1
A12: =IF(B12="","",IF(COUNTIF('My Colleges'!$B$8:$B$27,B12)>0,"On list","")) | B12: =IF(DB_Colleges!A6="","",DB_Colleges!A6) -> Georgia Southern University | C12: =IF(B12="","",DB_Colleges!B6) -> Georgia Public (USG) | D12: =IF(B12="","",DB_Colleges!C6&", "&DB_Colleges!D6) -> Statesboro, GA | E12: =IF(B12="","",IF(AND(NOT(ISNUMBER($X$4)),NOT(ISNUMBER($Y$4))),"Add scores",IF(NOT(ISNUMBER(DB_Colleges!Y6)),IF(OR(C12="Ivy League",C12="Highly Selective"),"Reach",IF(COUNT(U12:V12)=0,"No data",CHOOSE(W12+2,"Reach","Target","Likely"))),IF(DB_Colleges!Y6<0.15,"Reach",IF(DB_Colleges!Y6>=0.75,IF(W12>=0,"Likely","Target"),IF(DB_Colleges!Y6>=0.4,CHOOSE(W12+2,"Reach","Target","Likely"),IF(W12=1,"Target","Reach"))))))) -> Reach | F12: =IF(OR(B12="",NOT(ISNUMBER(DB_Colleges!Y6))),"",DB_Colleges!Y6) -> 0.7 | G12: =IF(OR(B12="",NOT(ISNUMBER(DB_Colleges!Z6))),"",DB_Colleges!Z6&"-"&DB_Colleges!AA6) -> 940-1130 | H12: =IF(OR(B12="",NOT(ISNUMBER(DB_Colleges!AD6))),"",DB_Colleges!AD6) | I12: =IF(B12="","",IF(COUNT(DB_Colleges!I6:O6)=0,IF(DB_Colleges!P6="Yes","Rolling","Check site"),MIN(DB_Colleges!I6:O6))) -> 46600 | J12: =IF(OR(B12="",COUNT(DB_Colleges!I6:O6)=0),"",INDEX({"ED","ED II","EA","EA II","REA","RD","Priority"},MATCH(MIN(DB_Colleges!I6:O6),DB_Colleges!I6:O6,0))) -> RD | K12: =IF(OR(B12="",NOT(ISNUMBER(DB_Colleges!N6))),"",DB_Colleges!N6) -> 46600 | L12: =IF(B12="","",DB_Colleges!G6&"") -> Common App; School portal | M12: =IF(OR(B12="",NOT(ISNUMBER(DB_Colleges!S6))),"",DB_Colleges!S6) -> 30 | N12: =IF(B12="","",DB_Colleges!U6&"") -> Required | O12: =IF(B12="","",IF(ISNUMBER(DB_Colleges!AH6),DB_Colleges!AH6,"Check")) -> Check | P12: =IF(B12="","",DB_Colleges!W6&"") -> Not required | Q12: =IF(OR(B12="",NOT(ISNUMBER(DB_Colleges!AF6))),"",DB_Colleges!AF6) | R12: =IF(OR(B12="",NOT(ISNUMBER(DB_Colleges!AG6))),"",DB_Colleges!AG6) | S12: =IF(B12="","",DB_Colleges!AK6&"") -> Mixed | T12: =IF(B12="","",DB_Colleges!AI6&"") -> https://www.georgiasouthern.edu/admissions-aid/first-year-students | U12: =IF(AND(ISNUMBER($X$4),ISNUMBER(DB_Colleges!Z6),ISNUMBER(DB_Colleges!AA6)),IF($X$4>=DB_Colleges!AA6,1,IF($X$4<DB_Colleges!Z6,-1,0)),"") -> -1 | V12: =IF(AND(ISNUMBER($Y$4),ISNUMBER(DB_Colleges!AD6)),IF($Y$4>=DB_Colleges!AD6+0.15,1,IF($Y$4<DB_Colleges!AD6-0.2,-1,0)),"") | W12: =IF(COUNT(U12:V12)=0,0,MIN(U12:V12)) -> -1
A13: =IF(B13="","",IF(COUNTIF('My Colleges'!$B$8:$B$27,B13)>0,"On list","")) | B13: =IF(DB_Colleges!A7="","",DB_Colleges!A7) -> Augusta University | C13: =IF(B13="","",DB_Colleges!B7) -> Georgia Public (USG) | D13: =IF(B13="","",DB_Colleges!C7&", "&DB_Colleges!D7) -> Augusta, GA | E13: =IF(B13="","",IF(AND(NOT(ISNUMBER($X$4)),NOT(ISNUMBER($Y$4))),"Add scores",IF(NOT(ISNUMBER(DB_Colleges!Y7)),IF(OR(C13="Ivy League",C13="Highly Selective"),"Reach",IF(COUNT(U13:V13)=0,"No data",CHOOSE(W13+2,"Reach","Target","Likely"))),IF(DB_Colleges!Y7<0.15,"Reach",IF(DB_Colleges!Y7>=0.75,IF(W13>=0,"Likely","Target"),IF(DB_Colleges!Y7>=0.4,CHOOSE(W13+2,"Reach","Target","Likely"),IF(W13=1,"Target","Reach"))))))) -> Reach | F13: =IF(OR(B13="",NOT(ISNUMBER(DB_Colleges!Y7))),"",DB_Colleges!Y7) | G13: =IF(OR(B13="",NOT(ISNUMBER(DB_Colleges!Z7))),"",DB_Colleges!Z7&"-"&DB_Colleges!AA7) -> 970-1140 | H13: =IF(OR(B13="",NOT(ISNUMBER(DB_Colleges!AD7))),"",DB_Colleges!AD7) | I13: =IF(B13="","",IF(COUNT(DB_Colleges!I7:O7)=0,IF(DB_Colleges!P7="Yes","Rolling","Check site"),MIN(DB_Colleges!I7:O7))) -> 46326 | J13: =IF(OR(B13="",COUNT(DB_Colleges!I7:O7)=0),"",INDEX({"ED","ED II","EA","EA II","REA","RD","Priority"},MATCH(MIN(DB_Colleges!I7:O7),DB_Colleges!I7:O7,0))) -> EA | K13: =IF(OR(B13="",NOT(ISNUMBER(DB_Colleges!N7))),"",DB_Colleges!N7) -> 46569 | L13: =IF(B13="","",DB_Colleges!G7&"") -> Common App | M13: =IF(OR(B13="",NOT(ISNUMBER(DB_Colleges!S7))),"",DB_Colleges!S7) -> 60 | N13: =IF(B13="","",DB_Colleges!U7&"") -> Required | O13: =IF(B13="","",IF(ISNUMBER(DB_Colleges!AH7),DB_Colleges!AH7,"Check")) -> Check | P13: =IF(B13="","",DB_Colleges!W7&"") -> Not required | Q13: =IF(OR(B13="",NOT(ISNUMBER(DB_Colleges!AF7))),"",DB_Colleges!AF7) | R13: =IF(OR(B13="",NOT(ISNUMBER(DB_Colleges!AG7))),"",DB_Colleges!AG7) | S13: =IF(B13="","",DB_Colleges!AK7&"") -> Mixed | T13: =IF(B13="","",DB_Colleges!AI7&"") -> https://www.augusta.edu/admissions/freshman.php | U13: =IF(AND(ISNUMBER($X$4),ISNUMBER(DB_Colleges!Z7),ISNUMBER(DB_Colleges!AA7)),IF($X$4>=DB_Colleges!AA7,1,IF($X$4<DB_Colleges!Z7,-1,0)),"") -> -1 | V13: =IF(AND(ISNUMBER($Y$4),ISNUMBER(DB_Colleges!AD7)),IF($Y$4>=DB_Colleges!AD7+0.15,1,IF($Y$4<DB_Colleges!AD7-0.2,-1,0)),"") | W13: =IF(COUNT(U13:V13)=0,0,MIN(U13:V13)) -> -1
A14: =IF(B14="","",IF(COUNTIF('My Colleges'!$B$8:$B$27,B14)>0,"On list","")) | B14: =IF(DB_Colleges!A8="","",DB_Colleges!A8) -> Valdosta State University | C14: =IF(B14="","",DB_Colleges!B8) -> Georgia Public (USG) | D14: =IF(B14="","",DB_Colleges!C8&", "&DB_Colleges!D8) -> Valdosta, GA | E14: =IF(B14="","",IF(AND(NOT(ISNUMBER($X$4)),NOT(ISNUMBER($Y$4))),"Add scores",IF(NOT(ISNUMBER(DB_Colleges!Y8)),IF(OR(C14="Ivy League",C14="Highly Selective"),"Reach",IF(COUNT(U14:V14)=0,"No data",CHOOSE(W14+2,"Reach","Target","Likely"))),IF(DB_Colleges!Y8<0.15,"Reach",IF(DB_Colleges!Y8>=0.75,IF(W14>=0,"Likely","Target"),IF(DB_Colleges!Y8>=0.4,CHOOSE(W14+2,"Reach","Target","Likely"),IF(W14=1,"Target","Reach"))))))) -> Target | F14: =IF(OR(B14="",NOT(ISNUMBER(DB_Colleges!Y8))),"",DB_Colleges!Y8) -> 0.78 | G14: =IF(OR(B14="",NOT(ISNUMBER(DB_Colleges!Z8))),"",DB_Colleges!Z8&"-"&DB_Colleges!AA8) -> 920-1110 | H14: =IF(OR(B14="",NOT(ISNUMBER(DB_Colleges!AD8))),"",DB_Colleges!AD8) | I14: =IF(B14="","",IF(COUNT(DB_Colleges!I8:O8)=0,IF(DB_Colleges!P8="Yes","Rolling","Check site"),MIN(DB_Colleges!I8:O8))) -> Rolling | J14: =IF(OR(B14="",COUNT(DB_Colleges!I8:O8)=0),"",INDEX({"ED","ED II","EA","EA II","REA","RD","Priority"},MATCH(MIN(DB_Colleges!I8:O8),DB_Colleges!I8:O8,0))) | K14: =IF(OR(B14="",NOT(ISNUMBER(DB_Colleges!N8))),"",DB_Colleges!N8) | L14: =IF(B14="","",DB_Colleges!G8&"") -> School portal | M14: =IF(OR(B14="",NOT(ISNUMBER(DB_Colleges!S8))),"",DB_Colleges!S8) | N14: =IF(B14="","",DB_Colleges!U8&"") -> Optional | O14: =IF(B14="","",IF(ISNUMBER(DB_Colleges!AH8),DB_Colleges!AH8,"Check")) -> Check | P14: =IF(B14="","",DB_Colleges!W8&"") -> Not required | Q14: =IF(OR(B14="",NOT(ISNUMBER(DB_Colleges!AF8))),"",DB_Colleges!AF8) | R14: =IF(OR(B14="",NOT(ISNUMBER(DB_Colleges!AG8))),"",DB_Colleges!AG8) | S14: =IF(B14="","",DB_Colleges!AK8&"") -> Mixed | T14: =IF(B14="","",DB_Colleges!AI8&"") -> https://www.valdosta.edu/admissions/undergraduate/dates-and-events.php | U14: =IF(AND(ISNUMBER($X$4),ISNUMBER(DB_Colleges!Z8),ISNUMBER(DB_Colleges!AA8)),IF($X$4>=DB_Colleges!AA8,1,IF($X$4<DB_Colleges!Z8,-1,0)),"") -> -1 | V14: =IF(AND(ISNUMBER($Y$4),ISNUMBER(DB_Colleges!AD8)),IF($Y$4>=DB_Colleges!AD8+0.15,1,IF($Y$4<DB_Colleges!AD8-0.2,-1,0)),"") | W14: =IF(COUNT(U14:V14)=0,0,MIN(U14:V14)) -> -1
A15: =IF(B15="","",IF(COUNTIF('My Colleges'!$B$8:$B$27,B15)>0,"On list","")) | B15: =IF(DB_Colleges!A9="","",DB_Colleges!A9) -> University of West Georgia | C15: =IF(B15="","",DB_Colleges!B9) -> Georgia Public (USG) | D15: =IF(B15="","",DB_Colleges!C9&", "&DB_Colleges!D9) -> Carrollton, GA | E15: =IF(B15="","",IF(AND(NOT(ISNUMBER($X$4)),NOT(ISNUMBER($Y$4))),"Add scores",IF(NOT(ISNUMBER(DB_Colleges!Y9)),IF(OR(C15="Ivy League",C15="Highly Selective"),"Reach",IF(COUNT(U15:V15)=0,"No data",CHOOSE(W15+2,"Reach","Target","Likely"))),IF(DB_Colleges!Y9<0.15,"Reach",IF(DB_Colleges!Y9>=0.75,IF(W15>=0,"Likely","Target"),IF(DB_Colleges!Y9>=0.4,CHOOSE(W15+2,"Reach","Target","Likely"),IF(W15=1,"Target","Reach"))))))) -> Target | F15: =IF(OR(B15="",NOT(ISNUMBER(DB_Colleges!Y9))),"",DB_Colleges!Y9) -> 0.8 | G15: =IF(OR(B15="",NOT(ISNUMBER(DB_Colleges!Z9))),"",DB_Colleges!Z9&"-"&DB_Colleges!AA9) -> 930-1150 | H15: =IF(OR(B15="",NOT(ISNUMBER(DB_Colleges!AD9))),"",DB_Colleges!AD9) | I15: =IF(B15="","",IF(COUNT(DB_Colleges!I9:O9)=0,IF(DB_Colleges!P9="Yes","Rolling","Check site"),MIN(DB_Colleges!I9:O9))) -> 46326 | J15: =IF(OR(B15="",COUNT(DB_Colleges!I9:O9)=0),"",INDEX({"ED","ED II","EA","EA II","REA","RD","Priority"},MATCH(MIN(DB_Colleges!I9:O9),DB_Colleges!I9:O9,0))) -> EA | K15: =IF(OR(B15="",NOT(ISNUMBER(DB_Colleges!N9))),"",DB_Colleges!N9) -> 46607 | L15: =IF(B15="","",DB_Colleges!G9&"") -> School portal | M15: =IF(OR(B15="",NOT(ISNUMBER(DB_Colleges!S9))),"",DB_Colleges!S9) -> 40 | N15: =IF(B15="","",DB_Colleges!U9&"") -> Flexible | O15: =IF(B15="","",IF(ISNUMBER(DB_Colleges!AH9),DB_Colleges!AH9,"Check")) -> Check | P15: =IF(B15="","",DB_Colleges!W9&"") -> Not required | Q15: =IF(OR(B15="",NOT(ISNUMBER(DB_Colleges!AF9))),"",DB_Colleges!AF9) | R15: =IF(OR(B15="",NOT(ISNUMBER(DB_Colleges!AG9))),"",DB_Colleges!AG9) | S15: =IF(B15="","",DB_Colleges!AK9&"") -> Mixed | T15: =IF(B15="","",DB_Colleges!AI9&"") -> https://www.westga.edu/undergraduate-admissions/dates-deadlines.php | U15: =IF(AND(ISNUMBER($X$4),ISNUMBER(DB_Colleges!Z9),ISNUMBER(DB_Colleges!AA9)),IF($X$4>=DB_Colleges!AA9,1,IF($X$4<DB_Colleges!Z9,-1,0)),"") -> -1 | V15: =IF(AND(ISNUMBER($Y$4),ISNUMBER(DB_Colleges!AD9)),IF($Y$4>=DB_Colleges!AD9+0.15,1,IF($Y$4<DB_Colleges!AD9-0.2,-1,0)),"") | W15: =IF(COUNT(U15:V15)=0,0,MIN(U15:V15)) -> -1
A16: =IF(B16="","",IF(COUNTIF('My Colleges'!$B$8:$B$27,B16)>0,"On list","")) | B16: =IF(DB_Colleges!A10="","",DB_Colleges!A10) -> Georgia College & State University | C16: =IF(B16="","",DB_Colleges!B10) -> Georgia Public (USG) | D16: =IF(B16="","",DB_Colleges!C10&", "&DB_Colleges!D10) -> Milledgeville, GA | E16: =IF(B16="","",IF(AND(NOT(ISNUMBER($X$4)),NOT(ISNUMBER($Y$4))),"Add scores",IF(NOT(ISNUMBER(DB_Colleges!Y10)),IF(OR(C16="Ivy League",C16="Highly Selective"),"Reach",IF(COUNT(U16:V16)=0,"No data",CHOOSE(W16+2,"Reach","Target","Likely"))),IF(DB_Colleges!Y10<0.15,"Reach",IF(DB_Colleges!Y10>=0.75,IF(W16>=0,"Likely","Target"),IF(DB_Colleges!Y10>=0.4,CHOOSE(W16+2,"Reach","Target","Likely"),IF(W16=1,"Target","Reach"))))))) -> Target | F16: =IF(OR(B16="",NOT(ISNUMBER(DB_Colleges!Y10))),"",DB_Colleges!Y10) -> 0.85 | G16: =IF(OR(B16="",NOT(ISNUMBER(DB_Colleges!Z10))),"",DB_Colleges!Z10&"-"&DB_Colleges!AA10) -> 1110-1270 | H16: =IF(OR(B16="",NOT(ISNUMBER(DB_Colleges!AD10))),"",DB_Colleges!AD10) | I16: =IF(B16="","",IF(COUNT(DB_Colleges!I10:O10)=0,IF(DB_Colleges!P10="Yes","Rolling","Check site"),MIN(DB_Colleges!I10:O10))) -> 46310 | J16: =IF(OR(B16="",COUNT(DB_Colleges!I10:O10)=0),"",INDEX({"ED","ED II","EA","EA II","REA","RD","Priority"},MATCH(MIN(DB_Colleges!I10:O10),DB_Colleges!I10:O10,0))) -> EA | K16: =IF(OR(B16="",NOT(ISNUMBER(DB_Colleges!N10))),"",DB_Colleges!N10) | L16: =IF(B16="","",DB_Colleges!G10&"") -> Common App | M16: =IF(OR(B16="",NOT(ISNUMBER(DB_Colleges!S10))),"",DB_Colleges!S10) -> 50 | N16: =IF(B16="","",DB_Colleges!U10&"") -> Required | O16: =IF(B16="","",IF(ISNUMBER(DB_Colleges!AH10),DB_Colleges!AH10,"Check")) -> Check | P16: =IF(B16="","",DB_Colleges!W10&"") -> Not required | Q16: =IF(OR(B16="",NOT(ISNUMBER(DB_Colleges!AF10))),"",DB_Colleges!AF10) | R16: =IF(OR(B16="",NOT(ISNUMBER(DB_Colleges!AG10))),"",DB_Colleges!AG10) | S16: =IF(B16="","",DB_Colleges!AK10&"") -> Mixed | T16: =IF(B16="","",DB_Colleges!AI10&"") -> https://www.gcsu.edu/admissions/first-year | U16: =IF(AND(ISNUMBER($X$4),ISNUMBER(DB_Colleges!Z10),ISNUMBER(DB_Colleges!AA10)),IF($X$4>=DB_Colleges!AA10,1,IF($X$4<DB_Colleges!Z10,-1,0)),"") -> -1 | V16: =IF(AND(ISNUMBER($Y$4),ISNUMBER(DB_Colleges!AD10)),IF($Y$4>=DB_Colleges!AD10+0.15,1,IF($Y$4<DB_Colleges!AD10-0.2,-1,0)),"") | W16: =IF(COUNT(U16:V16)=0,0,MIN(U16:V16)) -> -1
A17: =IF(B17="","",IF(COUNTIF('My Colleges'!$B$8:$B$27,B17)>0,"On list","")) | B17: =IF(DB_Colleges!A11="","",DB_Colleges!A11) -> Columbus State University | C17: =IF(B17="","",DB_Colleges!B11) -> Georgia Public (USG) | D17: =IF(B17="","",DB_Colleges!C11&", "&DB_Colleges!D11) -> Columbus, GA | E17: =IF(B17="","",IF(AND(NOT(ISNUMBER($X$4)),NOT(ISNUMBER($Y$4))),"Add scores",IF(NOT(ISNUMBER(DB_Colleges!Y11)),IF(OR(C17="Ivy League",C17="Highly Selective"),"Reach",IF(COUNT(U17:V17)=0,"No data",CHOOSE(W17+2,"Reach","Target","Likely"))),IF(DB_Colleges!Y11<0.15,"Reach",IF(DB_Colleges!Y11>=0.75,IF(W17>=0,"Likely","Target"),IF(DB_Colleges!Y11>=0.4,CHOOSE(W17+2,"Reach","Target","Likely"),IF(W17=1,"Target","Reach"))))))) -> Likely | F17: =IF(OR(B17="",NOT(ISNUMBER(DB_Colleges!Y11))),"",DB_Colleges!Y11) -> 0.99 | G17: =IF(OR(B17="",NOT(ISNUMBER(DB_Colleges!Z11))),"",DB_Colleges!Z11&"-"&DB_Colleges!AA11) -> 800-1060 | H17: =IF(OR(B17="",NOT(ISNUMBER(DB_Colleges!AD11))),"",DB_Colleges!AD11) | I17: =IF(B17="","",IF(COUNT(DB_Colleges!I11:O11)=0,IF(DB_Colleges!P11="Yes","Rolling","Check site"),MIN(DB_Colleges!I11:O11))) -> 46492 | J17: =IF(OR(B17="",COUNT(DB_Colleges!I11:O11)=0),"",INDEX({"ED","ED II","EA","EA II","REA","RD","Priority"},MATCH(MIN(DB_Colleges!I11:O11),DB_Colleges!I11:O11,0))) -> Priority | K17: =IF(OR(B17="",NOT(ISNUMBER(DB_Colleges!N11))),"",DB_Colleges!N11) -> 46568 | L17: =IF(B17="","",DB_Colleges!G11&"") -> School portal | M17: =IF(OR(B17="",NOT(ISNUMBER(DB_Colleges!S11))),"",DB_Colleges!S11) -> 40 | N17: =IF(B17="","",DB_Colleges!U11&"") -> Required | O17: =IF(B17="","",IF(ISNUMBER(DB_Colleges!AH11),DB_Colleges!AH11,"Check")) -> Check | P17: =IF(B17="","",DB_Colleges!W11&"") -> Not required | Q17: =IF(OR(B17="",NOT(ISNUMBER(DB_Colleges!AF11))),"",DB_Colleges!AF11) | R17: =IF(OR(B17="",NOT(ISNUMBER(DB_Colleges!AG11))),"",DB_Colleges!AG11) | S17: =IF(B17="","",DB_Colleges!AK11&"") -> Mixed | T17: =IF(B17="","",DB_Colleges!AI11&"") -> https://www.columbusstate.edu/admissions/undergraduate/first-time-freshmen.php | U17: =IF(AND(ISNUMBER($X$4),ISNUMBER(DB_Colleges!Z11),ISNUMBER(DB_Colleges!AA11)),IF($X$4>=DB_Colleges!AA11,1,IF($X$4<DB_Colleges!Z11,-1,0)),"") -> 0 | V17: =IF(AND(ISNUMBER($Y$4),ISNUMBER(DB_Colleges!AD11)),IF($Y$4>=DB_Colleges!AD11+0.15,1,IF($Y$4<DB_Colleges!AD11-0.2,-1,0)),"") | W17: =IF(COUNT(U17:V17)=0,0,MIN(U17:V17)) -> 0
A18: =IF(B18="","",IF(COUNTIF('My Colleges'!$B$8:$B$27,B18)>0,"On list","")) | B18: =IF(DB_Colleges!A12="","",DB_Colleges!A12) -> Georgia Southwestern State University | C18: =IF(B18="","",DB_Colleges!B12) -> Georgia Public (USG) | D18: =IF(B18="","",DB_Colleges!C12&", "&DB_Colleges!D12) -> Americus, GA | E18: =IF(B18="","",IF(AND(NOT(ISNUMBER($X$4)),NOT(ISNUMBER($Y$4))),"Add scores",IF(NOT(ISNUMBER(DB_Colleges!Y12)),IF(OR(C18="Ivy League",C18="Highly Selective"),"Reach",IF(COUNT(U18:V18)=0,"No data",CHOOSE(W18+2,"Reach","Target","Likely"))),IF(DB_Colleges!Y12<0.15,"Reach",IF(DB_Colleges!Y12>=0.75,IF(W18>=0,"Likely","Target"),IF(DB_Colleges!Y12>=0.4,CHOOSE(W18+2,"Reach","Target","Likely"),IF(W18=1,"Target","Reach"))))))) -> Target | F18: =IF(OR(B18="",NOT(ISNUMBER(DB_Colleges!Y12))),"",DB_Colleges!Y12) -> 0.75 | G18: =IF(OR(B18="",NOT(ISNUMBER(DB_Colleges!Z12))),"",DB_Colleges!Z12&"-"&DB_Colleges!AA12) -> 890-1110 | H18: =IF(OR(B18="",NOT(ISNUMBER(DB_Colleges!AD12))),"",DB_Colleges!AD12) | I18: =IF(B18="","",IF(COUNT(DB_Colleges!I12:O12)=0,IF(DB_Colleges!P12="Yes","Rolling","Check site"),MIN(DB_Colleges!I12:O12))) -> Rolling | J18: =IF(OR(B18="",COUNT(DB_Colleges!I12:O12)=0),"",INDEX({"ED","ED II","EA","EA II","REA","RD","Priority"},MATCH(MIN(DB_Colleges!I12:O12),DB_Colleges!I12:O12,0))) | K18: =IF(OR(B18="",NOT(ISNUMBER(DB_Colleges!N12))),"",DB_Colleges!N12) | L18: =IF(B18="","",DB_Colleges!G12&"") -> GAfutures; School portal | M18: =IF(OR(B18="",NOT(ISNUMBER(DB_Colleges!S12))),"",DB_Colleges!S12) | N18: =IF(B18="","",DB_Colleges!U12&"") -> Optional | O18: =IF(B18="","",IF(ISNUMBER(DB_Colleges!AH12),DB_Colleges!AH12,"Check")) -> Check | P18: =IF(B18="","",DB_Colleges!W12&"") -> Not required | Q18: =IF(OR(B18="",NOT(ISNUMBER(DB_Colleges!AF12))),"",DB_Colleges!AF12) | R18: =IF(OR(B18="",NOT(ISNUMBER(DB_Colleges!AG12))),"",DB_Colleges!AG12) | S18: =IF(B18="","",DB_Colleges!AK12&"") -> Mixed | T18: =IF(B18="","",DB_Colleges!AI12&"") -> https://www.gsw.edu/admissions/undergraduate/freshman | U18: =IF(AND(ISNUMBER($X$4),ISNUMBER(DB_Colleges!Z12),ISNUMBER(DB_Colleges!AA12)),IF($X$4>=DB_Colleges!AA12,1,IF($X$4<DB_Colleges!Z12,-1,0)),"") -> -1 | V18: =IF(AND(ISNUMBER($Y$4),ISNUMBER(DB_Colleges!AD12)),IF($Y$4>=DB_Colleges!AD12+0.15,1,IF($Y$4<DB_Colleges!AD12-0.2,-1,0)),"") | W18: =IF(COUNT(U18:V18)=0,0,MIN(U18:V18)) -> -1
A19: =IF(B19="","",IF(COUNTIF('My Colleges'!$B$8:$B$27,B19)>0,"On list","")) | B19: =IF(DB_Colleges!A13="","",DB_Colleges!A13) -> Clayton State University | C19: =IF(B19="","",DB_Colleges!B13) -> Georgia Public (USG) | D19: =IF(B19="","",DB_Colleges!C13&", "&DB_Colleges!D13) -> Morrow, GA | E19: =IF(B19="","",IF(AND(NOT(ISNUMBER($X$4)),NOT(ISNUMBER($Y$4))),"Add scores",IF(NOT(ISNUMBER(DB_Colleges!Y13)),IF(OR(C19="Ivy League",C19="Highly Selective"),"Reach",IF(COUNT(U19:V19)=0,"No data",CHOOSE(W19+2,"Reach","Target","Likely"))),IF(DB_Colleges!Y13<0.15,"Reach",IF(DB_Colleges!Y13>=0.75,IF(W19>=0,"Likely","Target"),IF(DB_Colleges!Y13>=0.4,CHOOSE(W19+2,"Reach","Target","Likely"),IF(W19=1,"Target","Reach"))))))) -> Reach | F19: =IF(OR(B19="",NOT(ISNUMBER(DB_Colleges!Y13))),"",DB_Colleges!Y13) -> 0.68 | G19: =IF(OR(B19="",NOT(ISNUMBER(DB_Colleges!Z13))),"",DB_Colleges!Z13&"-"&DB_Colleges!AA13) -> 860-1078 | H19: =IF(OR(B19="",NOT(ISNUMBER(DB_Colleges!AD13))),"",DB_Colleges!AD13) | I19: =IF(B19="","",IF(COUNT(DB_Colleges!I13:O13)=0,IF(DB_Colleges!P13="Yes","Rolling","Check site"),MIN(DB_Colleges!I13:O13))) -> Rolling | J19: =IF(OR(B19="",COUNT(DB_Colleges!I13:O13)=0),"",INDEX({"ED","ED II","EA","EA II","REA","RD","Priority"},MATCH(MIN(DB_Colleges!I13:O13),DB_Colleges!I13:O13,0))) | K19: =IF(OR(B19="",NOT(ISNUMBER(DB_Colleges!N13))),"",DB_Colleges!N13) | L19: =IF(B19="","",DB_Colleges!G13&"") -> Common App; School portal | M19: =IF(OR(B19="",NOT(ISNUMBER(DB_Colleges!S13))),"",DB_Colleges!S13) -> 40 | N19: =IF(B19="","",DB_Colleges!U13&"") -> Optional | O19: =IF(B19="","",IF(ISNUMBER(DB_Colleges!AH13),DB_Colleges!AH13,"Check")) -> Check | P19: =IF(B19="","",DB_Colleges!W13&"") -> Not required | Q19: =IF(OR(B19="",NOT(ISNUMBER(DB_Colleges!AF13))),"",DB_Colleges!AF13) | R19: =IF(OR(B19="",NOT(ISNUMBER(DB_Colleges!AG13))),"",DB_Colleges!AG13) | S19: =IF(B19="","",DB_Colleges!AK13&"") -> Aggregator only | T19: =IF(B19="","",DB_Colleges!AI13&"") -> https://www.clayton.edu/admissions/undergrad/freshman.php | U19: =IF(AND(ISNUMBER($X$4),ISNUMBER(DB_Colleges!Z13),ISNUMBER(DB_Colleges!AA13)),IF($X$4>=DB_Colleges!AA13,1,IF($X$4<DB_Colleges!Z13,-1,0)),"") -> -1 | V19: =IF(AND(ISNUMBER($Y$4),ISNUMBER(DB_Colleges!AD13)),IF($Y$4>=DB_Colleges!AD13+0.15,1,IF($Y$4<DB_Colleges!AD13-0.2,-1,0)),"") | W19: =IF(COUNT(U19:V19)=0,0,MIN(U19:V19)) -> -1
... A406: =IF(B406="","",IF(COUNTIF('My Colleges'!$B$8:$B$27,B406)>0,"On list","")) | B406: =IF(DB_Colleges!A400="","",DB_Colleges!A400) | C406: =IF(B406="","",DB_Colleges!B400) | D406: =IF(B406="","",DB_Colleges!C400&", "&DB_Colleges!D400) | E406: =IF(B406="","",IF(AND(NOT(ISNUMBER($X$4)),NOT(ISNUMBER($Y$4))),"Add scores",IF(NOT(ISNUMBER(DB_Colleges!Y400)),IF(OR(C406="Ivy League",C406="Highly Selective"),"Reach",IF(COUNT(U406:V406)=0,"No data",CHOOSE(W406+2,"Reach","Target","Likely"))),IF(DB_Colleges!Y400<0.15,"Reach",IF(DB_Colleges!Y400>=0.75,IF(W406>=0,"Likely","Target"),IF(DB_Colleges!Y400>=0.4,CHOOSE(W406+2,"Reach","Target","Likely"),IF(W406=1,"Target","Reach"))))))) | F406: =IF(OR(B406="",NOT(ISNUMBER(DB_Colleges!Y400))),"",DB_Colleges!Y400) | G406: =IF(OR(B406="",NOT(ISNUMBER(DB_Colleges!Z400))),"",DB_Colleges!Z400&"-"&DB_Colleges!AA400) | H406: =IF(OR(B406="",NOT(ISNUMBER(DB_Colleges!AD400))),"",DB_Colleges!AD400) | I406: =IF(B406="","",IF(COUNT(DB_Colleges!I400:O400)=0,IF(DB_Colleges!P400="Yes","Rolling","Check site"),MIN(DB_Colleges!I400:O400))) | J406: =IF(OR(B406="",COUNT(DB_Colleges!I400:O400)=0),"",INDEX({"ED","ED II","EA","EA II","REA","RD","Priority"},MATCH(MIN(DB_Colleges!I400:O400),DB_Colleges!I400:O400,0))) | K406: =IF(OR(B406="",NOT(ISNUMBER(DB_Colleges!N400))),"",DB_Colleges!N400) | L406: =IF(B406="","",DB_Colleges!G400&"") | M406: =IF(OR(B406="",NOT(ISNUMBER(DB_Colleges!S400))),"",DB_Colleges!S400) | N406: =IF(B406="","",DB_Colleges!U400&"") | O406: =IF(B406="","",IF(ISNUMBER(DB_Colleges!AH400),DB_Colleges!AH400,"Check")) | P406: =IF(B406="","",DB_Colleges!W400&"") | Q406: =IF(OR(B406="",NOT(ISNUMBER(DB_Colleges!AF400))),"",DB_Colleges!AF400) | R406: =IF(OR(B406="",NOT(ISNUMBER(DB_Colleges!AG400))),"",DB_Colleges!AG400) | S406: =IF(B406="","",DB_Colleges!AK400&"") | T406: =IF(B406="","",DB_Colleges!AI400&"") | U406: =IF(AND(ISNUMBER($X$4),ISNUMBER(DB_Colleges!Z400),ISNUMBER(DB_Colleges!AA400)),IF($X$4>=DB_Colleges!AA400,1,IF($X$4<DB_Colleges!Z400,-1,0)),"") | V406: =IF(AND(ISNUMBER($Y$4),ISNUMBER(DB_Colleges!AD400)),IF($Y$4>=DB_Colleges!AD400+0.15,1,IF($Y$4<DB_Colleges!AD400-0.2,-1,0)),"") | W406: =IF(COUNT(U406:V406)=0,0,MIN(U406:V406)) -> 0

Sheet My Colleges
A1: My Colleges
A2: Pick each college from the dropdown in column B (or type one that is not listed), then choose your round in column E. Everything gray fills in by itself. Aim for a balanced list: about 2 Likely, 3 to 4 Target, 2 Reach.
B4: Colleges on my list | D4: Likely / Target / Reach | F4: Next filing date | H4: Days until next | I4: Submitted | K4: Admitted | M4: Dates not verified
B5: =COUNTIFS(B8:B27,"?*",V8:V27,"<>No") -> 0 | D5: =COUNTIFS(D8:D27,"Likely",V8:V27,"<>No")&" / "&COUNTIFS(D8:D27,"Target",V8:V27,"<>No")&" / "&COUNTIFS(D8:D27,"Reach",V8:V27,"<>No") -> 0 / 0 / 0 | F5: =IF(COUNTIFS(I8:I27,">="&TODAY(),T8:T27,"<>Submitted",T8:T27,"<>Complete in portal",V8:V27,"<>No")=0,"",_xlfn.MINIFS(I8:I27,I8:I27,">="&TODAY(),T8:T27,"<>Submitted",T8:T27,"<>Complete in portal",V8:V27,"<>No")) | H5: =IF(F5="","",F5-TODAY()) | I5: =COUNTIF(T8:T27,"Submitted")+COUNTIF(T8:T27,"Complete in portal") -> 0 | K5: =COUNTIF(U8:U27,"Admitted") -> 0 | M5: =COUNTIFS(B8:B27,"?*",W8:W27,"<>Yes",V8:V27,"<>No") -> 0
A7: # | B7: College | C7: In Database? | D7: Fit | E7: Round | F7: Deadline for My Round | G7: My Deadline (only if not listed or Rolling) | H7: Scholarship (Merit) Deadline | I7: Effective Filing Date | J7: Days Out | K7: How to Apply | L7: App Fee | M7: Fee Waiver? | N7: Test Policy | O7: Recommendations | P7: Extra Essays | Q7: Steps Done | R7: Next Step | S7: Next Step Due | T7: Status | U7: Decision | V7: On Final List | W7: Deadline Verified | X7: Watch For | Y7: Notes | AA7: m | AB7: css | AC7: interview | AD7: data status | AE7: common app | AF7: platform
A8: 1 | C8: =IF($B8="","",IF(($AA8=0),"No: fill G","Yes")) | D8: =IF(($AA8=0),"",INDEX(Explore!$E$8:$E$406,$AA8)) | F8: =IF($B8="","",IF($E8="","Pick a round",IF($E8="Rolling","Rolling",IF(($AA8=0),"",IF(COUNT(INDEX(DB_Colleges!$I$2:$O$400,$AA8,0))=0,"No date on file",IF(ISNUMBER(INDEX(DB_Colleges!$I$2:$O$400,$AA8,MATCH($E8,{"ED","ED II","EA","EA II","REA","RD","Priority"},0))),INDEX(DB_Colleges!$I$2:$O$400,$AA8,MATCH($E8,{"ED","ED II","EA","EA II","REA","RD","Priority"},0)),"Not offered")))))) | H8: =IF(($AA8=0),"",IF(ISNUMBER(INDEX(DB_Colleges!$Q$2:$Q$400,$AA8)),INDEX(DB_Colleges!$Q$2:$Q$400,$AA8),"")) | I8: =IF($B8="","",IF(ISNUMBER($G8),IF(ISNUMBER($H8),MIN($G8,$H8),$G8),IF(ISNUMBER($F8),IF(ISNUMBER($H8),MIN($F8,$H8),$F8),IF(AND($E8="Rolling",ISNUMBER($H8)),$H8,"")))) | J8: =IF(AND(ISNUMBER($I8),$T8<>"Submitted",$T8<>"Complete in portal"),$I8-TODAY(),"") | K8: =IF(($AA8=0),"",INDEX(DB_Colleges!$G$2:$G$400,$AA8)&"") | L8: =IF(($AA8=0),"",IF(ISNUMBER(INDEX(DB_Colleges!$S$2:$S$400,$AA8)),INDEX(DB_Colleges!$S$2:$S$400,$AA8),"")) | N8: =IF(($AA8=0),"",INDEX(DB_Colleges!$U$2:$U$400,$AA8)&"") | O8: =IF(($AA8=0),"",INDEX(DB_Colleges!$V$2:$V$400,$AA8)&"") | P8: =IF(($AA8=0),"",IF(ISNUMBER(INDEX(DB_Colleges!$AH$2:$AH$400,$AA8)),INDEX(DB_Colleges!$AH$2:$AH$400,$AA8),"Check")) | Q8: =IF($B8="","",'Next Steps'!$AA8&" of "&'Next Steps'!$AB8) | R8: =IF($B8="","",'Next Steps'!$AC8) | S8: =IF($B8="","",'Next Steps'!$AD8) | X8: =IF($B8="","",IF($V8="No","Dropped from your list.",IF(AND(OR($E8="ED",$E8="ED II"),OR(ISNUMBER($F8),ISNUMBER($G8))),"BINDING: if admitted you must attend. ","")&IF(AND(OR($E8="ED",$E8="ED II"),ISNUMBER($F8),SUMPRODUCT((($E$8:$E$27="ED")+($E$8:$E$27="ED II"))*ISNUMBER($F$8:$F$27)*($V$8:$V$27<>"No"))>1),"Only one Early Decision can be active at a time. ","")&IF($E8="REA","Restrictive Early Action: limits other private early applications. ","")&IF(AND(OR($E8="REA",$E8="ED"),ISNUMBER($F8),SUMPRODUCT(($E$8:$E$27="REA")*ISNUMBER($F$8:$F$27)*($V$8:$V$27<>"No"))>0,SUMPRODUCT((($E$8:$E$27="ED")+($E$8:$E$27="ED II"))*ISNUMBER($F$8:$F$27)*($V$8:$V$27<>"No"))>0),"You have Restrictive Early Action and Early Decision at the same time: check the REA college's rules, this is usually not allowed. ","")&IF($F8="Not offered","This college does not offer that round: pick another. ","")&IF(AND($E8="Rolling",NOT(ISNUMBER($G8))),"Rolling: set a target date in column G. ","")&IF(AND(NOT(($AA8=0)),NOT(ISNUMBER($F8)),NOT(ISNUMBER($G8)),$E8<>"",$E8<>"Rolling",$F8<>"Not offered"),"No date on file yet: find it on the college site and type it in column G. ","")&IF(AND(ISNUMBER($H8),ISNUMBER($I8),$H8=$I8,ISNUMBER($F8),$H8<$F8),"Scholarship deadline is earlier than the application deadline, so it is your real deadline. ","")&IF($AE8="No","Not on Common App: apply on "&$AF8&". ","")&IF(($AA8=0),"Not in the database: type the deadline in column G and check requirements on the college site. ","")&IF(AND(NOT(($AA8=0)),$W8<>"Yes",$AD8<>"Official 2026-27"),"Date not yet confirmed: check the college site, then set Deadline Verified to Yes. ","")&IF(LEFT($AB8,8)="Required",IF($AB8="Required","CSS Profile required. ","CSS Profile may be required: check the college's aid page. "),"")&IF($AC8<>"","Interview: "&$AC8&". Watch your email, including spam, and reply the same day. ",""))) | AA8: =IF($B8="",0,IFERROR(MATCH($B8,DB_Colleges!$A$2:$A$400,0),0)) -> 0 | AB8: =IF(($AA8=0),"",INDEX(DB_Colleges!$W$2:$W$400,$AA8)&"") | AC8: =IF(($AA8=0),"",IF(OR(LEFT(INDEX(DB_Colleges!$X$2:$X$400,$AA8)&"",4)="None",LEFT(INDEX(DB_Colleges!$X$2:$X$400,$AA8)&"",3)="No ",LEFT(INDEX(DB_Colleges!$X$2:$X$400,$AA8)&"",3)="Not"),"",INDEX(DB_Colleges!$X$2:$X$400,$AA8)&"")) | AD8: =IF(($AA8=0),"",INDEX(DB_Colleges!$AK$2:$AK$400,$AA8)&"") | AE8: =IF(($AA8=0),"",INDEX(DB_Colleges!$H$2:$H$400,$AA8)&"") | AF8: =IF(($AA8=0),"",INDEX(DB_Colleges!$G$2:$G$400,$AA8)&"")
A9: 2 | C9: =IF($B9="","",IF(($AA9=0),"No: fill G","Yes")) | D9: =IF(($AA9=0),"",INDEX(Explore!$E$8:$E$406,$AA9)) | F9: =IF($B9="","",IF($E9="","Pick a round",IF($E9="Rolling","Rolling",IF(($AA9=0),"",IF(COUNT(INDEX(DB_Colleges!$I$2:$O$400,$AA9,0))=0,"No date on file",IF(ISNUMBER(INDEX(DB_Colleges!$I$2:$O$400,$AA9,MATCH($E9,{"ED","ED II","EA","EA II","REA","RD","Priority"},0))),INDEX(DB_Colleges!$I$2:$O$400,$AA9,MATCH($E9,{"ED","ED II","EA","EA II","REA","RD","Priority"},0)),"Not offered")))))) | H9: =IF(($AA9=0),"",IF(ISNUMBER(INDEX(DB_Colleges!$Q$2:$Q$400,$AA9)),INDEX(DB_Colleges!$Q$2:$Q$400,$AA9),"")) | I9: =IF($B9="","",IF(ISNUMBER($G9),IF(ISNUMBER($H9),MIN($G9,$H9),$G9),IF(ISNUMBER($F9),IF(ISNUMBER($H9),MIN($F9,$H9),$F9),IF(AND($E9="Rolling",ISNUMBER($H9)),$H9,"")))) | J9: =IF(AND(ISNUMBER($I9),$T9<>"Submitted",$T9<>"Complete in portal"),$I9-TODAY(),"") | K9: =IF(($AA9=0),"",INDEX(DB_Colleges!$G$2:$G$400,$AA9)&"") | L9: =IF(($AA9=0),"",IF(ISNUMBER(INDEX(DB_Colleges!$S$2:$S$400,$AA9)),INDEX(DB_Colleges!$S$2:$S$400,$AA9),"")) | N9: =IF(($AA9=0),"",INDEX(DB_Colleges!$U$2:$U$400,$AA9)&"") | O9: =IF(($AA9=0),"",INDEX(DB_Colleges!$V$2:$V$400,$AA9)&"") | P9: =IF(($AA9=0),"",IF(ISNUMBER(INDEX(DB_Colleges!$AH$2:$AH$400,$AA9)),INDEX(DB_Colleges!$AH$2:$AH$400,$AA9),"Check")) | Q9: =IF($B9="","",'Next Steps'!$AA9&" of "&'Next Steps'!$AB9) | R9: =IF($B9="","",'Next Steps'!$AC9) | S9: =IF($B9="","",'Next Steps'!$AD9) | X9: =IF($B9="","",IF($V9="No","Dropped from your list.",IF(AND(OR($E9="ED",$E9="ED II"),OR(ISNUMBER($F9),ISNUMBER($G9))),"BINDING: if admitted you must attend. ","")&IF(AND(OR($E9="ED",$E9="ED II"),ISNUMBER($F9),SUMPRODUCT((($E$8:$E$27="ED")+($E$8:$E$27="ED II"))*ISNUMBER($F$8:$F$27)*($V$8:$V$27<>"No"))>1),"Only one Early Decision can be active at a time. ","")&IF($E9="REA","Restrictive Early Action: limits other private early applications. ","")&IF(AND(OR($E9="REA",$E9="ED"),ISNUMBER($F9),SUMPRODUCT(($E$8:$E$27="REA")*ISNUMBER($F$8:$F$27)*($V$8:$V$27<>"No"))>0,SUMPRODUCT((($E$8:$E$27="ED")+($E$8:$E$27="ED II"))*ISNUMBER($F$8:$F$27)*($V$8:$V$27<>"No"))>0),"You have Restrictive Early Action and Early Decision at the same time: check the REA college's rules, this is usually not allowed. ","")&IF($F9="Not offered","This college does not offer that round: pick another. ","")&IF(AND($E9="Rolling",NOT(ISNUMBER($G9))),"Rolling: set a target date in column G. ","")&IF(AND(NOT(($AA9=0)),NOT(ISNUMBER($F9)),NOT(ISNUMBER($G9)),$E9<>"",$E9<>"Rolling",$F9<>"Not offered"),"No date on file yet: find it on the college site and type it in column G. ","")&IF(AND(ISNUMBER($H9),ISNUMBER($I9),$H9=$I9,ISNUMBER($F9),$H9<$F9),"Scholarship deadline is earlier than the application deadline, so it is your real deadline. ","")&IF($AE9="No","Not on Common App: apply on "&$AF9&". ","")&IF(($AA9=0),"Not in the database: type the deadline in column G and check requirements on the college site. ","")&IF(AND(NOT(($AA9=0)),$W9<>"Yes",$AD9<>"Official 2026-27"),"Date not yet confirmed: check the college site, then set Deadline Verified to Yes. ","")&IF(LEFT($AB9,8)="Required",IF($AB9="Required","CSS Profile required. ","CSS Profile may be required: check the college's aid page. "),"")&IF($AC9<>"","Interview: "&$AC9&". Watch your email, including spam, and reply the same day. ",""))) | AA9: =IF($B9="",0,IFERROR(MATCH($B9,DB_Colleges!$A$2:$A$400,0),0)) -> 0 | AB9: =IF(($AA9=0),"",INDEX(DB_Colleges!$W$2:$W$400,$AA9)&"") | AC9: =IF(($AA9=0),"",IF(OR(LEFT(INDEX(DB_Colleges!$X$2:$X$400,$AA9)&"",4)="None",LEFT(INDEX(DB_Colleges!$X$2:$X$400,$AA9)&"",3)="No ",LEFT(INDEX(DB_Colleges!$X$2:$X$400,$AA9)&"",3)="Not"),"",INDEX(DB_Colleges!$X$2:$X$400,$AA9)&"")) | AD9: =IF(($AA9=0),"",INDEX(DB_Colleges!$AK$2:$AK$400,$AA9)&"") | AE9: =IF(($AA9=0),"",INDEX(DB_Colleges!$H$2:$H$400,$AA9)&"") | AF9: =IF(($AA9=0),"",INDEX(DB_Colleges!$G$2:$G$400,$AA9)&"")
A10: 3 | C10: =IF($B10="","",IF(($AA10=0),"No: fill G","Yes")) | D10: =IF(($AA10=0),"",INDEX(Explore!$E$8:$E$406,$AA10)) | F10: =IF($B10="","",IF($E10="","Pick a round",IF($E10="Rolling","Rolling",IF(($AA10=0),"",IF(COUNT(INDEX(DB_Colleges!$I$2:$O$400,$AA10,0))=0,"No date on file",IF(ISNUMBER(INDEX(DB_Colleges!$I$2:$O$400,$AA10,MATCH($E10,{"ED","ED II","EA","EA II","REA","RD","Priority"},0))),INDEX(DB_Colleges!$I$2:$O$400,$AA10,MATCH($E10,{"ED","ED II","EA","EA II","REA","RD","Priority"},0)),"Not offered")))))) | H10: =IF(($AA10=0),"",IF(ISNUMBER(INDEX(DB_Colleges!$Q$2:$Q$400,$AA10)),INDEX(DB_Colleges!$Q$2:$Q$400,$AA10),"")) | I10: =IF($B10="","",IF(ISNUMBER($G10),IF(ISNUMBER($H10),MIN($G10,$H10),$G10),IF(ISNUMBER($F10),IF(ISNUMBER($H10),MIN($F10,$H10),$F10),IF(AND($E10="Rolling",ISNUMBER($H10)),$H10,"")))) | J10: =IF(AND(ISNUMBER($I10),$T10<>"Submitted",$T10<>"Complete in portal"),$I10-TODAY(),"") | K10: =IF(($AA10=0),"",INDEX(DB_Colleges!$G$2:$G$400,$AA10)&"") | L10: =IF(($AA10=0),"",IF(ISNUMBER(INDEX(DB_Colleges!$S$2:$S$400,$AA10)),INDEX(DB_Colleges!$S$2:$S$400,$AA10),"")) | N10: =IF(($AA10=0),"",INDEX(DB_Colleges!$U$2:$U$400,$AA10)&"") | O10: =IF(($AA10=0),"",INDEX(DB_Colleges!$V$2:$V$400,$AA10)&"") | P10: =IF(($AA10=0),"",IF(ISNUMBER(INDEX(DB_Colleges!$AH$2:$AH$400,$AA10)),INDEX(DB_Colleges!$AH$2:$AH$400,$AA10),"Check")) | Q10: =IF($B10="","",'Next Steps'!$AA10&" of "&'Next Steps'!$AB10) | R10: =IF($B10="","",'Next Steps'!$AC10) | S10: =IF($B10="","",'Next Steps'!$AD10) | X10: =IF($B10="","",IF($V10="No","Dropped from your list.",IF(AND(OR($E10="ED",$E10="ED II"),OR(ISNUMBER($F10),ISNUMBER($G10))),"BINDING: if admitted you must attend. ","")&IF(AND(OR($E10="ED",$E10="ED II"),ISNUMBER($F10),SUMPRODUCT((($E$8:$E$27="ED")+($E$8:$E$27="ED II"))*ISNUMBER($F$8:$F$27)*($V$8:$V$27<>"No"))>1),"Only one Early Decision can be active at a time. ","")&IF($E10="REA","Restrictive Early Action: limits other private early applications. ","")&IF(AND(OR($E10="REA",$E10="ED"),ISNUMBER($F10),SUMPRODUCT(($E$8:$E$27="REA")*ISNUMBER($F$8:$F$27)*($V$8:$V$27<>"No"))>0,SUMPRODUCT((($E$8:$E$27="ED")+($E$8:$E$27="ED II"))*ISNUMBER($F$8:$F$27)*($V$8:$V$27<>"No"))>0),"You have Restrictive Early Action and Early Decision at the same time: check the REA college's rules, this is usually not allowed. ","")&IF($F10="Not offered","This college does not offer that round: pick another. ","")&IF(AND($E10="Rolling",NOT(ISNUMBER($G10))),"Rolling: set a target date in column G. ","")&IF(AND(NOT(($AA10=0)),NOT(ISNUMBER($F10)),NOT(ISNUMBER($G10)),$E10<>"",$E10<>"Rolling",$F10<>"Not offered"),"No date on file yet: find it on the college site and type it in column G. ","")&IF(AND(ISNUMBER($H10),ISNUMBER($I10),$H10=$I10,ISNUMBER($F10),$H10<$F10),"Scholarship deadline is earlier than the application deadline, so it is your real deadline. ","")&IF($AE10="No","Not on Common App: apply on "&$AF10&". ","")&IF(($AA10=0),"Not in the database: type the deadline in column G and check requirements on the college site. ","")&IF(AND(NOT(($AA10=0)),$W10<>"Yes",$AD10<>"Official 2026-27"),"Date not yet confirmed: check the college site, then set Deadline Verified to Yes. ","")&IF(LEFT($AB10,8)="Required",IF($AB10="Required","CSS Profile required. ","CSS Profile may be required: check the college's aid page. "),"")&IF($AC10<>"","Interview: "&$AC10&". Watch your email, including spam, and reply the same day. ",""))) | AA10: =IF($B10="",0,IFERROR(MATCH($B10,DB_Colleges!$A$2:$A$400,0),0)) -> 0 | AB10: =IF(($AA10=0),"",INDEX(DB_Colleges!$W$2:$W$400,$AA10)&"") | AC10: =IF(($AA10=0),"",IF(OR(LEFT(INDEX(DB_Colleges!$X$2:$X$400,$AA10)&"",4)="None",LEFT(INDEX(DB_Colleges!$X$2:$X$400,$AA10)&"",3)="No ",LEFT(INDEX(DB_Colleges!$X$2:$X$400,$AA10)&"",3)="Not"),"",INDEX(DB_Colleges!$X$2:$X$400,$AA10)&"")) | AD10: =IF(($AA10=0),"",INDEX(DB_Colleges!$AK$2:$AK$400,$AA10)&"") | AE10: =IF(($AA10=0),"",INDEX(DB_Colleges!$H$2:$H$400,$AA10)&"") | AF10: =IF(($AA10=0),"",INDEX(DB_Colleges!$G$2:$G$400,$AA10)&"")
A11: 4 | C11: =IF($B11="","",IF(($AA11=0),"No: fill G","Yes")) | D11: =IF(($AA11=0),"",INDEX(Explore!$E$8:$E$406,$AA11)) | F11: =IF($B11="","",IF($E11="","Pick a round",IF($E11="Rolling","Rolling",IF(($AA11=0),"",IF(COUNT(INDEX(DB_Colleges!$I$2:$O$400,$AA11,0))=0,"No date on file",IF(ISNUMBER(INDEX(DB_Colleges!$I$2:$O$400,$AA11,MATCH($E11,{"ED","ED II","EA","EA II","REA","RD","Priority"},0))),INDEX(DB_Colleges!$I$2:$O$400,$AA11,MATCH($E11,{"ED","ED II","EA","EA II","REA","RD","Priority"},0)),"Not offered")))))) | H11: =IF(($AA11=0),"",IF(ISNUMBER(INDEX(DB_Colleges!$Q$2:$Q$400,$AA11)),INDEX(DB_Colleges!$Q$2:$Q$400,$AA11),"")) | I11: =IF($B11="","",IF(ISNUMBER($G11),IF(ISNUMBER($H11),MIN($G11,$H11),$G11),IF(ISNUMBER($F11),IF(ISNUMBER($H11),MIN($F11,$H11),$F11),IF(AND($E11="Rolling",ISNUMBER($H11)),$H11,"")))) | J11: =IF(AND(ISNUMBER($I11),$T11<>"Submitted",$T11<>"Complete in portal"),$I11-TODAY(),"") | K11: =IF(($AA11=0),"",INDEX(DB_Colleges!$G$2:$G$400,$AA11)&"") | L11: =IF(($AA11=0),"",IF(ISNUMBER(INDEX(DB_Colleges!$S$2:$S$400,$AA11)),INDEX(DB_Colleges!$S$2:$S$400,$AA11),"")) | N11: =IF(($AA11=0),"",INDEX(DB_Colleges!$U$2:$U$400,$AA11)&"") | O11: =IF(($AA11=0),"",INDEX(DB_Colleges!$V$2:$V$400,$AA11)&"") | P11: =IF(($AA11=0),"",IF(ISNUMBER(INDEX(DB_Colleges!$AH$2:$AH$400,$AA11)),INDEX(DB_Colleges!$AH$2:$AH$400,$AA11),"Check")) | Q11: =IF($B11="","",'Next Steps'!$AA11&" of "&'Next Steps'!$AB11) | R11: =IF($B11="","",'Next Steps'!$AC11) | S11: =IF($B11="","",'Next Steps'!$AD11) | X11: =IF($B11="","",IF($V11="No","Dropped from your list.",IF(AND(OR($E11="ED",$E11="ED II"),OR(ISNUMBER($F11),ISNUMBER($G11))),"BINDING: if admitted you must attend. ","")&IF(AND(OR($E11="ED",$E11="ED II"),ISNUMBER($F11),SUMPRODUCT((($E$8:$E$27="ED")+($E$8:$E$27="ED II"))*ISNUMBER($F$8:$F$27)*($V$8:$V$27<>"No"))>1),"Only one Early Decision can be active at a time. ","")&IF($E11="REA","Restrictive Early Action: limits other private early applications. ","")&IF(AND(OR($E11="REA",$E11="ED"),ISNUMBER($F11),SUMPRODUCT(($E$8:$E$27="REA")*ISNUMBER($F$8:$F$27)*($V$8:$V$27<>"No"))>0,SUMPRODUCT((($E$8:$E$27="ED")+($E$8:$E$27="ED II"))*ISNUMBER($F$8:$F$27)*($V$8:$V$27<>"No"))>0),"You have Restrictive Early Action and Early Decision at the same time: check the REA college's rules, this is usually not allowed. ","")&IF($F11="Not offered","This college does not offer that round: pick another. ","")&IF(AND($E11="Rolling",NOT(ISNUMBER($G11))),"Rolling: set a target date in column G. ","")&IF(AND(NOT(($AA11=0)),NOT(ISNUMBER($F11)),NOT(ISNUMBER($G11)),$E11<>"",$E11<>"Rolling",$F11<>"Not offered"),"No date on file yet: find it on the college site and type it in column G. ","")&IF(AND(ISNUMBER($H11),ISNUMBER($I11),$H11=$I11,ISNUMBER($F11),$H11<$F11),"Scholarship deadline is earlier than the application deadline, so it is your real deadline. ","")&IF($AE11="No","Not on Common App: apply on "&$AF11&". ","")&IF(($AA11=0),"Not in the database: type the deadline in column G and check requirements on the college site. ","")&IF(AND(NOT(($AA11=0)),$W11<>"Yes",$AD11<>"Official 2026-27"),"Date not yet confirmed: check the college site, then set Deadline Verified to Yes. ","")&IF(LEFT($AB11,8)="Required",IF($AB11="Required","CSS Profile required. ","CSS Profile may be required: check the college's aid page. "),"")&IF($AC11<>"","Interview: "&$AC11&". Watch your email, including spam, and reply the same day. ",""))) | AA11: =IF($B11="",0,IFERROR(MATCH($B11,DB_Colleges!$A$2:$A$400,0),0)) -> 0 | AB11: =IF(($AA11=0),"",INDEX(DB_Colleges!$W$2:$W$400,$AA11)&"") | AC11: =IF(($AA11=0),"",IF(OR(LEFT(INDEX(DB_Colleges!$X$2:$X$400,$AA11)&"",4)="None",LEFT(INDEX(DB_Colleges!$X$2:$X$400,$AA11)&"",3)="No ",LEFT(INDEX(DB_Colleges!$X$2:$X$400,$AA11)&"",3)="Not"),"",INDEX(DB_Colleges!$X$2:$X$400,$AA11)&"")) | AD11: =IF(($AA11=0),"",INDEX(DB_Colleges!$AK$2:$AK$400,$AA11)&"") | AE11: =IF(($AA11=0),"",INDEX(DB_Colleges!$H$2:$H$400,$AA11)&"") | AF11: =IF(($AA11=0),"",INDEX(DB_Colleges!$G$2:$G$400,$AA11)&"")
A12: 5 | C12: =IF($B12="","",IF(($AA12=0),"No: fill G","Yes")) | D12: =IF(($AA12=0),"",INDEX(Explore!$E$8:$E$406,$AA12)) | F12: =IF($B12="","",IF($E12="","Pick a round",IF($E12="Rolling","Rolling",IF(($AA12=0),"",IF(COUNT(INDEX(DB_Colleges!$I$2:$O$400,$AA12,0))=0,"No date on file",IF(ISNUMBER(INDEX(DB_Colleges!$I$2:$O$400,$AA12,MATCH($E12,{"ED","ED II","EA","EA II","REA","RD","Priority"},0))),INDEX(DB_Colleges!$I$2:$O$400,$AA12,MATCH($E12,{"ED","ED II","EA","EA II","REA","RD","Priority"},0)),"Not offered")))))) | H12: =IF(($AA12=0),"",IF(ISNUMBER(INDEX(DB_Colleges!$Q$2:$Q$400,$AA12)),INDEX(DB_Colleges!$Q$2:$Q$400,$AA12),"")) | I12: =IF($B12="","",IF(ISNUMBER($G12),IF(ISNUMBER($H12),MIN($G12,$H12),$G12),IF(ISNUMBER($F12),IF(ISNUMBER($H12),MIN($F12,$H12),$F12),IF(AND($E12="Rolling",ISNUMBER($H12)),$H12,"")))) | J12: =IF(AND(ISNUMBER($I12),$T12<>"Submitted",$T12<>"Complete in portal"),$I12-TODAY(),"") | K12: =IF(($AA12=0),"",INDEX(DB_Colleges!$G$2:$G$400,$AA12)&"") | L12: =IF(($AA12=0),"",IF(ISNUMBER(INDEX(DB_Colleges!$S$2:$S$400,$AA12)),INDEX(DB_Colleges!$S$2:$S$400,$AA12),"")) | N12: =IF(($AA12=0),"",INDEX(DB_Colleges!$U$2:$U$400,$AA12)&"") | O12: =IF(($AA12=0),"",INDEX(DB_Colleges!$V$2:$V$400,$AA12)&"") | P12: =IF(($AA12=0),"",IF(ISNUMBER(INDEX(DB_Colleges!$AH$2:$AH$400,$AA12)),INDEX(DB_Colleges!$AH$2:$AH$400,$AA12),"Check")) | Q12: =IF($B12="","",'Next Steps'!$AA12&" of "&'Next Steps'!$AB12) | R12: =IF($B12="","",'Next Steps'!$AC12) | S12: =IF($B12="","",'Next Steps'!$AD12) | X12: =IF($B12="","",IF($V12="No","Dropped from your list.",IF(AND(OR($E12="ED",$E12="ED II"),OR(ISNUMBER($F12),ISNUMBER($G12))),"BINDING: if admitted you must attend. ","")&IF(AND(OR($E12="ED",$E12="ED II"),ISNUMBER($F12),SUMPRODUCT((($E$8:$E$27="ED")+($E$8:$E$27="ED II"))*ISNUMBER($F$8:$F$27)*($V$8:$V$27<>"No"))>1),"Only one Early Decision can be active at a time. ","")&IF($E12="REA","Restrictive Early Action: limits other private early applications. ","")&IF(AND(OR($E12="REA",$E12="ED"),ISNUMBER($F12),SUMPRODUCT(($E$8:$E$27="REA")*ISNUMBER($F$8:$F$27)*($V$8:$V$27<>"No"))>0,SUMPRODUCT((($E$8:$E$27="ED")+($E$8:$E$27="ED II"))*ISNUMBER($F$8:$F$27)*($V$8:$V$27<>"No"))>0),"You have Restrictive Early Action and Early Decision at the same time: check the REA college's rules, this is usually not allowed. ","")&IF($F12="Not offered","This college does not offer that round: pick another. ","")&IF(AND($E12="Rolling",NOT(ISNUMBER($G12))),"Rolling: set a target date in column G. ","")&IF(AND(NOT(($AA12=0)),NOT(ISNUMBER($F12)),NOT(ISNUMBER($G12)),$E12<>"",$E12<>"Rolling",$F12<>"Not offered"),"No date on file yet: find it on the college site and type it in column G. ","")&IF(AND(ISNUMBER($H12),ISNUMBER($I12),$H12=$I12,ISNUMBER($F12),$H12<$F12),"Scholarship deadline is earlier than the application deadline, so it is your real deadline. ","")&IF($AE12="No","Not on Common App: apply on "&$AF12&". ","")&IF(($AA12=0),"Not in the database: type the deadline in column G and check requirements on the college site. ","")&IF(AND(NOT(($AA12=0)),$W12<>"Yes",$AD12<>"Official 2026-27"),"Date not yet confirmed: check the college site, then set Deadline Verified to Yes. ","")&IF(LEFT($AB12,8)="Required",IF($AB12="Required","CSS Profile required. ","CSS Profile may be required: check the college's aid page. "),"")&IF($AC12<>"","Interview: "&$AC12&". Watch your email, including spam, and reply the same day. ",""))) | AA12: =IF($B12="",0,IFERROR(MATCH($B12,DB_Colleges!$A$2:$A$400,0),0)) -> 0 | AB12: =IF(($AA12=0),"",INDEX(DB_Colleges!$W$2:$W$400,$AA12)&"") | AC12: =IF(($AA12=0),"",IF(OR(LEFT(INDEX(DB_Colleges!$X$2:$X$400,$AA12)&"",4)="None",LEFT(INDEX(DB_Colleges!$X$2:$X$400,$AA12)&"",3)="No ",LEFT(INDEX(DB_Colleges!$X$2:$X$400,$AA12)&"",3)="Not"),"",INDEX(DB_Colleges!$X$2:$X$400,$AA12)&"")) | AD12: =IF(($AA12=0),"",INDEX(DB_Colleges!$AK$2:$AK$400,$AA12)&"") | AE12: =IF(($AA12=0),"",INDEX(DB_Colleges!$H$2:$H$400,$AA12)&"") | AF12: =IF(($AA12=0),"",INDEX(DB_Colleges!$G$2:$G$400,$AA12)&"")
A13: 6 | C13: =IF($B13="","",IF(($AA13=0),"No: fill G","Yes")) | D13: =IF(($AA13=0),"",INDEX(Explore!$E$8:$E$406,$AA13)) | F13: =IF($B13="","",IF($E13="","Pick a round",IF($E13="Rolling","Rolling",IF(($AA13=0),"",IF(COUNT(INDEX(DB_Colleges!$I$2:$O$400,$AA13,0))=0,"No date on file",IF(ISNUMBER(INDEX(DB_Colleges!$I$2:$O$400,$AA13,MATCH($E13,{"ED","ED II","EA","EA II","REA","RD","Priority"},0))),INDEX(DB_Colleges!$I$2:$O$400,$AA13,MATCH($E13,{"ED","ED II","EA","EA II","REA","RD","Priority"},0)),"Not offered")))))) | H13: =IF(($AA13=0),"",IF(ISNUMBER(INDEX(DB_Colleges!$Q$2:$Q$400,$AA13)),INDEX(DB_Colleges!$Q$2:$Q$400,$AA13),"")) | I13: =IF($B13="","",IF(ISNUMBER($G13),IF(ISNUMBER($H13),MIN($G13,$H13),$G13),IF(ISNUMBER($F13),IF(ISNUMBER($H13),MIN($F13,$H13),$F13),IF(AND($E13="Rolling",ISNUMBER($H13)),$H13,"")))) | J13: =IF(AND(ISNUMBER($I13),$T13<>"Submitted",$T13<>"Complete in portal"),$I13-TODAY(),"") | K13: =IF(($AA13=0),"",INDEX(DB_Colleges!$G$2:$G$400,$AA13)&"") | L13: =IF(($AA13=0),"",IF(ISNUMBER(INDEX(DB_Colleges!$S$2:$S$400,$AA13)),INDEX(DB_Colleges!$S$2:$S$400,$AA13),"")) | N13: =IF(($AA13=0),"",INDEX(DB_Colleges!$U$2:$U$400,$AA13)&"") | O13: =IF(($AA13=0),"",INDEX(DB_Colleges!$V$2:$V$400,$AA13)&"") | P13: =IF(($AA13=0),"",IF(ISNUMBER(INDEX(DB_Colleges!$AH$2:$AH$400,$AA13)),INDEX(DB_Colleges!$AH$2:$AH$400,$AA13),"Check")) | Q13: =IF($B13="","",'Next Steps'!$AA13&" of "&'Next Steps'!$AB13) | R13: =IF($B13="","",'Next Steps'!$AC13) | S13: =IF($B13="","",'Next Steps'!$AD13) | X13: =IF($B13="","",IF($V13="No","Dropped from your list.",IF(AND(OR($E13="ED",$E13="ED II"),OR(ISNUMBER($F13),ISNUMBER($G13))),"BINDING: if admitted you must attend. ","")&IF(AND(OR($E13="ED",$E13="ED II"),ISNUMBER($F13),SUMPRODUCT((($E$8:$E$27="ED")+($E$8:$E$27="ED II"))*ISNUMBER($F$8:$F$27)*($V$8:$V$27<>"No"))>1),"Only one Early Decision can be active at a time. ","")&IF($E13="REA","Restrictive Early Action: limits other private early applications. ","")&IF(AND(OR($E13="REA",$E13="ED"),ISNUMBER($F13),SUMPRODUCT(($E$8:$E$27="REA")*ISNUMBER($F$8:$F$27)*($V$8:$V$27<>"No"))>0,SUMPRODUCT((($E$8:$E$27="ED")+($E$8:$E$27="ED II"))*ISNUMBER($F$8:$F$27)*($V$8:$V$27<>"No"))>0),"You have Restrictive Early Action and Early Decision at the same time: check the REA college's rules, this is usually not allowed. ","")&IF($F13="Not offered","This college does not offer that round: pick another. ","")&IF(AND($E13="Rolling",NOT(ISNUMBER($G13))),"Rolling: set a target date in column G. ","")&IF(AND(NOT(($AA13=0)),NOT(ISNUMBER($F13)),NOT(ISNUMBER($G13)),$E13<>"",$E13<>"Rolling",$F13<>"Not offered"),"No date on file yet: find it on the college site and type it in column G. ","")&IF(AND(ISNUMBER($H13),ISNUMBER($I13),$H13=$I13,ISNUMBER($F13),$H13<$F13),"Scholarship deadline is earlier than the application deadline, so it is your real deadline. ","")&IF($AE13="No","Not on Common App: apply on "&$AF13&". ","")&IF(($AA13=0),"Not in the database: type the deadline in column G and check requirements on the college site. ","")&IF(AND(NOT(($AA13=0)),$W13<>"Yes",$AD13<>"Official 2026-27"),"Date not yet confirmed: check the college site, then set Deadline Verified to Yes. ","")&IF(LEFT($AB13,8)="Required",IF($AB13="Required","CSS Profile required. ","CSS Profile may be required: check the college's aid page. "),"")&IF($AC13<>"","Interview: "&$AC13&". Watch your email, including spam, and reply the same day. ",""))) | AA13: =IF($B13="",0,IFERROR(MATCH($B13,DB_Colleges!$A$2:$A$400,0),0)) -> 0 | AB13: =IF(($AA13=0),"",INDEX(DB_Colleges!$W$2:$W$400,$AA13)&"") | AC13: =IF(($AA13=0),"",IF(OR(LEFT(INDEX(DB_Colleges!$X$2:$X$400,$AA13)&"",4)="None",LEFT(INDEX(DB_Colleges!$X$2:$X$400,$AA13)&"",3)="No ",LEFT(INDEX(DB_Colleges!$X$2:$X$400,$AA13)&"",3)="Not"),"",INDEX(DB_Colleges!$X$2:$X$400,$AA13)&"")) | AD13: =IF(($AA13=0),"",INDEX(DB_Colleges!$AK$2:$AK$400,$AA13)&"") | AE13: =IF(($AA13=0),"",INDEX(DB_Colleges!$H$2:$H$400,$AA13)&"") | AF13: =IF(($AA13=0),"",INDEX(DB_Colleges!$G$2:$G$400,$AA13)&"")
A14: 7 | C14: =IF($B14="","",IF(($AA14=0),"No: fill G","Yes")) | D14: =IF(($AA14=0),"",INDEX(Explore!$E$8:$E$406,$AA14)) | F14: =IF($B14="","",IF($E14="","Pick a round",IF($E14="Rolling","Rolling",IF(($AA14=0),"",IF(COUNT(INDEX(DB_Colleges!$I$2:$O$400,$AA14,0))=0,"No date on file",IF(ISNUMBER(INDEX(DB_Colleges!$I$2:$O$400,$AA14,MATCH($E14,{"ED","ED II","EA","EA II","REA","RD","Priority"},0))),INDEX(DB_Colleges!$I$2:$O$400,$AA14,MATCH($E14,{"ED","ED II","EA","EA II","REA","RD","Priority"},0)),"Not offered")))))) | H14: =IF(($AA14=0),"",IF(ISNUMBER(INDEX(DB_Colleges!$Q$2:$Q$400,$AA14)),INDEX(DB_Colleges!$Q$2:$Q$400,$AA14),"")) | I14: =IF($B14="","",IF(ISNUMBER($G14),IF(ISNUMBER($H14),MIN($G14,$H14),$G14),IF(ISNUMBER($F14),IF(ISNUMBER($H14),MIN($F14,$H14),$F14),IF(AND($E14="Rolling",ISNUMBER($H14)),$H14,"")))) | J14: =IF(AND(ISNUMBER($I14),$T14<>"Submitted",$T14<>"Complete in portal"),$I14-TODAY(),"") | K14: =IF(($AA14=0),"",INDEX(DB_Colleges!$G$2:$G$400,$AA14)&"") | L14: =IF(($AA14=0),"",IF(ISNUMBER(INDEX(DB_Colleges!$S$2:$S$400,$AA14)),INDEX(DB_Colleges!$S$2:$S$400,$AA14),"")) | N14: =IF(($AA14=0),"",INDEX(DB_Colleges!$U$2:$U$400,$AA14)&"") | O14: =IF(($AA14=0),"",INDEX(DB_Colleges!$V$2:$V$400,$AA14)&"") | P14: =IF(($AA14=0),"",IF(ISNUMBER(INDEX(DB_Colleges!$AH$2:$AH$400,$AA14)),INDEX(DB_Colleges!$AH$2:$AH$400,$AA14),"Check")) | Q14: =IF($B14="","",'Next Steps'!$AA14&" of "&'Next Steps'!$AB14) | R14: =IF($B14="","",'Next Steps'!$AC14) | S14: =IF($B14="","",'Next Steps'!$AD14) | X14: =IF($B14="","",IF($V14="No","Dropped from your list.",IF(AND(OR($E14="ED",$E14="ED II"),OR(ISNUMBER($F14),ISNUMBER($G14))),"BINDING: if admitted you must attend. ","")&IF(AND(OR($E14="ED",$E14="ED II"),ISNUMBER($F14),SUMPRODUCT((($E$8:$E$27="ED")+($E$8:$E$27="ED II"))*ISNUMBER($F$8:$F$27)*($V$8:$V$27<>"No"))>1),"Only one Early Decision can be active at a time. ","")&IF($E14="REA","Restrictive Early Action: limits other private early applications. ","")&IF(AND(OR($E14="REA",$E14="ED"),ISNUMBER($F14),SUMPRODUCT(($E$8:$E$27="REA")*ISNUMBER($F$8:$F$27)*($V$8:$V$27<>"No"))>0,SUMPRODUCT((($E$8:$E$27="ED")+($E$8:$E$27="ED II"))*ISNUMBER($F$8:$F$27)*($V$8:$V$27<>"No"))>0),"You have Restrictive Early Action and Early Decision at the same time: check the REA college's rules, this is usually not allowed. ","")&IF($F14="Not offered","This college does not offer that round: pick another. ","")&IF(AND($E14="Rolling",NOT(ISNUMBER($G14))),"Rolling: set a target date in column G. ","")&IF(AND(NOT(($AA14=0)),NOT(ISNUMBER($F14)),NOT(ISNUMBER($G14)),$E14<>"",$E14<>"Rolling",$F14<>"Not offered"),"No date on file yet: find it on the college site and type it in column G. ","")&IF(AND(ISNUMBER($H14),ISNUMBER($I14),$H14=$I14,ISNUMBER($F14),$H14<$F14),"Scholarship deadline is earlier than the application deadline, so it is your real deadline. ","")&IF($AE14="No","Not on Common App: apply on "&$AF14&". ","")&IF(($AA14=0),"Not in the database: type the deadline in column G and check requirements on the college site. ","")&IF(AND(NOT(($AA14=0)),$W14<>"Yes",$AD14<>"Official 2026-27"),"Date not yet confirmed: check the college site, then set Deadline Verified to Yes. ","")&IF(LEFT($AB14,8)="Required",IF($AB14="Required","CSS Profile required. ","CSS Profile may be required: check the college's aid page. "),"")&IF($AC14<>"","Interview: "&$AC14&". Watch your email, including spam, and reply the same day. ",""))) | AA14: =IF($B14="",0,IFERROR(MATCH($B14,DB_Colleges!$A$2:$A$400,0),0)) -> 0 | AB14: =IF(($AA14=0),"",INDEX(DB_Colleges!$W$2:$W$400,$AA14)&"") | AC14: =IF(($AA14=0),"",IF(OR(LEFT(INDEX(DB_Colleges!$X$2:$X$400,$AA14)&"",4)="None",LEFT(INDEX(DB_Colleges!$X$2:$X$400,$AA14)&"",3)="No ",LEFT(INDEX(DB_Colleges!$X$2:$X$400,$AA14)&"",3)="Not"),"",INDEX(DB_Colleges!$X$2:$X$400,$AA14)&"")) | AD14: =IF(($AA14=0),"",INDEX(DB_Colleges!$AK$2:$AK$400,$AA14)&"") | AE14: =IF(($AA14=0),"",INDEX(DB_Colleges!$H$2:$H$400,$AA14)&"") | AF14: =IF(($AA14=0),"",INDEX(DB_Colleges!$G$2:$G$400,$AA14)&"")
A15: 8 | C15: =IF($B15="","",IF(($AA15=0),"No: fill G","Yes")) | D15: =IF(($AA15=0),"",INDEX(Explore!$E$8:$E$406,$AA15)) | F15: =IF($B15="","",IF($E15="","Pick a round",IF($E15="Rolling","Rolling",IF(($AA15=0),"",IF(COUNT(INDEX(DB_Colleges!$I$2:$O$400,$AA15,0))=0,"No date on file",IF(ISNUMBER(INDEX(DB_Colleges!$I$2:$O$400,$AA15,MATCH($E15,{"ED","ED II","EA","EA II","REA","RD","Priority"},0))),INDEX(DB_Colleges!$I$2:$O$400,$AA15,MATCH($E15,{"ED","ED II","EA","EA II","REA","RD","Priority"},0)),"Not offered")))))) | H15: =IF(($AA15=0),"",IF(ISNUMBER(INDEX(DB_Colleges!$Q$2:$Q$400,$AA15)),INDEX(DB_Colleges!$Q$2:$Q$400,$AA15),"")) | I15: =IF($B15="","",IF(ISNUMBER($G15),IF(ISNUMBER($H15),MIN($G15,$H15),$G15),IF(ISNUMBER($F15),IF(ISNUMBER($H15),MIN($F15,$H15),$F15),IF(AND($E15="Rolling",ISNUMBER($H15)),$H15,"")))) | J15: =IF(AND(ISNUMBER($I15),$T15<>"Submitted",$T15<>"Complete in portal"),$I15-TODAY(),"") | K15: =IF(($AA15=0),"",INDEX(DB_Colleges!$G$2:$G$400,$AA15)&"") | L15: =IF(($AA15=0),"",IF(ISNUMBER(INDEX(DB_Colleges!$S$2:$S$400,$AA15)),INDEX(DB_Colleges!$S$2:$S$400,$AA15),"")) | N15: =IF(($AA15=0),"",INDEX(DB_Colleges!$U$2:$U$400,$AA15)&"") | O15: =IF(($AA15=0),"",INDEX(DB_Colleges!$V$2:$V$400,$AA15)&"") | P15: =IF(($AA15=0),"",IF(ISNUMBER(INDEX(DB_Colleges!$AH$2:$AH$400,$AA15)),INDEX(DB_Colleges!$AH$2:$AH$400,$AA15),"Check")) | Q15: =IF($B15="","",'Next Steps'!$AA15&" of "&'Next Steps'!$AB15) | R15: =IF($B15="","",'Next Steps'!$AC15) | S15: =IF($B15="","",'Next Steps'!$AD15) | X15: =IF($B15="","",IF($V15="No","Dropped from your list.",IF(AND(OR($E15="ED",$E15="ED II"),OR(ISNUMBER($F15),ISNUMBER($G15))),"BINDING: if admitted you must attend. ","")&IF(AND(OR($E15="ED",$E15="ED II"),ISNUMBER($F15),SUMPRODUCT((($E$8:$E$27="ED")+($E$8:$E$27="ED II"))*ISNUMBER($F$8:$F$27)*($V$8:$V$27<>"No"))>1),"Only one Early Decision can be active at a time. ","")&IF($E15="REA","Restrictive Early Action: limits other private early applications. ","")&IF(AND(OR($E15="REA",$E15="ED"),ISNUMBER($F15),SUMPRODUCT(($E$8:$E$27="REA")*ISNUMBER($F$8:$F$27)*($V$8:$V$27<>"No"))>0,SUMPRODUCT((($E$8:$E$27="ED")+($E$8:$E$27="ED II"))*ISNUMBER($F$8:$F$27)*($V$8:$V$27<>"No"))>0),"You have Restrictive Early Action and Early Decision at the same time: check the REA college's rules, this is usually not allowed. ","")&IF($F15="Not offered","This college does not offer that round: pick another. ","")&IF(AND($E15="Rolling",NOT(ISNUMBER($G15))),"Rolling: set a target date in column G. ","")&IF(AND(NOT(($AA15=0)),NOT(ISNUMBER($F15)),NOT(ISNUMBER($G15)),$E15<>"",$E15<>"Rolling",$F15<>"Not offered"),"No date on file yet: find it on the college site and type it in column G. ","")&IF(AND(ISNUMBER($H15),ISNUMBER($I15),$H15=$I15,ISNUMBER($F15),$H15<$F15),"Scholarship deadline is earlier than the application deadline, so it is your real deadline. ","")&IF($AE15="No","Not on Common App: apply on "&$AF15&". ","")&IF(($AA15=0),"Not in the database: type the deadline in column G and check requirements on the college site. ","")&IF(AND(NOT(($AA15=0)),$W15<>"Yes",$AD15<>"Official 2026-27"),"Date not yet confirmed: check the college site, then set Deadline Verified to Yes. ","")&IF(LEFT($AB15,8)="Required",IF($AB15="Required","CSS Profile required. ","CSS Profile may be required: check the college's aid page. "),"")&IF($AC15<>"","Interview: "&$AC15&". Watch your email, including spam, and reply the same day. ",""))) | AA15: =IF($B15="",0,IFERROR(MATCH($B15,DB_Colleges!$A$2:$A$400,0),0)) -> 0 | AB15: =IF(($AA15=0),"",INDEX(DB_Colleges!$W$2:$W$400,$AA15)&"") | AC15: =IF(($AA15=0),"",IF(OR(LEFT(INDEX(DB_Colleges!$X$2:$X$400,$AA15)&"",4)="None",LEFT(INDEX(DB_Colleges!$X$2:$X$400,$AA15)&"",3)="No ",LEFT(INDEX(DB_Colleges!$X$2:$X$400,$AA15)&"",3)="Not"),"",INDEX(DB_Colleges!$X$2:$X$400,$AA15)&"")) | AD15: =IF(($AA15=0),"",INDEX(DB_Colleges!$AK$2:$AK$400,$AA15)&"") | AE15: =IF(($AA15=0),"",INDEX(DB_Colleges!$H$2:$H$400,$AA15)&"") | AF15: =IF(($AA15=0),"",INDEX(DB_Colleges!$G$2:$G$400,$AA15)&"")
A16: 9 | C16: =IF($B16="","",IF(($AA16=0),"No: fill G","Yes")) | D16: =IF(($AA16=0),"",INDEX(Explore!$E$8:$E$406,$AA16)) | F16: =IF($B16="","",IF($E16="","Pick a round",IF($E16="Rolling","Rolling",IF(($AA16=0),"",IF(COUNT(INDEX(DB_Colleges!$I$2:$O$400,$AA16,0))=0,"No date on file",IF(ISNUMBER(INDEX(DB_Colleges!$I$2:$O$400,$AA16,MATCH($E16,{"ED","ED II","EA","EA II","REA","RD","Priority"},0))),INDEX(DB_Colleges!$I$2:$O$400,$AA16,MATCH($E16,{"ED","ED II","EA","EA II","REA","RD","Priority"},0)),"Not offered")))))) | H16: =IF(($AA16=0),"",IF(ISNUMBER(INDEX(DB_Colleges!$Q$2:$Q$400,$AA16)),INDEX(DB_Colleges!$Q$2:$Q$400,$AA16),"")) | I16: =IF($B16="","",IF(ISNUMBER($G16),IF(ISNUMBER($H16),MIN($G16,$H16),$G16),IF(ISNUMBER($F16),IF(ISNUMBER($H16),MIN($F16,$H16),$F16),IF(AND($E16="Rolling",ISNUMBER($H16)),$H16,"")))) | J16: =IF(AND(ISNUMBER($I16),$T16<>"Submitted",$T16<>"Complete in portal"),$I16-TODAY(),"") | K16: =IF(($AA16=0),"",INDEX(DB_Colleges!$G$2:$G$400,$AA16)&"") | L16: =IF(($AA16=0),"",IF(ISNUMBER(INDEX(DB_Colleges!$S$2:$S$400,$AA16)),INDEX(DB_Colleges!$S$2:$S$400,$AA16),"")) | N16: =IF(($AA16=0),"",INDEX(DB_Colleges!$U$2:$U$400,$AA16)&"") | O16: =IF(($AA16=0),"",INDEX(DB_Colleges!$V$2:$V$400,$AA16)&"") | P16: =IF(($AA16=0),"",IF(ISNUMBER(INDEX(DB_Colleges!$AH$2:$AH$400,$AA16)),INDEX(DB_Colleges!$AH$2:$AH$400,$AA16),"Check")) | Q16: =IF($B16="","",'Next Steps'!$AA16&" of "&'Next Steps'!$AB16) | R16: =IF($B16="","",'Next Steps'!$AC16) | S16: =IF($B16="","",'Next Steps'!$AD16) | X16: =IF($B16="","",IF($V16="No","Dropped from your list.",IF(AND(OR($E16="ED",$E16="ED II"),OR(ISNUMBER($F16),ISNUMBER($G16))),"BINDING: if admitted you must attend. ","")&IF(AND(OR($E16="ED",$E16="ED II"),ISNUMBER($F16),SUMPRODUCT((($E$8:$E$27="ED")+($E$8:$E$27="ED II"))*ISNUMBER($F$8:$F$27)*($V$8:$V$27<>"No"))>1),"Only one Early Decision can be active at a time. ","")&IF($E16="REA","Restrictive Early Action: limits other private early applications. ","")&IF(AND(OR($E16="REA",$E16="ED"),ISNUMBER($F16),SUMPRODUCT(($E$8:$E$27="REA")*ISNUMBER($F$8:$F$27)*($V$8:$V$27<>"No"))>0,SUMPRODUCT((($E$8:$E$27="ED")+($E$8:$E$27="ED II"))*ISNUMBER($F$8:$F$27)*($V$8:$V$27<>"No"))>0),"You have Restrictive Early Action and Early Decision at the same time: check the REA college's rules, this is usually not allowed. ","")&IF($F16="Not offered","This college does not offer that round: pick another. ","")&IF(AND($E16="Rolling",NOT(ISNUMBER($G16))),"Rolling: set a target date in column G. ","")&IF(AND(NOT(($AA16=0)),NOT(ISNUMBER($F16)),NOT(ISNUMBER($G16)),$E16<>"",$E16<>"Rolling",$F16<>"Not offered"),"No date on file yet: find it on the college site and type it in column G. ","")&IF(AND(ISNUMBER($H16),ISNUMBER($I16),$H16=$I16,ISNUMBER($F16),$H16<$F16),"Scholarship deadline is earlier than the application deadline, so it is your real deadline. ","")&IF($AE16="No","Not on Common App: apply on "&$AF16&". ","")&IF(($AA16=0),"Not in the database: type the deadline in column G and check requirements on the college site. ","")&IF(AND(NOT(($AA16=0)),$W16<>"Yes",$AD16<>"Official 2026-27"),"Date not yet confirmed: check the college site, then set Deadline Verified to Yes. ","")&IF(LEFT($AB16,8)="Required",IF($AB16="Required","CSS Profile required. ","CSS Profile may be required: check the college's aid page. "),"")&IF($AC16<>"","Interview: "&$AC16&". Watch your email, including spam, and reply the same day. ",""))) | AA16: =IF($B16="",0,IFERROR(MATCH($B16,DB_Colleges!$A$2:$A$400,0),0)) -> 0 | AB16: =IF(($AA16=0),"",INDEX(DB_Colleges!$W$2:$W$400,$AA16)&"") | AC16: =IF(($AA16=0),"",IF(OR(LEFT(INDEX(DB_Colleges!$X$2:$X$400,$AA16)&"",4)="None",LEFT(INDEX(DB_Colleges!$X$2:$X$400,$AA16)&"",3)="No ",LEFT(INDEX(DB_Colleges!$X$2:$X$400,$AA16)&"",3)="Not"),"",INDEX(DB_Colleges!$X$2:$X$400,$AA16)&"")) | AD16: =IF(($AA16=0),"",INDEX(DB_Colleges!$AK$2:$AK$400,$AA16)&"") | AE16: =IF(($AA16=0),"",INDEX(DB_Colleges!$H$2:$H$400,$AA16)&"") | AF16: =IF(($AA16=0),"",INDEX(DB_Colleges!$G$2:$G$400,$AA16)&"")
A17: 10 | C17: =IF($B17="","",IF(($AA17=0),"No: fill G","Yes")) | D17: =IF(($AA17=0),"",INDEX(Explore!$E$8:$E$406,$AA17)) | F17: =IF($B17="","",IF($E17="","Pick a round",IF($E17="Rolling","Rolling",IF(($AA17=0),"",IF(COUNT(INDEX(DB_Colleges!$I$2:$O$400,$AA17,0))=0,"No date on file",IF(ISNUMBER(INDEX(DB_Colleges!$I$2:$O$400,$AA17,MATCH($E17,{"ED","ED II","EA","EA II","REA","RD","Priority"},0))),INDEX(DB_Colleges!$I$2:$O$400,$AA17,MATCH($E17,{"ED","ED II","EA","EA II","REA","RD","Priority"},0)),"Not offered")))))) | H17: =IF(($AA17=0),"",IF(ISNUMBER(INDEX(DB_Colleges!$Q$2:$Q$400,$AA17)),INDEX(DB_Colleges!$Q$2:$Q$400,$AA17),"")) | I17: =IF($B17="","",IF(ISNUMBER($G17),IF(ISNUMBER($H17),MIN($G17,$H17),$G17),IF(ISNUMBER($F17),IF(ISNUMBER($H17),MIN($F17,$H17),$F17),IF(AND($E17="Rolling",ISNUMBER($H17)),$H17,"")))) | J17: =IF(AND(ISNUMBER($I17),$T17<>"Submitted",$T17<>"Complete in portal"),$I17-TODAY(),"") | K17: =IF(($AA17=0),"",INDEX(DB_Colleges!$G$2:$G$400,$AA17)&"") | L17: =IF(($AA17=0),"",IF(ISNUMBER(INDEX(DB_Colleges!$S$2:$S$400,$AA17)),INDEX(DB_Colleges!$S$2:$S$400,$AA17),"")) | N17: =IF(($AA17=0),"",INDEX(DB_Colleges!$U$2:$U$400,$AA17)&"") | O17: =IF(($AA17=0),"",INDEX(DB_Colleges!$V$2:$V$400,$AA17)&"") | P17: =IF(($AA17=0),"",IF(ISNUMBER(INDEX(DB_Colleges!$AH$2:$AH$400,$AA17)),INDEX(DB_Colleges!$AH$2:$AH$400,$AA17),"Check")) | Q17: =IF($B17="","",'Next Steps'!$AA17&" of "&'Next Steps'!$AB17) | R17: =IF($B17="","",'Next Steps'!$AC17) | S17: =IF($B17="","",'Next Steps'!$AD17) | X17: =IF($B17="","",IF($V17="No","Dropped from your list.",IF(AND(OR($E17="ED",$E17="ED II"),OR(ISNUMBER($F17),ISNUMBER($G17))),"BINDING: if admitted you must attend. ","")&IF(AND(OR($E17="ED",$E17="ED II"),ISNUMBER($F17),SUMPRODUCT((($E$8:$E$27="ED")+($E$8:$E$27="ED II"))*ISNUMBER($F$8:$F$27)*($V$8:$V$27<>"No"))>1),"Only one Early Decision can be active at a time. ","")&IF($E17="REA","Restrictive Early Action: limits other private early applications. ","")&IF(AND(OR($E17="REA",$E17="ED"),ISNUMBER($F17),SUMPRODUCT(($E$8:$E$27="REA")*ISNUMBER($F$8:$F$27)*($V$8:$V$27<>"No"))>0,SUMPRODUCT((($E$8:$E$27="ED")+($E$8:$E$27="ED II"))*ISNUMBER($F$8:$F$27)*($V$8:$V$27<>"No"))>0),"You have Restrictive Early Action and Early Decision at the same time: check the REA college's rules, this is usually not allowed. ","")&IF($F17="Not offered","This college does not offer that round: pick another. ","")&IF(AND($E17="Rolling",NOT(ISNUMBER($G17))),"Rolling: set a target date in column G. ","")&IF(AND(NOT(($AA17=0)),NOT(ISNUMBER($F17)),NOT(ISNUMBER($G17)),$E17<>"",$E17<>"Rolling",$F17<>"Not offered"),"No date on file yet: find it on the college site and type it in column G. ","")&IF(AND(ISNUMBER($H17),ISNUMBER($I17),$H17=$I17,ISNUMBER($F17),$H17<$F17),"Scholarship deadline is earlier than the application deadline, so it is your real deadline. ","")&IF($AE17="No","Not on Common App: apply on "&$AF17&". ","")&IF(($AA17=0),"Not in the database: type the deadline in column G and check requirements on the college site. ","")&IF(AND(NOT(($AA17=0)),$W17<>"Yes",$AD17<>"Official 2026-27"),"Date not yet confirmed: check the college site, then set Deadline Verified to Yes. ","")&IF(LEFT($AB17,8)="Required",IF($AB17="Required","CSS Profile required. ","CSS Profile may be required: check the college's aid page. "),"")&IF($AC17<>"","Interview: "&$AC17&". Watch your email, including spam, and reply the same day. ",""))) | AA17: =IF($B17="",0,IFERROR(MATCH($B17,DB_Colleges!$A$2:$A$400,0),0)) -> 0 | AB17: =IF(($AA17=0),"",INDEX(DB_Colleges!$W$2:$W$400,$AA17)&"") | AC17: =IF(($AA17=0),"",IF(OR(LEFT(INDEX(DB_Colleges!$X$2:$X$400,$AA17)&"",4)="None",LEFT(INDEX(DB_Colleges!$X$2:$X$400,$AA17)&"",3)="No ",LEFT(INDEX(DB_Colleges!$X$2:$X$400,$AA17)&"",3)="Not"),"",INDEX(DB_Colleges!$X$2:$X$400,$AA17)&"")) | AD17: =IF(($AA17=0),"",INDEX(DB_Colleges!$AK$2:$AK$400,$AA17)&"") | AE17: =IF(($AA17=0),"",INDEX(DB_Colleges!$H$2:$H$400,$AA17)&"") | AF17: =IF(($AA17=0),"",INDEX(DB_Colleges!$G$2:$G$400,$AA17)&"")
A18: 11 | C18: =IF($B18="","",IF(($AA18=0),"No: fill G","Yes")) | D18: =IF(($AA18=0),"",INDEX(Explore!$E$8:$E$406,$AA18)) | F18: =IF($B18="","",IF($E18="","Pick a round",IF($E18="Rolling","Rolling",IF(($AA18=0),"",IF(COUNT(INDEX(DB_Colleges!$I$2:$O$400,$AA18,0))=0,"No date on file",IF(ISNUMBER(INDEX(DB_Colleges!$I$2:$O$400,$AA18,MATCH($E18,{"ED","ED II","EA","EA II","REA","RD","Priority"},0))),INDEX(DB_Colleges!$I$2:$O$400,$AA18,MATCH($E18,{"ED","ED II","EA","EA II","REA","RD","Priority"},0)),"Not offered")))))) | H18: =IF(($AA18=0),"",IF(ISNUMBER(INDEX(DB_Colleges!$Q$2:$Q$400,$AA18)),INDEX(DB_Colleges!$Q$2:$Q$400,$AA18),"")) | I18: =IF($B18="","",IF(ISNUMBER($G18),IF(ISNUMBER($H18),MIN($G18,$H18),$G18),IF(ISNUMBER($F18),IF(ISNUMBER($H18),MIN($F18,$H18),$F18),IF(AND($E18="Rolling",ISNUMBER($H18)),$H18,"")))) | J18: =IF(AND(ISNUMBER($I18),$T18<>"Submitted",$T18<>"Complete in portal"),$I18-TODAY(),"") | K18: =IF(($AA18=0),"",INDEX(DB_Colleges!$G$2:$G$400,$AA18)&"") | L18: =IF(($AA18=0),"",IF(ISNUMBER(INDEX(DB_Colleges!$S$2:$S$400,$AA18)),INDEX(DB_Colleges!$S$2:$S$400,$AA18),"")) | N18: =IF(($AA18=0),"",INDEX(DB_Colleges!$U$2:$U$400,$AA18)&"") | O18: =IF(($AA18=0),"",INDEX(DB_Colleges!$V$2:$V$400,$AA18)&"") | P18: =IF(($AA18=0),"",IF(ISNUMBER(INDEX(DB_Colleges!$AH$2:$AH$400,$AA18)),INDEX(DB_Colleges!$AH$2:$AH$400,$AA18),"Check")) | Q18: =IF($B18="","",'Next Steps'!$AA18&" of "&'Next Steps'!$AB18) | R18: =IF($B18="","",'Next Steps'!$AC18) | S18: =IF($B18="","",'Next Steps'!$AD18) | X18: =IF($B18="","",IF($V18="No","Dropped from your list.",IF(AND(OR($E18="ED",$E18="ED II"),OR(ISNUMBER($F18),ISNUMBER($G18))),"BINDING: if admitted you must attend. ","")&IF(AND(OR($E18="ED",$E18="ED II"),ISNUMBER($F18),SUMPRODUCT((($E$8:$E$27="ED")+($E$8:$E$27="ED II"))*ISNUMBER($F$8:$F$27)*($V$8:$V$27<>"No"))>1),"Only one Early Decision can be active at a time. ","")&IF($E18="REA","Restrictive Early Action: limits other private early applications. ","")&IF(AND(OR($E18="REA",$E18="ED"),ISNUMBER($F18),SUMPRODUCT(($E$8:$E$27="REA")*ISNUMBER($F$8:$F$27)*($V$8:$V$27<>"No"))>0,SUMPRODUCT((($E$8:$E$27="ED")+($E$8:$E$27="ED II"))*ISNUMBER($F$8:$F$27)*($V$8:$V$27<>"No"))>0),"You have Restrictive Early Action and Early Decision at the same time: check the REA college's rules, this is usually not allowed. ","")&IF($F18="Not offered","This college does not offer that round: pick another. ","")&IF(AND($E18="Rolling",NOT(ISNUMBER($G18))),"Rolling: set a target date in column G. ","")&IF(AND(NOT(($AA18=0)),NOT(ISNUMBER($F18)),NOT(ISNUMBER($G18)),$E18<>"",$E18<>"Rolling",$F18<>"Not offered"),"No date on file yet: find it on the college site and type it in column G. ","")&IF(AND(ISNUMBER($H18),ISNUMBER($I18),$H18=$I18,ISNUMBER($F18),$H18<$F18),"Scholarship deadline is earlier than the application deadline, so it is your real deadline. ","")&IF($AE18="No","Not on Common App: apply on "&$AF18&". ","")&IF(($AA18=0),"Not in the database: type the deadline in column G and check requirements on the college site. ","")&IF(AND(NOT(($AA18=0)),$W18<>"Yes",$AD18<>"Official 2026-27"),"Date not yet confirmed: check the college site, then set Deadline Verified to Yes. ","")&IF(LEFT($AB18,8)="Required",IF($AB18="Required","CSS Profile required. ","CSS Profile may be required: check the college's aid page. "),"")&IF($AC18<>"","Interview: "&$AC18&". Watch your email, including spam, and reply the same day. ",""))) | AA18: =IF($B18="",0,IFERROR(MATCH($B18,DB_Colleges!$A$2:$A$400,0),0)) -> 0 | AB18: =IF(($AA18=0),"",INDEX(DB_Colleges!$W$2:$W$400,$AA18)&"") | AC18: =IF(($AA18=0),"",IF(OR(LEFT(INDEX(DB_Colleges!$X$2:$X$400,$AA18)&"",4)="None",LEFT(INDEX(DB_Colleges!$X$2:$X$400,$AA18)&"",3)="No ",LEFT(INDEX(DB_Colleges!$X$2:$X$400,$AA18)&"",3)="Not"),"",INDEX(DB_Colleges!$X$2:$X$400,$AA18)&"")) | AD18: =IF(($AA18=0),"",INDEX(DB_Colleges!$AK$2:$AK$400,$AA18)&"") | AE18: =IF(($AA18=0),"",INDEX(DB_Colleges!$H$2:$H$400,$AA18)&"") | AF18: =IF(($AA18=0),"",INDEX(DB_Colleges!$G$2:$G$400,$AA18)&"")
A19: 12 | C19: =IF($B19="","",IF(($AA19=0),"No: fill G","Yes")) | D19: =IF(($AA19=0),"",INDEX(Explore!$E$8:$E$406,$AA19)) | F19: =IF($B19="","",IF($E19="","Pick a round",IF($E19="Rolling","Rolling",IF(($AA19=0),"",IF(COUNT(INDEX(DB_Colleges!$I$2:$O$400,$AA19,0))=0,"No date on file",IF(ISNUMBER(INDEX(DB_Colleges!$I$2:$O$400,$AA19,MATCH($E19,{"ED","ED II","EA","EA II","REA","RD","Priority"},0))),INDEX(DB_Colleges!$I$2:$O$400,$AA19,MATCH($E19,{"ED","ED II","EA","EA II","REA","RD","Priority"},0)),"Not offered")))))) | H19: =IF(($AA19=0),"",IF(ISNUMBER(INDEX(DB_Colleges!$Q$2:$Q$400,$AA19)),INDEX(DB_Colleges!$Q$2:$Q$400,$AA19),"")) | I19: =IF($B19="","",IF(ISNUMBER($G19),IF(ISNUMBER($H19),MIN($G19,$H19),$G19),IF(ISNUMBER($F19),IF(ISNUMBER($H19),MIN($F19,$H19),$F19),IF(AND($E19="Rolling",ISNUMBER($H19)),$H19,"")))) | J19: =IF(AND(ISNUMBER($I19),$T19<>"Submitted",$T19<>"Complete in portal"),$I19-TODAY(),"") | K19: =IF(($AA19=0),"",INDEX(DB_Colleges!$G$2:$G$400,$AA19)&"") | L19: =IF(($AA19=0),"",IF(ISNUMBER(INDEX(DB_Colleges!$S$2:$S$400,$AA19)),INDEX(DB_Colleges!$S$2:$S$400,$AA19),"")) | N19: =IF(($AA19=0),"",INDEX(DB_Colleges!$U$2:$U$400,$AA19)&"") | O19: =IF(($AA19=0),"",INDEX(DB_Colleges!$V$2:$V$400,$AA19)&"") | P19: =IF(($AA19=0),"",IF(ISNUMBER(INDEX(DB_Colleges!$AH$2:$AH$400,$AA19)),INDEX(DB_Colleges!$AH$2:$AH$400,$AA19),"Check")) | Q19: =IF($B19="","",'Next Steps'!$AA19&" of "&'Next Steps'!$AB19) | R19: =IF($B19="","",'Next Steps'!$AC19) | S19: =IF($B19="","",'Next Steps'!$AD19) | X19: =IF($B19="","",IF($V19="No","Dropped from your list.",IF(AND(OR($E19="ED",$E19="ED II"),OR(ISNUMBER($F19),ISNUMBER($G19))),"BINDING: if admitted you must attend. ","")&IF(AND(OR($E19="ED",$E19="ED II"),ISNUMBER($F19),SUMPRODUCT((($E$8:$E$27="ED")+($E$8:$E$27="ED II"))*ISNUMBER($F$8:$F$27)*($V$8:$V$27<>"No"))>1),"Only one Early Decision can be active at a time. ","")&IF($E19="REA","Restrictive Early Action: limits other private early applications. ","")&IF(AND(OR($E19="REA",$E19="ED"),ISNUMBER($F19),SUMPRODUCT(($E$8:$E$27="REA")*ISNUMBER($F$8:$F$27)*($V$8:$V$27<>"No"))>0,SUMPRODUCT((($E$8:$E$27="ED")+($E$8:$E$27="ED II"))*ISNUMBER($F$8:$F$27)*($V$8:$V$27<>"No"))>0),"You have Restrictive Early Action and Early Decision at the same time: check the REA college's rules, this is usually not allowed. ","")&IF($F19="Not offered","This college does not offer that round: pick another. ","")&IF(AND($E19="Rolling",NOT(ISNUMBER($G19))),"Rolling: set a target date in column G. ","")&IF(AND(NOT(($AA19=0)),NOT(ISNUMBER($F19)),NOT(ISNUMBER($G19)),$E19<>"",$E19<>"Rolling",$F19<>"Not offered"),"No date on file yet: find it on the college site and type it in column G. ","")&IF(AND(ISNUMBER($H19),ISNUMBER($I19),$H19=$I19,ISNUMBER($F19),$H19<$F19),"Scholarship deadline is earlier than the application deadline, so it is your real deadline. ","")&IF($AE19="No","Not on Common App: apply on "&$AF19&". ","")&IF(($AA19=0),"Not in the database: type the deadline in column G and check requirements on the college site. ","")&IF(AND(NOT(($AA19=0)),$W19<>"Yes",$AD19<>"Official 2026-27"),"Date not yet confirmed: check the college site, then set Deadline Verified to Yes. ","")&IF(LEFT($AB19,8)="Required",IF($AB19="Required","CSS Profile required. ","CSS Profile may be required: check the college's aid page. "),"")&IF($AC19<>"","Interview: "&$AC19&". Watch your email, including spam, and reply the same day. ",""))) | AA19: =IF($B19="",0,IFERROR(MATCH($B19,DB_Colleges!$A$2:$A$400,0),0)) -> 0 | AB19: =IF(($AA19=0),"",INDEX(DB_Colleges!$W$2:$W$400,$AA19)&"") | AC19: =IF(($AA19=0),"",IF(OR(LEFT(INDEX(DB_Colleges!$X$2:$X$400,$AA19)&"",4)="None",LEFT(INDEX(DB_Colleges!$X$2:$X$400,$AA19)&"",3)="No ",LEFT(INDEX(DB_Colleges!$X$2:$X$400,$AA19)&"",3)="Not"),"",INDEX(DB_Colleges!$X$2:$X$400,$AA19)&"")) | AD19: =IF(($AA19=0),"",INDEX(DB_Colleges!$AK$2:$AK$400,$AA19)&"") | AE19: =IF(($AA19=0),"",INDEX(DB_Colleges!$H$2:$H$400,$AA19)&"") | AF19: =IF(($AA19=0),"",INDEX(DB_Colleges!$G$2:$G$400,$AA19)&"")
... A27: 20 | C27: =IF($B27="","",IF(($AA27=0),"No: fill G","Yes")) | D27: =IF(($AA27=0),"",INDEX(Explore!$E$8:$E$406,$AA27)) | F27: =IF($B27="","",IF($E27="","Pick a round",IF($E27="Rolling","Rolling",IF(($AA27=0),"",IF(COUNT(INDEX(DB_Colleges!$I$2:$O$400,$AA27,0))=0,"No date on file",IF(ISNUMBER(INDEX(DB_Colleges!$I$2:$O$400,$AA27,MATCH($E27,{"ED","ED II","EA","EA II","REA","RD","Priority"},0))),INDEX(DB_Colleges!$I$2:$O$400,$AA27,MATCH($E27,{"ED","ED II","EA","EA II","REA","RD","Priority"},0)),"Not offered")))))) | H27: =IF(($AA27=0),"",IF(ISNUMBER(INDEX(DB_Colleges!$Q$2:$Q$400,$AA27)),INDEX(DB_Colleges!$Q$2:$Q$400,$AA27),"")) | I27: =IF($B27="","",IF(ISNUMBER($G27),IF(ISNUMBER($H27),MIN($G27,$H27),$G27),IF(ISNUMBER($F27),IF(ISNUMBER($H27),MIN($F27,$H27),$F27),IF(AND($E27="Rolling",ISNUMBER($H27)),$H27,"")))) | J27: =IF(AND(ISNUMBER($I27),$T27<>"Submitted",$T27<>"Complete in portal"),$I27-TODAY(),"") | K27: =IF(($AA27=0),"",INDEX(DB_Colleges!$G$2:$G$400,$AA27)&"") | L27: =IF(($AA27=0),"",IF(ISNUMBER(INDEX(DB_Colleges!$S$2:$S$400,$AA27)),INDEX(DB_Colleges!$S$2:$S$400,$AA27),"")) | N27: =IF(($AA27=0),"",INDEX(DB_Colleges!$U$2:$U$400,$AA27)&"") | O27: =IF(($AA27=0),"",INDEX(DB_Colleges!$V$2:$V$400,$AA27)&"") | P27: =IF(($AA27=0),"",IF(ISNUMBER(INDEX(DB_Colleges!$AH$2:$AH$400,$AA27)),INDEX(DB_Colleges!$AH$2:$AH$400,$AA27),"Check")) | Q27: =IF($B27="","",'Next Steps'!$AA27&" of "&'Next Steps'!$AB27) | R27: =IF($B27="","",'Next Steps'!$AC27) | S27: =IF($B27="","",'Next Steps'!$AD27) | X27: =IF($B27="","",IF($V27="No","Dropped from your list.",IF(AND(OR($E27="ED",$E27="ED II"),OR(ISNUMBER($F27),ISNUMBER($G27))),"BINDING: if admitted you must attend. ","")&IF(AND(OR($E27="ED",$E27="ED II"),ISNUMBER($F27),SUMPRODUCT((($E$8:$E$27="ED")+($E$8:$E$27="ED II"))*ISNUMBER($F$8:$F$27)*($V$8:$V$27<>"No"))>1),"Only one Early Decision can be active at a time. ","")&IF($E27="REA","Restrictive Early Action: limits other private early applications. ","")&IF(AND(OR($E27="REA",$E27="ED"),ISNUMBER($F27),SUMPRODUCT(($E$8:$E$27="REA")*ISNUMBER($F$8:$F$27)*($V$8:$V$27<>"No"))>0,SUMPRODUCT((($E$8:$E$27="ED")+($E$8:$E$27="ED II"))*ISNUMBER($F$8:$F$27)*($V$8:$V$27<>"No"))>0),"You have Restrictive Early Action and Early Decision at the same time: check the REA college's rules, this is usually not allowed. ","")&IF($F27="Not offered","This college does not offer that round: pick another. ","")&IF(AND($E27="Rolling",NOT(ISNUMBER($G27))),"Rolling: set a target date in column G. ","")&IF(AND(NOT(($AA27=0)),NOT(ISNUMBER($F27)),NOT(ISNUMBER($G27)),$E27<>"",$E27<>"Rolling",$F27<>"Not offered"),"No date on file yet: find it on the college site and type it in column G. ","")&IF(AND(ISNUMBER($H27),ISNUMBER($I27),$H27=$I27,ISNUMBER($F27),$H27<$F27),"Scholarship deadline is earlier than the application deadline, so it is your real deadline. ","")&IF($AE27="No","Not on Common App: apply on "&$AF27&". ","")&IF(($AA27=0),"Not in the database: type the deadline in column G and check requirements on the college site. ","")&IF(AND(NOT(($AA27=0)),$W27<>"Yes",$AD27<>"Official 2026-27"),"Date not yet confirmed: check the college site, then set Deadline Verified to Yes. ","")&IF(LEFT($AB27,8)="Required",IF($AB27="Required","CSS Profile required. ","CSS Profile may be required: check the college's aid page. "),"")&IF($AC27<>"","Interview: "&$AC27&". Watch your email, including spam, and reply the same day. ",""))) | AA27: =IF($B27="",0,IFERROR(MATCH($B27,DB_Colleges!$A$2:$A$400,0),0)) -> 0 | AB27: =IF(($AA27=0),"",INDEX(DB_Colleges!$W$2:$W$400,$AA27)&"") | AC27: =IF(($AA27=0),"",IF(OR(LEFT(INDEX(DB_Colleges!$X$2:$X$400,$AA27)&"",4)="None",LEFT(INDEX(DB_Colleges!$X$2:$X$400,$AA27)&"",3)="No ",LEFT(INDEX(DB_Colleges!$X$2:$X$400,$AA27)&"",3)="Not"),"",INDEX(DB_Colleges!$X$2:$X$400,$AA27)&"")) | AD27: =IF(($AA27=0),"",INDEX(DB_Colleges!$AK$2:$AK$400,$AA27)&"") | AE27: =IF(($AA27=0),"",INDEX(DB_Colleges!$H$2:$H$400,$AA27)&"") | AF27: =IF(($AA27=0),"",INDEX(DB_Colleges!$G$2:$G$400,$AA27)&"")
B29: How this tab works
B30: - Effective Filing Date is the earlier of your round's deadline and the college's scholarship deadline. Every due date on Next Steps counts back from it.
B31: - Cream rows are binding Early Decision. Only one Early Decision can be active at a time; Early Decision II is only for after an Early Decision I result.
B32: - If a college is not in the list, type its name in column B anyway and type the deadline in column G. Then check its requirements on its own website.
B33: - To drop a college, set On Final List to No. Never delete or reorder rows: your Next Steps checklists and Essays are tied to these rows.
B34: - Status Complete in portal means you logged in after submitting and saw every item (transcript, scores, recommendations) marked received.

Sheet Next Steps
A1: Next Steps
A2: One checklist per college, in the same order as My Colleges. Due dates count back from each college's Effective Filing Date. Check the box when a step is done. n/a means the step does not apply to that college.
A4: Steps overdue | C4: Due in next 7 days | G4: Steps done
A5: =COUNTIF($AE$8:$AP$27,"<"&TODAY()) -> 0 | C5: =COUNTIFS($AE$8:$AP$27,">="&TODAY(),$AE$8:$AP$27,"<"&(TODAY()+8)) -> 0 | G5: =SUM(AA8:AA27)&" of "&SUM(AB8:AB27) -> 0 of 0
C6: Confirm requirements on college site | E6: Ask recommenders | G6: Draft extra essays | I6: Final extra essays | K6: Request transcript | M6: Send test scores | O6: Fee paid or waiver | Q6: Submit application | S6: Scholarship application | U6: CSS Profile | W6: Confirm all received in portal | Y6: Interview | AE6: Confirm requirements on college site | AF6: Ask recommenders | AG6: Draft extra essays | AH6: Final extra essays | AI6: Request transcript | AJ6: Send test scores | AK6: Fee paid or waiver | AL6: Submit application | AM6: Scholarship application | AN6: CSS Profile | AO6: Confirm all received in portal | AP6: Interview
A7: College | B7: Filing Date | C7: Due | D7: Done | E7: Due | F7: Done | G7: Due | H7: Done | I7: Due | J7: Done | K7: Due | L7: Done | M7: Due | N7: Done | O7: Due | P7: Done | Q7: Due | R7: Done | S7: Due | T7: Done | U7: Due | V7: Done | W7: Due | X7: Done | Y7: Due | Z7: Done | AA7: Steps Done | AB7: Steps Total | AC7: Next Step | AD7: Next Due
A8: =IF('My Colleges'!$B8="","",'My Colleges'!$B8) | B8: =IF($A8="","",IF('My Colleges'!$V8="No","Dropped",'My Colleges'!$I8)) | C8: =IF(OR($A8="",NOT(ISNUMBER($B8))),"",IF(TRUE(),MAX($B8-35,MIN(Summary!$B$8+7,$B8-3)),"n/a")) | D8: =FALSE() -> FALSE | E8: =IF(OR($A8="",NOT(ISNUMBER($B8))),"",IF(NOT(OR('My Colleges'!$O8="None",'My Colleges'!$O8="None required")),MAX($B8-21,MIN(Summary!$B$8+7,$B8-3)),"n/a")) | F8: =FALSE() -> FALSE | G8: =IF(OR($A8="",NOT(ISNUMBER($B8))),"",IF(NOT(AND(ISNUMBER('My Colleges'!$P8),'My Colleges'!$P8=0)),MAX($B8-28,MIN(Summary!$B$8+7,$B8-3)),"n/a")) | H8: =FALSE() -> FALSE | I8: =IF(OR($A8="",NOT(ISNUMBER($B8))),"",IF(NOT(AND(ISNUMBER('My Colleges'!$P8),'My Colleges'!$P8=0)),MAX($B8-10,MIN(Summary!$B$8+7,$B8-3)),"n/a")) | J8: =FALSE() -> FALSE | K8: =IF(OR($A8="",NOT(ISNUMBER($B8))),"",IF(TRUE(),MAX($B8-14,MIN(Summary!$B$8+7,$B8-3)),"n/a")) | L8: =FALSE() -> FALSE | M8: =IF(OR($A8="",NOT(ISNUMBER($B8))),"",IF(AND('My Colleges'!$N8<>"Blind",OR('My Colleges'!$N8="Required",ISNUMBER(Me!$B$13),ISNUMBER(Me!$B$14))),MAX($B8-14,MIN(Summary!$B$8+7,$B8-3)),"n/a")) | N8: =FALSE() -> FALSE | O8: =IF(OR($A8="",NOT(ISNUMBER($B8))),"",IF(NOT(AND(ISNUMBER('My Colleges'!$L8),'My Colleges'!$L8=0)),MAX($B8-5,MIN(Summary!$B$8+7,$B8-3)),"n/a")) | P8: =FALSE() -> FALSE | Q8: =IF(OR($A8="",NOT(ISNUMBER($B8))),"",IF(TRUE(),$B8-3,"n/a")) | R8: =FALSE() -> FALSE | S8: =IF(OR($A8="",NOT(ISNUMBER($B8))),"",IF(ISNUMBER('My Colleges'!$H8),MAX('My Colleges'!$H8-7,MIN(Summary!$B$8+7,'My Colleges'!$H8-3)),"n/a")) | T8: =FALSE() -> FALSE | U8: =IF(OR($A8="",NOT(ISNUMBER($B8))),"",IF(LEFT('My Colleges'!$AB8,8)="Required",MAX($B8-7,MIN(Summary!$B$8+7,$B8-3)),"n/a")) | V8: =FALSE() -> FALSE | W8: =IF(OR($A8="",NOT(ISNUMBER($B8))),"",IF(TRUE(),$B8+10,"n/a")) | X8: =FALSE() -> FALSE | Y8: =IF(OR($A8="",NOT(ISNUMBER($B8))),"",IF('My Colleges'!$AC8<>"",$B8+21,"n/a")) | Z8: =FALSE() -> FALSE | AA8: =IF($A8="","",AB8-COUNT($AE8:$AO8)) | AB8: =IF($A8="","",SUMPRODUCT((MOD(COLUMN($C8:$X8)-COLUMN($C8),2)=0)*ISNUMBER($C8:$X8))) | AC8: =IF($A8="","",IF($B8="Dropped","Dropped",IF(NOT(ISNUMBER($B8)),"Set a deadline on My Colleges",IF(COUNT($AE8:$AP8)=0,"All steps done",INDEX($AE$6:$AP$6,MATCH(MIN($AE8:$AP8),$AE8:$AP8,0)))))) | AD8: =IF(COUNT($AE8:$AP8)=0,"",INT(MIN($AE8:$AP8))) | AE8: =IF(AND(ISNUMBER(C8),D8<>TRUE(),'My Colleges'!$T8<>"Submitted",'My Colleges'!$T8<>"Complete in portal"),C8+ROW()/1000+1/100000,"") | AF8: =IF(AND(ISNUMBER(E8),F8<>TRUE(),'My Colleges'!$T8<>"Submitted",'My Colleges'!$T8<>"Complete in portal"),E8+ROW()/1000+2/100000,"") | AG8: =IF(AND(ISNUMBER(G8),H8<>TRUE(),'My Colleges'!$T8<>"Submitted",'My Colleges'!$T8<>"Complete in portal"),G8+ROW()/1000+3/100000,"") | AH8: =IF(AND(ISNUMBER(I8),J8<>TRUE(),'My Colleges'!$T8<>"Submitted",'My Colleges'!$T8<>"Complete in portal"),I8+ROW()/1000+4/100000,"") | AI8: =IF(AND(ISNUMBER(K8),L8<>TRUE(),'My Colleges'!$T8<>"Submitted",'My Colleges'!$T8<>"Complete in portal"),K8+ROW()/1000+5/100000,"") | AJ8: =IF(AND(ISNUMBER(M8),N8<>TRUE(),'My Colleges'!$T8<>"Submitted",'My Colleges'!$T8<>"Complete in portal"),M8+ROW()/1000+6/100000,"") | AK8: =IF(AND(ISNUMBER(O8),P8<>TRUE(),'My Colleges'!$T8<>"Submitted",'My Colleges'!$T8<>"Complete in portal"),O8+ROW()/1000+7/100000,"") | AL8: =IF(AND(ISNUMBER(Q8),R8<>TRUE(),'My Colleges'!$T8<>"Submitted",'My Colleges'!$T8<>"Complete in portal"),Q8+ROW()/1000+8/100000,"") | AM8: =IF(AND(ISNUMBER(S8),T8<>TRUE()),S8+ROW()/1000+9/100000,"") | AN8: =IF(AND(ISNUMBER(U8),V8<>TRUE()),U8+ROW()/1000+10/100000,"") | AO8: =IF(AND(ISNUMBER(W8),X8<>TRUE()),W8+ROW()/1000+11/100000,"") | AP8: =IF(AND(ISNUMBER(Y8),Z8<>TRUE(),ISNUMBER(SEARCH("requir",'My Colleges'!$AC8))+ISNUMBER(SEARCH("evaluat",'My Colleges'!$AC8))>0),Y8+ROW()/1000+12/100000,"")
A9: =IF('My Colleges'!$B9="","",'My Colleges'!$B9) | B9: =IF($A9="","",IF('My Colleges'!$V9="No","Dropped",'My Colleges'!$I9)) | C9: =IF(OR($A9="",NOT(ISNUMBER($B9))),"",IF(TRUE(),MAX($B9-35,MIN(Summary!$B$8+7,$B9-3)),"n/a")) | D9: =FALSE() -> FALSE | E9: =IF(OR($A9="",NOT(ISNUMBER($B9))),"",IF(NOT(OR('My Colleges'!$O9="None",'My Colleges'!$O9="None required")),MAX($B9-21,MIN(Summary!$B$8+7,$B9-3)),"n/a")) | F9: =FALSE() -> FALSE | G9: =IF(OR($A9="",NOT(ISNUMBER($B9))),"",IF(NOT(AND(ISNUMBER('My Colleges'!$P9),'My Colleges'!$P9=0)),MAX($B9-28,MIN(Summary!$B$8+7,$B9-3)),"n/a")) | H9: =FALSE() -> FALSE | I9: =IF(OR($A9="",NOT(ISNUMBER($B9))),"",IF(NOT(AND(ISNUMBER('My Colleges'!$P9),'My Colleges'!$P9=0)),MAX($B9-10,MIN(Summary!$B$8+7,$B9-3)),"n/a")) | J9: =FALSE() -> FALSE | K9: =IF(OR($A9="",NOT(ISNUMBER($B9))),"",IF(TRUE(),MAX($B9-14,MIN(Summary!$B$8+7,$B9-3)),"n/a")) | L9: =FALSE() -> FALSE | M9: =IF(OR($A9="",NOT(ISNUMBER($B9))),"",IF(AND('My Colleges'!$N9<>"Blind",OR('My Colleges'!$N9="Required",ISNUMBER(Me!$B$13),ISNUMBER(Me!$B$14))),MAX($B9-14,MIN(Summary!$B$8+7,$B9-3)),"n/a")) | N9: =FALSE() -> FALSE | O9: =IF(OR($A9="",NOT(ISNUMBER($B9))),"",IF(NOT(AND(ISNUMBER('My Colleges'!$L9),'My Colleges'!$L9=0)),MAX($B9-5,MIN(Summary!$B$8+7,$B9-3)),"n/a")) | P9: =FALSE() -> FALSE | Q9: =IF(OR($A9="",NOT(ISNUMBER($B9))),"",IF(TRUE(),$B9-3,"n/a")) | R9: =FALSE() -> FALSE | S9: =IF(OR($A9="",NOT(ISNUMBER($B9))),"",IF(ISNUMBER('My Colleges'!$H9),MAX('My Colleges'!$H9-7,MIN(Summary!$B$8+7,'My Colleges'!$H9-3)),"n/a")) | T9: =FALSE() -> FALSE | U9: =IF(OR($A9="",NOT(ISNUMBER($B9))),"",IF(LEFT('My Colleges'!$AB9,8)="Required",MAX($B9-7,MIN(Summary!$B$8+7,$B9-3)),"n/a")) | V9: =FALSE() -> FALSE | W9: =IF(OR($A9="",NOT(ISNUMBER($B9))),"",IF(TRUE(),$B9+10,"n/a")) | X9: =FALSE() -> FALSE | Y9: =IF(OR($A9="",NOT(ISNUMBER($B9))),"",IF('My Colleges'!$AC9<>"",$B9+21,"n/a")) | Z9: =FALSE() -> FALSE | AA9: =IF($A9="","",AB9-COUNT($AE9:$AO9)) | AB9: =IF($A9="","",SUMPRODUCT((MOD(COLUMN($C9:$X9)-COLUMN($C9),2)=0)*ISNUMBER($C9:$X9))) | AC9: =IF($A9="","",IF($B9="Dropped","Dropped",IF(NOT(ISNUMBER($B9)),"Set a deadline on My Colleges",IF(COUNT($AE9:$AP9)=0,"All steps done",INDEX($AE$6:$AP$6,MATCH(MIN($AE9:$AP9),$AE9:$AP9,0)))))) | AD9: =IF(COUNT($AE9:$AP9)=0,"",INT(MIN($AE9:$AP9))) | AE9: =IF(AND(ISNUMBER(C9),D9<>TRUE(),'My Colleges'!$T9<>"Submitted",'My Colleges'!$T9<>"Complete in portal"),C9+ROW()/1000+1/100000,"") | AF9: =IF(AND(ISNUMBER(E9),F9<>TRUE(),'My Colleges'!$T9<>"Submitted",'My Colleges'!$T9<>"Complete in portal"),E9+ROW()/1000+2/100000,"") | AG9: =IF(AND(ISNUMBER(G9),H9<>TRUE(),'My Colleges'!$T9<>"Submitted",'My Colleges'!$T9<>"Complete in portal"),G9+ROW()/1000+3/100000,"") | AH9: =IF(AND(ISNUMBER(I9),J9<>TRUE(),'My Colleges'!$T9<>"Submitted",'My Colleges'!$T9<>"Complete in portal"),I9+ROW()/1000+4/100000,"") | AI9: =IF(AND(ISNUMBER(K9),L9<>TRUE(),'My Colleges'!$T9<>"Submitted",'My Colleges'!$T9<>"Complete in portal"),K9+ROW()/1000+5/100000,"") | AJ9: =IF(AND(ISNUMBER(M9),N9<>TRUE(),'My Colleges'!$T9<>"Submitted",'My Colleges'!$T9<>"Complete in portal"),M9+ROW()/1000+6/100000,"") | AK9: =IF(AND(ISNUMBER(O9),P9<>TRUE(),'My Colleges'!$T9<>"Submitted",'My Colleges'!$T9<>"Complete in portal"),O9+ROW()/1000+7/100000,"") | AL9: =IF(AND(ISNUMBER(Q9),R9<>TRUE(),'My Colleges'!$T9<>"Submitted",'My Colleges'!$T9<>"Complete in portal"),Q9+ROW()/1000+8/100000,"") | AM9: =IF(AND(ISNUMBER(S9),T9<>TRUE()),S9+ROW()/1000+9/100000,"") | AN9: =IF(AND(ISNUMBER(U9),V9<>TRUE()),U9+ROW()/1000+10/100000,"") | AO9: =IF(AND(ISNUMBER(W9),X9<>TRUE()),W9+ROW()/1000+11/100000,"") | AP9: =IF(AND(ISNUMBER(Y9),Z9<>TRUE(),ISNUMBER(SEARCH("requir",'My Colleges'!$AC9))+ISNUMBER(SEARCH("evaluat",'My Colleges'!$AC9))>0),Y9+ROW()/1000+12/100000,"")
A10: =IF('My Colleges'!$B10="","",'My Colleges'!$B10) | B10: =IF($A10="","",IF('My Colleges'!$V10="No","Dropped",'My Colleges'!$I10)) | C10: =IF(OR($A10="",NOT(ISNUMBER($B10))),"",IF(TRUE(),MAX($B10-35,MIN(Summary!$B$8+7,$B10-3)),"n/a")) | D10: =FALSE() -> FALSE | E10: =IF(OR($A10="",NOT(ISNUMBER($B10))),"",IF(NOT(OR('My Colleges'!$O10="None",'My Colleges'!$O10="None required")),MAX($B10-21,MIN(Summary!$B$8+7,$B10-3)),"n/a")) | F10: =FALSE() -> FALSE | G10: =IF(OR($A10="",NOT(ISNUMBER($B10))),"",IF(NOT(AND(ISNUMBER('My Colleges'!$P10),'My Colleges'!$P10=0)),MAX($B10-28,MIN(Summary!$B$8+7,$B10-3)),"n/a")) | H10: =FALSE() -> FALSE | I10: =IF(OR($A10="",NOT(ISNUMBER($B10))),"",IF(NOT(AND(ISNUMBER('My Colleges'!$P10),'My Colleges'!$P10=0)),MAX($B10-10,MIN(Summary!$B$8+7,$B10-3)),"n/a")) | J10: =FALSE() -> FALSE | K10: =IF(OR($A10="",NOT(ISNUMBER($B10))),"",IF(TRUE(),MAX($B10-14,MIN(Summary!$B$8+7,$B10-3)),"n/a")) | L10: =FALSE() -> FALSE | M10: =IF(OR($A10="",NOT(ISNUMBER($B10))),"",IF(AND('My Colleges'!$N10<>"Blind",OR('My Colleges'!$N10="Required",ISNUMBER(Me!$B$13),ISNUMBER(Me!$B$14))),MAX($B10-14,MIN(Summary!$B$8+7,$B10-3)),"n/a")) | N10: =FALSE() -> FALSE | O10: =IF(OR($A10="",NOT(ISNUMBER($B10))),"",IF(NOT(AND(ISNUMBER('My Colleges'!$L10),'My Colleges'!$L10=0)),MAX($B10-5,MIN(Summary!$B$8+7,$B10-3)),"n/a")) | P10: =FALSE() -> FALSE | Q10: =IF(OR($A10="",NOT(ISNUMBER($B10))),"",IF(TRUE(),$B10-3,"n/a")) | R10: =FALSE() -> FALSE | S10: =IF(OR($A10="",NOT(ISNUMBER($B10))),"",IF(ISNUMBER('My Colleges'!$H10),MAX('My Colleges'!$H10-7,MIN(Summary!$B$8+7,'My Colleges'!$H10-3)),"n/a")) | T10: =FALSE() -> FALSE | U10: =IF(OR($A10="",NOT(ISNUMBER($B10))),"",IF(LEFT('My Colleges'!$AB10,8)="Required",MAX($B10-7,MIN(Summary!$B$8+7,$B10-3)),"n/a")) | V10: =FALSE() -> FALSE | W10: =IF(OR($A10="",NOT(ISNUMBER($B10))),"",IF(TRUE(),$B10+10,"n/a")) | X10: =FALSE() -> FALSE | Y10: =IF(OR($A10="",NOT(ISNUMBER($B10))),"",IF('My Colleges'!$AC10<>"",$B10+21,"n/a")) | Z10: =FALSE() -> FALSE | AA10: =IF($A10="","",AB10-COUNT($AE10:$AO10)) | AB10: =IF($A10="","",SUMPRODUCT((MOD(COLUMN($C10:$X10)-COLUMN($C10),2)=0)*ISNUMBER($C10:$X10))) | AC10: =IF($A10="","",IF($B10="Dropped","Dropped",IF(NOT(ISNUMBER($B10)),"Set a deadline on My Colleges",IF(COUNT($AE10:$AP10)=0,"All steps done",INDEX($AE$6:$AP$6,MATCH(MIN($AE10:$AP10),$AE10:$AP10,0)))))) | AD10: =IF(COUNT($AE10:$AP10)=0,"",INT(MIN($AE10:$AP10))) | AE10: =IF(AND(ISNUMBER(C10),D10<>TRUE(),'My Colleges'!$T10<>"Submitted",'My Colleges'!$T10<>"Complete in portal"),C10+ROW()/1000+1/100000,"") | AF10: =IF(AND(ISNUMBER(E10),F10<>TRUE(),'My Colleges'!$T10<>"Submitted",'My Colleges'!$T10<>"Complete in portal"),E10+ROW()/1000+2/100000,"") | AG10: =IF(AND(ISNUMBER(G10),H10<>TRUE(),'My Colleges'!$T10<>"Submitted",'My Colleges'!$T10<>"Complete in portal"),G10+ROW()/1000+3/100000,"") | AH10: =IF(AND(ISNUMBER(I10),J10<>TRUE(),'My Colleges'!$T10<>"Submitted",'My Colleges'!$T10<>"Complete in portal"),I10+ROW()/1000+4/100000,"") | AI10: =IF(AND(ISNUMBER(K10),L10<>TRUE(),'My Colleges'!$T10<>"Submitted",'My Colleges'!$T10<>"Complete in portal"),K10+ROW()/1000+5/100000,"") | AJ10: =IF(AND(ISNUMBER(M10),N10<>TRUE(),'My Colleges'!$T10<>"Submitted",'My Colleges'!$T10<>"Complete in portal"),M10+ROW()/1000+6/100000,"") | AK10: =IF(AND(ISNUMBER(O10),P10<>TRUE(),'My Colleges'!$T10<>"Submitted",'My Colleges'!$T10<>"Complete in portal"),O10+ROW()/1000+7/100000,"") | AL10: =IF(AND(ISNUMBER(Q10),R10<>TRUE(),'My Colleges'!$T10<>"Submitted",'My Colleges'!$T10<>"Complete in portal"),Q10+ROW()/1000+8/100000,"") | AM10: =IF(AND(ISNUMBER(S10),T10<>TRUE()),S10+ROW()/1000+9/100000,"") | AN10: =IF(AND(ISNUMBER(U10),V10<>TRUE()),U10+ROW()/1000+10/100000,"") | AO10: =IF(AND(ISNUMBER(W10),X10<>TRUE()),W10+ROW()/1000+11/100000,"") | AP10: =IF(AND(ISNUMBER(Y10),Z10<>TRUE(),ISNUMBER(SEARCH("requir",'My Colleges'!$AC10))+ISNUMBER(SEARCH("evaluat",'My Colleges'!$AC10))>0),Y10+ROW()/1000+12/100000,"")
A11: =IF('My Colleges'!$B11="","",'My Colleges'!$B11) | B11: =IF($A11="","",IF('My Colleges'!$V11="No","Dropped",'My Colleges'!$I11)) | C11: =IF(OR($A11="",NOT(ISNUMBER($B11))),"",IF(TRUE(),MAX($B11-35,MIN(Summary!$B$8+7,$B11-3)),"n/a")) | D11: =FALSE() -> FALSE | E11: =IF(OR($A11="",NOT(ISNUMBER($B11))),"",IF(NOT(OR('My Colleges'!$O11="None",'My Colleges'!$O11="None required")),MAX($B11-21,MIN(Summary!$B$8+7,$B11-3)),"n/a")) | F11: =FALSE() -> FALSE | G11: =IF(OR($A11="",NOT(ISNUMBER($B11))),"",IF(NOT(AND(ISNUMBER('My Colleges'!$P11),'My Colleges'!$P11=0)),MAX($B11-28,MIN(Summary!$B$8+7,$B11-3)),"n/a")) | H11: =FALSE() -> FALSE | I11: =IF(OR($A11="",NOT(ISNUMBER($B11))),"",IF(NOT(AND(ISNUMBER('My Colleges'!$P11),'My Colleges'!$P11=0)),MAX($B11-10,MIN(Summary!$B$8+7,$B11-3)),"n/a")) | J11: =FALSE() -> FALSE | K11: =IF(OR($A11="",NOT(ISNUMBER($B11))),"",IF(TRUE(),MAX($B11-14,MIN(Summary!$B$8+7,$B11-3)),"n/a")) | L11: =FALSE() -> FALSE | M11: =IF(OR($A11="",NOT(ISNUMBER($B11))),"",IF(AND('My Colleges'!$N11<>"Blind",OR('My Colleges'!$N11="Required",ISNUMBER(Me!$B$13),ISNUMBER(Me!$B$14))),MAX($B11-14,MIN(Summary!$B$8+7,$B11-3)),"n/a")) | N11: =FALSE() -> FALSE | O11: =IF(OR($A11="",NOT(ISNUMBER($B11))),"",IF(NOT(AND(ISNUMBER('My Colleges'!$L11),'My Colleges'!$L11=0)),MAX($B11-5,MIN(Summary!$B$8+7,$B11-3)),"n/a")) | P11: =FALSE() -> FALSE | Q11: =IF(OR($A11="",NOT(ISNUMBER($B11))),"",IF(TRUE(),$B11-3,"n/a")) | R11: =FALSE() -> FALSE | S11: =IF(OR($A11="",NOT(ISNUMBER($B11))),"",IF(ISNUMBER('My Colleges'!$H11),MAX('My Colleges'!$H11-7,MIN(Summary!$B$8+7,'My Colleges'!$H11-3)),"n/a")) | T11: =FALSE() -> FALSE | U11: =IF(OR($A11="",NOT(ISNUMBER($B11))),"",IF(LEFT('My Colleges'!$AB11,8)="Required",MAX($B11-7,MIN(Summary!$B$8+7,$B11-3)),"n/a")) | V11: =FALSE() -> FALSE | W11: =IF(OR($A11="",NOT(ISNUMBER($B11))),"",IF(TRUE(),$B11+10,"n/a")) | X11: =FALSE() -> FALSE | Y11: =IF(OR($A11="",NOT(ISNUMBER($B11))),"",IF('My Colleges'!$AC11<>"",$B11+21,"n/a")) | Z11: =FALSE() -> FALSE | AA11: =IF($A11="","",AB11-COUNT($AE11:$AO11)) | AB11: =IF($A11="","",SUMPRODUCT((MOD(COLUMN($C11:$X11)-COLUMN($C11),2)=0)*ISNUMBER($C11:$X11))) | AC11: =IF($A11="","",IF($B11="Dropped","Dropped",IF(NOT(ISNUMBER($B11)),"Set a deadline on My Colleges",IF(COUNT($AE11:$AP11)=0,"All steps done",INDEX($AE$6:$AP$6,MATCH(MIN($AE11:$AP11),$AE11:$AP11,0)))))) | AD11: =IF(COUNT($AE11:$AP11)=0,"",INT(MIN($AE11:$AP11))) | AE11: =IF(AND(ISNUMBER(C11),D11<>TRUE(),'My Colleges'!$T11<>"Submitted",'My Colleges'!$T11<>"Complete in portal"),C11+ROW()/1000+1/100000,"") | AF11: =IF(AND(ISNUMBER(E11),F11<>TRUE(),'My Colleges'!$T11<>"Submitted",'My Colleges'!$T11<>"Complete in portal"),E11+ROW()/1000+2/100000,"") | AG11: =IF(AND(ISNUMBER(G11),H11<>TRUE(),'My Colleges'!$T11<>"Submitted",'My Colleges'!$T11<>"Complete in portal"),G11+ROW()/1000+3/100000,"") | AH11: =IF(AND(ISNUMBER(I11),J11<>TRUE(),'My Colleges'!$T11<>"Submitted",'My Colleges'!$T11<>"Complete in portal"),I11+ROW()/1000+4/100000,"") | AI11: =IF(AND(ISNUMBER(K11),L11<>TRUE(),'My Colleges'!$T11<>"Submitted",'My Colleges'!$T11<>"Complete in portal"),K11+ROW()/1000+5/100000,"") | AJ11: =IF(AND(ISNUMBER(M11),N11<>TRUE(),'My Colleges'!$T11<>"Submitted",'My Colleges'!$T11<>"Complete in portal"),M11+ROW()/1000+6/100000,"") | AK11: =IF(AND(ISNUMBER(O11),P11<>TRUE(),'My Colleges'!$T11<>"Submitted",'My Colleges'!$T11<>"Complete in portal"),O11+ROW()/1000+7/100000,"") | AL11: =IF(AND(ISNUMBER(Q11),R11<>TRUE(),'My Colleges'!$T11<>"Submitted",'My Colleges'!$T11<>"Complete in portal"),Q11+ROW()/1000+8/100000,"") | AM11: =IF(AND(ISNUMBER(S11),T11<>TRUE()),S11+ROW()/1000+9/100000,"") | AN11: =IF(AND(ISNUMBER(U11),V11<>TRUE()),U11+ROW()/1000+10/100000,"") | AO11: =IF(AND(ISNUMBER(W11),X11<>TRUE()),W11+ROW()/1000+11/100000,"") | AP11: =IF(AND(ISNUMBER(Y11),Z11<>TRUE(),ISNUMBER(SEARCH("requir",'My Colleges'!$AC11))+ISNUMBER(SEARCH("evaluat",'My Colleges'!$AC11))>0),Y11+ROW()/1000+12/100000,"")
A12: =IF('My Colleges'!$B12="","",'My Colleges'!$B12) | B12: =IF($A12="","",IF('My Colleges'!$V12="No","Dropped",'My Colleges'!$I12)) | C12: =IF(OR($A12="",NOT(ISNUMBER($B12))),"",IF(TRUE(),MAX($B12-35,MIN(Summary!$B$8+7,$B12-3)),"n/a")) | D12: =FALSE() -> FALSE | E12: =IF(OR($A12="",NOT(ISNUMBER($B12))),"",IF(NOT(OR('My Colleges'!$O12="None",'My Colleges'!$O12="None required")),MAX($B12-21,MIN(Summary!$B$8+7,$B12-3)),"n/a")) | F12: =FALSE() -> FALSE | G12: =IF(OR($A12="",NOT(ISNUMBER($B12))),"",IF(NOT(AND(ISNUMBER('My Colleges'!$P12),'My Colleges'!$P12=0)),MAX($B12-28,MIN(Summary!$B$8+7,$B12-3)),"n/a")) | H12: =FALSE() -> FALSE | I12: =IF(OR($A12="",NOT(ISNUMBER($B12))),"",IF(NOT(AND(ISNUMBER('My Colleges'!$P12),'My Colleges'!$P12=0)),MAX($B12-10,MIN(Summary!$B$8+7,$B12-3)),"n/a")) | J12: =FALSE() -> FALSE | K12: =IF(OR($A12="",NOT(ISNUMBER($B12))),"",IF(TRUE(),MAX($B12-14,MIN(Summary!$B$8+7,$B12-3)),"n/a")) | L12: =FALSE() -> FALSE | M12: =IF(OR($A12="",NOT(ISNUMBER($B12))),"",IF(AND('My Colleges'!$N12<>"Blind",OR('My Colleges'!$N12="Required",ISNUMBER(Me!$B$13),ISNUMBER(Me!$B$14))),MAX($B12-14,MIN(Summary!$B$8+7,$B12-3)),"n/a")) | N12: =FALSE() -> FALSE | O12: =IF(OR($A12="",NOT(ISNUMBER($B12))),"",IF(NOT(AND(ISNUMBER('My Colleges'!$L12),'My Colleges'!$L12=0)),MAX($B12-5,MIN(Summary!$B$8+7,$B12-3)),"n/a")) | P12: =FALSE() -> FALSE | Q12: =IF(OR($A12="",NOT(ISNUMBER($B12))),"",IF(TRUE(),$B12-3,"n/a")) | R12: =FALSE() -> FALSE | S12: =IF(OR($A12="",NOT(ISNUMBER($B12))),"",IF(ISNUMBER('My Colleges'!$H12),MAX('My Colleges'!$H12-7,MIN(Summary!$B$8+7,'My Colleges'!$H12-3)),"n/a")) | T12: =FALSE() -> FALSE | U12: =IF(OR($A12="",NOT(ISNUMBER($B12))),"",IF(LEFT('My Colleges'!$AB12,8)="Required",MAX($B12-7,MIN(Summary!$B$8+7,$B12-3)),"n/a")) | V12: =FALSE() -> FALSE | W12: =IF(OR($A12="",NOT(ISNUMBER($B12))),"",IF(TRUE(),$B12+10,"n/a")) | X12: =FALSE() -> FALSE | Y12: =IF(OR($A12="",NOT(ISNUMBER($B12))),"",IF('My Colleges'!$AC12<>"",$B12+21,"n/a")) | Z12: =FALSE() -> FALSE | AA12: =IF($A12="","",AB12-COUNT($AE12:$AO12)) | AB12: =IF($A12="","",SUMPRODUCT((MOD(COLUMN($C12:$X12)-COLUMN($C12),2)=0)*ISNUMBER($C12:$X12))) | AC12: =IF($A12="","",IF($B12="Dropped","Dropped",IF(NOT(ISNUMBER($B12)),"Set a deadline on My Colleges",IF(COUNT($AE12:$AP12)=0,"All steps done",INDEX($AE$6:$AP$6,MATCH(MIN($AE12:$AP12),$AE12:$AP12,0)))))) | AD12: =IF(COUNT($AE12:$AP12)=0,"",INT(MIN($AE12:$AP12))) | AE12: =IF(AND(ISNUMBER(C12),D12<>TRUE(),'My Colleges'!$T12<>"Submitted",'My Colleges'!$T12<>"Complete in portal"),C12+ROW()/1000+1/100000,"") | AF12: =IF(AND(ISNUMBER(E12),F12<>TRUE(),'My Colleges'!$T12<>"Submitted",'My Colleges'!$T12<>"Complete in portal"),E12+ROW()/1000+2/100000,"") | AG12: =IF(AND(ISNUMBER(G12),H12<>TRUE(),'My Colleges'!$T12<>"Submitted",'My Colleges'!$T12<>"Complete in portal"),G12+ROW()/1000+3/100000,"") | AH12: =IF(AND(ISNUMBER(I12),J12<>TRUE(),'My Colleges'!$T12<>"Submitted",'My Colleges'!$T12<>"Complete in portal"),I12+ROW()/1000+4/100000,"") | AI12: =IF(AND(ISNUMBER(K12),L12<>TRUE(),'My Colleges'!$T12<>"Submitted",'My Colleges'!$T12<>"Complete in portal"),K12+ROW()/1000+5/100000,"") | AJ12: =IF(AND(ISNUMBER(M12),N12<>TRUE(),'My Colleges'!$T12<>"Submitted",'My Colleges'!$T12<>"Complete in portal"),M12+ROW()/1000+6/100000,"") | AK12: =IF(AND(ISNUMBER(O12),P12<>TRUE(),'My Colleges'!$T12<>"Submitted",'My Colleges'!$T12<>"Complete in portal"),O12+ROW()/1000+7/100000,"") | AL12: =IF(AND(ISNUMBER(Q12),R12<>TRUE(),'My Colleges'!$T12<>"Submitted",'My Colleges'!$T12<>"Complete in portal"),Q12+ROW()/1000+8/100000,"") | AM12: =IF(AND(ISNUMBER(S12),T12<>TRUE()),S12+ROW()/1000+9/100000,"") | AN12: =IF(AND(ISNUMBER(U12),V12<>TRUE()),U12+ROW()/1000+10/100000,"") | AO12: =IF(AND(ISNUMBER(W12),X12<>TRUE()),W12+ROW()/1000+11/100000,"") | AP12: =IF(AND(ISNUMBER(Y12),Z12<>TRUE(),ISNUMBER(SEARCH("requir",'My Colleges'!$AC12))+ISNUMBER(SEARCH("evaluat",'My Colleges'!$AC12))>0),Y12+ROW()/1000+12/100000,"")
A13: =IF('My Colleges'!$B13="","",'My Colleges'!$B13) | B13: =IF($A13="","",IF('My Colleges'!$V13="No","Dropped",'My Colleges'!$I13)) | C13: =IF(OR($A13="",NOT(ISNUMBER($B13))),"",IF(TRUE(),MAX($B13-35,MIN(Summary!$B$8+7,$B13-3)),"n/a")) | D13: =FALSE() -> FALSE | E13: =IF(OR($A13="",NOT(ISNUMBER($B13))),"",IF(NOT(OR('My Colleges'!$O13="None",'My Colleges'!$O13="None required")),MAX($B13-21,MIN(Summary!$B$8+7,$B13-3)),"n/a")) | F13: =FALSE() -> FALSE | G13: =IF(OR($A13="",NOT(ISNUMBER($B13))),"",IF(NOT(AND(ISNUMBER('My Colleges'!$P13),'My Colleges'!$P13=0)),MAX($B13-28,MIN(Summary!$B$8+7,$B13-3)),"n/a")) | H13: =FALSE() -> FALSE | I13: =IF(OR($A13="",NOT(ISNUMBER($B13))),"",IF(NOT(AND(ISNUMBER('My Colleges'!$P13),'My Colleges'!$P13=0)),MAX($B13-10,MIN(Summary!$B$8+7,$B13-3)),"n/a")) | J13: =FALSE() -> FALSE | K13: =IF(OR($A13="",NOT(ISNUMBER($B13))),"",IF(TRUE(),MAX($B13-14,MIN(Summary!$B$8+7,$B13-3)),"n/a")) | L13: =FALSE() -> FALSE | M13: =IF(OR($A13="",NOT(ISNUMBER($B13))),"",IF(AND('My Colleges'!$N13<>"Blind",OR('My Colleges'!$N13="Required",ISNUMBER(Me!$B$13),ISNUMBER(Me!$B$14))),MAX($B13-14,MIN(Summary!$B$8+7,$B13-3)),"n/a")) | N13: =FALSE() -> FALSE | O13: =IF(OR($A13="",NOT(ISNUMBER($B13))),"",IF(NOT(AND(ISNUMBER('My Colleges'!$L13),'My Colleges'!$L13=0)),MAX($B13-5,MIN(Summary!$B$8+7,$B13-3)),"n/a")) | P13: =FALSE() -> FALSE | Q13: =IF(OR($A13="",NOT(ISNUMBER($B13))),"",IF(TRUE(),$B13-3,"n/a")) | R13: =FALSE() -> FALSE | S13: =IF(OR($A13="",NOT(ISNUMBER($B13))),"",IF(ISNUMBER('My Colleges'!$H13),MAX('My Colleges'!$H13-7,MIN(Summary!$B$8+7,'My Colleges'!$H13-3)),"n/a")) | T13: =FALSE() -> FALSE | U13: =IF(OR($A13="",NOT(ISNUMBER($B13))),"",IF(LEFT('My Colleges'!$AB13,8)="Required",MAX($B13-7,MIN(Summary!$B$8+7,$B13-3)),"n/a")) | V13: =FALSE() -> FALSE | W13: =IF(OR($A13="",NOT(ISNUMBER($B13))),"",IF(TRUE(),$B13+10,"n/a")) | X13: =FALSE() -> FALSE | Y13: =IF(OR($A13="",NOT(ISNUMBER($B13))),"",IF('My Colleges'!$AC13<>"",$B13+21,"n/a")) | Z13: =FALSE() -> FALSE | AA13: =IF($A13="","",AB13-COUNT($AE13:$AO13)) | AB13: =IF($A13="","",SUMPRODUCT((MOD(COLUMN($C13:$X13)-COLUMN($C13),2)=0)*ISNUMBER($C13:$X13))) | AC13: =IF($A13="","",IF($B13="Dropped","Dropped",IF(NOT(ISNUMBER($B13)),"Set a deadline on My Colleges",IF(COUNT($AE13:$AP13)=0,"All steps done",INDEX($AE$6:$AP$6,MATCH(MIN($AE13:$AP13),$AE13:$AP13,0)))))) | AD13: =IF(COUNT($AE13:$AP13)=0,"",INT(MIN($AE13:$AP13))) | AE13: =IF(AND(ISNUMBER(C13),D13<>TRUE(),'My Colleges'!$T13<>"Submitted",'My Colleges'!$T13<>"Complete in portal"),C13+ROW()/1000+1/100000,"") | AF13: =IF(AND(ISNUMBER(E13),F13<>TRUE(),'My Colleges'!$T13<>"Submitted",'My Colleges'!$T13<>"Complete in portal"),E13+ROW()/1000+2/100000,"") | AG13: =IF(AND(ISNUMBER(G13),H13<>TRUE(),'My Colleges'!$T13<>"Submitted",'My Colleges'!$T13<>"Complete in portal"),G13+ROW()/1000+3/100000,"") | AH13: =IF(AND(ISNUMBER(I13),J13<>TRUE(),'My Colleges'!$T13<>"Submitted",'My Colleges'!$T13<>"Complete in portal"),I13+ROW()/1000+4/100000,"") | AI13: =IF(AND(ISNUMBER(K13),L13<>TRUE(),'My Colleges'!$T13<>"Submitted",'My Colleges'!$T13<>"Complete in portal"),K13+ROW()/1000+5/100000,"") | AJ13: =IF(AND(ISNUMBER(M13),N13<>TRUE(),'My Colleges'!$T13<>"Submitted",'My Colleges'!$T13<>"Complete in portal"),M13+ROW()/1000+6/100000,"") | AK13: =IF(AND(ISNUMBER(O13),P13<>TRUE(),'My Colleges'!$T13<>"Submitted",'My Colleges'!$T13<>"Complete in portal"),O13+ROW()/1000+7/100000,"") | AL13: =IF(AND(ISNUMBER(Q13),R13<>TRUE(),'My Colleges'!$T13<>"Submitted",'My Colleges'!$T13<>"Complete in portal"),Q13+ROW()/1000+8/100000,"") | AM13: =IF(AND(ISNUMBER(S13),T13<>TRUE()),S13+ROW()/1000+9/100000,"") | AN13: =IF(AND(ISNUMBER(U13),V13<>TRUE()),U13+ROW()/1000+10/100000,"") | AO13: =IF(AND(ISNUMBER(W13),X13<>TRUE()),W13+ROW()/1000+11/100000,"") | AP13: =IF(AND(ISNUMBER(Y13),Z13<>TRUE(),ISNUMBER(SEARCH("requir",'My Colleges'!$AC13))+ISNUMBER(SEARCH("evaluat",'My Colleges'!$AC13))>0),Y13+ROW()/1000+12/100000,"")
A14: =IF('My Colleges'!$B14="","",'My Colleges'!$B14) | B14: =IF($A14="","",IF('My Colleges'!$V14="No","Dropped",'My Colleges'!$I14)) | C14: =IF(OR($A14="",NOT(ISNUMBER($B14))),"",IF(TRUE(),MAX($B14-35,MIN(Summary!$B$8+7,$B14-3)),"n/a")) | D14: =FALSE() -> FALSE | E14: =IF(OR($A14="",NOT(ISNUMBER($B14))),"",IF(NOT(OR('My Colleges'!$O14="None",'My Colleges'!$O14="None required")),MAX($B14-21,MIN(Summary!$B$8+7,$B14-3)),"n/a")) | F14: =FALSE() -> FALSE | G14: =IF(OR($A14="",NOT(ISNUMBER($B14))),"",IF(NOT(AND(ISNUMBER('My Colleges'!$P14),'My Colleges'!$P14=0)),MAX($B14-28,MIN(Summary!$B$8+7,$B14-3)),"n/a")) | H14: =FALSE() -> FALSE | I14: =IF(OR($A14="",NOT(ISNUMBER($B14))),"",IF(NOT(AND(ISNUMBER('My Colleges'!$P14),'My Colleges'!$P14=0)),MAX($B14-10,MIN(Summary!$B$8+7,$B14-3)),"n/a")) | J14: =FALSE() -> FALSE | K14: =IF(OR($A14="",NOT(ISNUMBER($B14))),"",IF(TRUE(),MAX($B14-14,MIN(Summary!$B$8+7,$B14-3)),"n/a")) | L14: =FALSE() -> FALSE | M14: =IF(OR($A14="",NOT(ISNUMBER($B14))),"",IF(AND('My Colleges'!$N14<>"Blind",OR('My Colleges'!$N14="Required",ISNUMBER(Me!$B$13),ISNUMBER(Me!$B$14))),MAX($B14-14,MIN(Summary!$B$8+7,$B14-3)),"n/a")) | N14: =FALSE() -> FALSE | O14: =IF(OR($A14="",NOT(ISNUMBER($B14))),"",IF(NOT(AND(ISNUMBER('My Colleges'!$L14),'My Colleges'!$L14=0)),MAX($B14-5,MIN(Summary!$B$8+7,$B14-3)),"n/a")) | P14: =FALSE() -> FALSE | Q14: =IF(OR($A14="",NOT(ISNUMBER($B14))),"",IF(TRUE(),$B14-3,"n/a")) | R14: =FALSE() -> FALSE | S14: =IF(OR($A14="",NOT(ISNUMBER($B14))),"",IF(ISNUMBER('My Colleges'!$H14),MAX('My Colleges'!$H14-7,MIN(Summary!$B$8+7,'My Colleges'!$H14-3)),"n/a")) | T14: =FALSE() -> FALSE | U14: =IF(OR($A14="",NOT(ISNUMBER($B14))),"",IF(LEFT('My Colleges'!$AB14,8)="Required",MAX($B14-7,MIN(Summary!$B$8+7,$B14-3)),"n/a")) | V14: =FALSE() -> FALSE | W14: =IF(OR($A14="",NOT(ISNUMBER($B14))),"",IF(TRUE(),$B14+10,"n/a")) | X14: =FALSE() -> FALSE | Y14: =IF(OR($A14="",NOT(ISNUMBER($B14))),"",IF('My Colleges'!$AC14<>"",$B14+21,"n/a")) | Z14: =FALSE() -> FALSE | AA14: =IF($A14="","",AB14-COUNT($AE14:$AO14)) | AB14: =IF($A14="","",SUMPRODUCT((MOD(COLUMN($C14:$X14)-COLUMN($C14),2)=0)*ISNUMBER($C14:$X14))) | AC14: =IF($A14="","",IF($B14="Dropped","Dropped",IF(NOT(ISNUMBER($B14)),"Set a deadline on My Colleges",IF(COUNT($AE14:$AP14)=0,"All steps done",INDEX($AE$6:$AP$6,MATCH(MIN($AE14:$AP14),$AE14:$AP14,0)))))) | AD14: =IF(COUNT($AE14:$AP14)=0,"",INT(MIN($AE14:$AP14))) | AE14: =IF(AND(ISNUMBER(C14),D14<>TRUE(),'My Colleges'!$T14<>"Submitted",'My Colleges'!$T14<>"Complete in portal"),C14+ROW()/1000+1/100000,"") | AF14: =IF(AND(ISNUMBER(E14),F14<>TRUE(),'My Colleges'!$T14<>"Submitted",'My Colleges'!$T14<>"Complete in portal"),E14+ROW()/1000+2/100000,"") | AG14: =IF(AND(ISNUMBER(G14),H14<>TRUE(),'My Colleges'!$T14<>"Submitted",'My Colleges'!$T14<>"Complete in portal"),G14+ROW()/1000+3/100000,"") | AH14: =IF(AND(ISNUMBER(I14),J14<>TRUE(),'My Colleges'!$T14<>"Submitted",'My Colleges'!$T14<>"Complete in portal"),I14+ROW()/1000+4/100000,"") | AI14: =IF(AND(ISNUMBER(K14),L14<>TRUE(),'My Colleges'!$T14<>"Submitted",'My Colleges'!$T14<>"Complete in portal"),K14+ROW()/1000+5/100000,"") | AJ14: =IF(AND(ISNUMBER(M14),N14<>TRUE(),'My Colleges'!$T14<>"Submitted",'My Colleges'!$T14<>"Complete in portal"),M14+ROW()/1000+6/100000,"") | AK14: =IF(AND(ISNUMBER(O14),P14<>TRUE(),'My Colleges'!$T14<>"Submitted",'My Colleges'!$T14<>"Complete in portal"),O14+ROW()/1000+7/100000,"") | AL14: =IF(AND(ISNUMBER(Q14),R14<>TRUE(),'My Colleges'!$T14<>"Submitted",'My Colleges'!$T14<>"Complete in portal"),Q14+ROW()/1000+8/100000,"") | AM14: =IF(AND(ISNUMBER(S14),T14<>TRUE()),S14+ROW()/1000+9/100000,"") | AN14: =IF(AND(ISNUMBER(U14),V14<>TRUE()),U14+ROW()/1000+10/100000,"") | AO14: =IF(AND(ISNUMBER(W14),X14<>TRUE()),W14+ROW()/1000+11/100000,"") | AP14: =IF(AND(ISNUMBER(Y14),Z14<>TRUE(),ISNUMBER(SEARCH("requir",'My Colleges'!$AC14))+ISNUMBER(SEARCH("evaluat",'My Colleges'!$AC14))>0),Y14+ROW()/1000+12/100000,"")
A15: =IF('My Colleges'!$B15="","",'My Colleges'!$B15) | B15: =IF($A15="","",IF('My Colleges'!$V15="No","Dropped",'My Colleges'!$I15)) | C15: =IF(OR($A15="",NOT(ISNUMBER($B15))),"",IF(TRUE(),MAX($B15-35,MIN(Summary!$B$8+7,$B15-3)),"n/a")) | D15: =FALSE() -> FALSE | E15: =IF(OR($A15="",NOT(ISNUMBER($B15))),"",IF(NOT(OR('My Colleges'!$O15="None",'My Colleges'!$O15="None required")),MAX($B15-21,MIN(Summary!$B$8+7,$B15-3)),"n/a")) | F15: =FALSE() -> FALSE | G15: =IF(OR($A15="",NOT(ISNUMBER($B15))),"",IF(NOT(AND(ISNUMBER('My Colleges'!$P15),'My Colleges'!$P15=0)),MAX($B15-28,MIN(Summary!$B$8+7,$B15-3)),"n/a")) | H15: =FALSE() -> FALSE | I15: =IF(OR($A15="",NOT(ISNUMBER($B15))),"",IF(NOT(AND(ISNUMBER('My Colleges'!$P15),'My Colleges'!$P15=0)),MAX($B15-10,MIN(Summary!$B$8+7,$B15-3)),"n/a")) | J15: =FALSE() -> FALSE | K15: =IF(OR($A15="",NOT(ISNUMBER($B15))),"",IF(TRUE(),MAX($B15-14,MIN(Summary!$B$8+7,$B15-3)),"n/a")) | L15: =FALSE() -> FALSE | M15: =IF(OR($A15="",NOT(ISNUMBER($B15))),"",IF(AND('My Colleges'!$N15<>"Blind",OR('My Colleges'!$N15="Required",ISNUMBER(Me!$B$13),ISNUMBER(Me!$B$14))),MAX($B15-14,MIN(Summary!$B$8+7,$B15-3)),"n/a")) | N15: =FALSE() -> FALSE | O15: =IF(OR($A15="",NOT(ISNUMBER($B15))),"",IF(NOT(AND(ISNUMBER('My Colleges'!$L15),'My Colleges'!$L15=0)),MAX($B15-5,MIN(Summary!$B$8+7,$B15-3)),"n/a")) | P15: =FALSE() -> FALSE | Q15: =IF(OR($A15="",NOT(ISNUMBER($B15))),"",IF(TRUE(),$B15-3,"n/a")) | R15: =FALSE() -> FALSE | S15: =IF(OR($A15="",NOT(ISNUMBER($B15))),"",IF(ISNUMBER('My Colleges'!$H15),MAX('My Colleges'!$H15-7,MIN(Summary!$B$8+7,'My Colleges'!$H15-3)),"n/a")) | T15: =FALSE() -> FALSE | U15: =IF(OR($A15="",NOT(ISNUMBER($B15))),"",IF(LEFT('My Colleges'!$AB15,8)="Required",MAX($B15-7,MIN(Summary!$B$8+7,$B15-3)),"n/a")) | V15: =FALSE() -> FALSE | W15: =IF(OR($A15="",NOT(ISNUMBER($B15))),"",IF(TRUE(),$B15+10,"n/a")) | X15: =FALSE() -> FALSE | Y15: =IF(OR($A15="",NOT(ISNUMBER($B15))),"",IF('My Colleges'!$AC15<>"",$B15+21,"n/a")) | Z15: =FALSE() -> FALSE | AA15: =IF($A15="","",AB15-COUNT($AE15:$AO15)) | AB15: =IF($A15="","",SUMPRODUCT((MOD(COLUMN($C15:$X15)-COLUMN($C15),2)=0)*ISNUMBER($C15:$X15))) | AC15: =IF($A15="","",IF($B15="Dropped","Dropped",IF(NOT(ISNUMBER($B15)),"Set a deadline on My Colleges",IF(COUNT($AE15:$AP15)=0,"All steps done",INDEX($AE$6:$AP$6,MATCH(MIN($AE15:$AP15),$AE15:$AP15,0)))))) | AD15: =IF(COUNT($AE15:$AP15)=0,"",INT(MIN($AE15:$AP15))) | AE15: =IF(AND(ISNUMBER(C15),D15<>TRUE(),'My Colleges'!$T15<>"Submitted",'My Colleges'!$T15<>"Complete in portal"),C15+ROW()/1000+1/100000,"") | AF15: =IF(AND(ISNUMBER(E15),F15<>TRUE(),'My Colleges'!$T15<>"Submitted",'My Colleges'!$T15<>"Complete in portal"),E15+ROW()/1000+2/100000,"") | AG15: =IF(AND(ISNUMBER(G15),H15<>TRUE(),'My Colleges'!$T15<>"Submitted",'My Colleges'!$T15<>"Complete in portal"),G15+ROW()/1000+3/100000,"") | AH15: =IF(AND(ISNUMBER(I15),J15<>TRUE(),'My Colleges'!$T15<>"Submitted",'My Colleges'!$T15<>"Complete in portal"),I15+ROW()/1000+4/100000,"") | AI15: =IF(AND(ISNUMBER(K15),L15<>TRUE(),'My Colleges'!$T15<>"Submitted",'My Colleges'!$T15<>"Complete in portal"),K15+ROW()/1000+5/100000,"") | AJ15: =IF(AND(ISNUMBER(M15),N15<>TRUE(),'My Colleges'!$T15<>"Submitted",'My Colleges'!$T15<>"Complete in portal"),M15+ROW()/1000+6/100000,"") | AK15: =IF(AND(ISNUMBER(O15),P15<>TRUE(),'My Colleges'!$T15<>"Submitted",'My Colleges'!$T15<>"Complete in portal"),O15+ROW()/1000+7/100000,"") | AL15: =IF(AND(ISNUMBER(Q15),R15<>TRUE(),'My Colleges'!$T15<>"Submitted",'My Colleges'!$T15<>"Complete in portal"),Q15+ROW()/1000+8/100000,"") | AM15: =IF(AND(ISNUMBER(S15),T15<>TRUE()),S15+ROW()/1000+9/100000,"") | AN15: =IF(AND(ISNUMBER(U15),V15<>TRUE()),U15+ROW()/1000+10/100000,"") | AO15: =IF(AND(ISNUMBER(W15),X15<>TRUE()),W15+ROW()/1000+11/100000,"") | AP15: =IF(AND(ISNUMBER(Y15),Z15<>TRUE(),ISNUMBER(SEARCH("requir",'My Colleges'!$AC15))+ISNUMBER(SEARCH("evaluat",'My Colleges'!$AC15))>0),Y15+ROW()/1000+12/100000,"")
A16: =IF('My Colleges'!$B16="","",'My Colleges'!$B16) | B16: =IF($A16="","",IF('My Colleges'!$V16="No","Dropped",'My Colleges'!$I16)) | C16: =IF(OR($A16="",NOT(ISNUMBER($B16))),"",IF(TRUE(),MAX($B16-35,MIN(Summary!$B$8+7,$B16-3)),"n/a")) | D16: =FALSE() -> FALSE | E16: =IF(OR($A16="",NOT(ISNUMBER($B16))),"",IF(NOT(OR('My Colleges'!$O16="None",'My Colleges'!$O16="None required")),MAX($B16-21,MIN(Summary!$B$8+7,$B16-3)),"n/a")) | F16: =FALSE() -> FALSE | G16: =IF(OR($A16="",NOT(ISNUMBER($B16))),"",IF(NOT(AND(ISNUMBER('My Colleges'!$P16),'My Colleges'!$P16=0)),MAX($B16-28,MIN(Summary!$B$8+7,$B16-3)),"n/a")) | H16: =FALSE() -> FALSE | I16: =IF(OR($A16="",NOT(ISNUMBER($B16))),"",IF(NOT(AND(ISNUMBER('My Colleges'!$P16),'My Colleges'!$P16=0)),MAX($B16-10,MIN(Summary!$B$8+7,$B16-3)),"n/a")) | J16: =FALSE() -> FALSE | K16: =IF(OR($A16="",NOT(ISNUMBER($B16))),"",IF(TRUE(),MAX($B16-14,MIN(Summary!$B$8+7,$B16-3)),"n/a")) | L16: =FALSE() -> FALSE | M16: =IF(OR($A16="",NOT(ISNUMBER($B16))),"",IF(AND('My Colleges'!$N16<>"Blind",OR('My Colleges'!$N16="Required",ISNUMBER(Me!$B$13),ISNUMBER(Me!$B$14))),MAX($B16-14,MIN(Summary!$B$8+7,$B16-3)),"n/a")) | N16: =FALSE() -> FALSE | O16: =IF(OR($A16="",NOT(ISNUMBER($B16))),"",IF(NOT(AND(ISNUMBER('My Colleges'!$L16),'My Colleges'!$L16=0)),MAX($B16-5,MIN(Summary!$B$8+7,$B16-3)),"n/a")) | P16: =FALSE() -> FALSE | Q16: =IF(OR($A16="",NOT(ISNUMBER($B16))),"",IF(TRUE(),$B16-3,"n/a")) | R16: =FALSE() -> FALSE | S16: =IF(OR($A16="",NOT(ISNUMBER($B16))),"",IF(ISNUMBER('My Colleges'!$H16),MAX('My Colleges'!$H16-7,MIN(Summary!$B$8+7,'My Colleges'!$H16-3)),"n/a")) | T16: =FALSE() -> FALSE | U16: =IF(OR($A16="",NOT(ISNUMBER($B16))),"",IF(LEFT('My Colleges'!$AB16,8)="Required",MAX($B16-7,MIN(Summary!$B$8+7,$B16-3)),"n/a")) | V16: =FALSE() -> FALSE | W16: =IF(OR($A16="",NOT(ISNUMBER($B16))),"",IF(TRUE(),$B16+10,"n/a")) | X16: =FALSE() -> FALSE | Y16: =IF(OR($A16="",NOT(ISNUMBER($B16))),"",IF('My Colleges'!$AC16<>"",$B16+21,"n/a")) | Z16: =FALSE() -> FALSE | AA16: =IF($A16="","",AB16-COUNT($AE16:$AO16)) | AB16: =IF($A16="","",SUMPRODUCT((MOD(COLUMN($C16:$X16)-COLUMN($C16),2)=0)*ISNUMBER($C16:$X16))) | AC16: =IF($A16="","",IF($B16="Dropped","Dropped",IF(NOT(ISNUMBER($B16)),"Set a deadline on My Colleges",IF(COUNT($AE16:$AP16)=0,"All steps done",INDEX($AE$6:$AP$6,MATCH(MIN($AE16:$AP16),$AE16:$AP16,0)))))) | AD16: =IF(COUNT($AE16:$AP16)=0,"",INT(MIN($AE16:$AP16))) | AE16: =IF(AND(ISNUMBER(C16),D16<>TRUE(),'My Colleges'!$T16<>"Submitted",'My Colleges'!$T16<>"Complete in portal"),C16+ROW()/1000+1/100000,"") | AF16: =IF(AND(ISNUMBER(E16),F16<>TRUE(),'My Colleges'!$T16<>"Submitted",'My Colleges'!$T16<>"Complete in portal"),E16+ROW()/1000+2/100000,"") | AG16: =IF(AND(ISNUMBER(G16),H16<>TRUE(),'My Colleges'!$T16<>"Submitted",'My Colleges'!$T16<>"Complete in portal"),G16+ROW()/1000+3/100000,"") | AH16: =IF(AND(ISNUMBER(I16),J16<>TRUE(),'My Colleges'!$T16<>"Submitted",'My Colleges'!$T16<>"Complete in portal"),I16+ROW()/1000+4/100000,"") | AI16: =IF(AND(ISNUMBER(K16),L16<>TRUE(),'My Colleges'!$T16<>"Submitted",'My Colleges'!$T16<>"Complete in portal"),K16+ROW()/1000+5/100000,"") | AJ16: =IF(AND(ISNUMBER(M16),N16<>TRUE(),'My Colleges'!$T16<>"Submitted",'My Colleges'!$T16<>"Complete in portal"),M16+ROW()/1000+6/100000,"") | AK16: =IF(AND(ISNUMBER(O16),P16<>TRUE(),'My Colleges'!$T16<>"Submitted",'My Colleges'!$T16<>"Complete in portal"),O16+ROW()/1000+7/100000,"") | AL16: =IF(AND(ISNUMBER(Q16),R16<>TRUE(),'My Colleges'!$T16<>"Submitted",'My Colleges'!$T16<>"Complete in portal"),Q16+ROW()/1000+8/100000,"") | AM16: =IF(AND(ISNUMBER(S16),T16<>TRUE()),S16+ROW()/1000+9/100000,"") | AN16: =IF(AND(ISNUMBER(U16),V16<>TRUE()),U16+ROW()/1000+10/100000,"") | AO16: =IF(AND(ISNUMBER(W16),X16<>TRUE()),W16+ROW()/1000+11/100000,"") | AP16: =IF(AND(ISNUMBER(Y16),Z16<>TRUE(),ISNUMBER(SEARCH("requir",'My Colleges'!$AC16))+ISNUMBER(SEARCH("evaluat",'My Colleges'!$AC16))>0),Y16+ROW()/1000+12/100000,"")
A17: =IF('My Colleges'!$B17="","",'My Colleges'!$B17) | B17: =IF($A17="","",IF('My Colleges'!$V17="No","Dropped",'My Colleges'!$I17)) | C17: =IF(OR($A17="",NOT(ISNUMBER($B17))),"",IF(TRUE(),MAX($B17-35,MIN(Summary!$B$8+7,$B17-3)),"n/a")) | D17: =FALSE() -> FALSE | E17: =IF(OR($A17="",NOT(ISNUMBER($B17))),"",IF(NOT(OR('My Colleges'!$O17="None",'My Colleges'!$O17="None required")),MAX($B17-21,MIN(Summary!$B$8+7,$B17-3)),"n/a")) | F17: =FALSE() -> FALSE | G17: =IF(OR($A17="",NOT(ISNUMBER($B17))),"",IF(NOT(AND(ISNUMBER('My Colleges'!$P17),'My Colleges'!$P17=0)),MAX($B17-28,MIN(Summary!$B$8+7,$B17-3)),"n/a")) | H17: =FALSE() -> FALSE | I17: =IF(OR($A17="",NOT(ISNUMBER($B17))),"",IF(NOT(AND(ISNUMBER('My Colleges'!$P17),'My Colleges'!$P17=0)),MAX($B17-10,MIN(Summary!$B$8+7,$B17-3)),"n/a")) | J17: =FALSE() -> FALSE | K17: =IF(OR($A17="",NOT(ISNUMBER($B17))),"",IF(TRUE(),MAX($B17-14,MIN(Summary!$B$8+7,$B17-3)),"n/a")) | L17: =FALSE() -> FALSE | M17: =IF(OR($A17="",NOT(ISNUMBER($B17))),"",IF(AND('My Colleges'!$N17<>"Blind",OR('My Colleges'!$N17="Required",ISNUMBER(Me!$B$13),ISNUMBER(Me!$B$14))),MAX($B17-14,MIN(Summary!$B$8+7,$B17-3)),"n/a")) | N17: =FALSE() -> FALSE | O17: =IF(OR($A17="",NOT(ISNUMBER($B17))),"",IF(NOT(AND(ISNUMBER('My Colleges'!$L17),'My Colleges'!$L17=0)),MAX($B17-5,MIN(Summary!$B$8+7,$B17-3)),"n/a")) | P17: =FALSE() -> FALSE | Q17: =IF(OR($A17="",NOT(ISNUMBER($B17))),"",IF(TRUE(),$B17-3,"n/a")) | R17: =FALSE() -> FALSE | S17: =IF(OR($A17="",NOT(ISNUMBER($B17))),"",IF(ISNUMBER('My Colleges'!$H17),MAX('My Colleges'!$H17-7,MIN(Summary!$B$8+7,'My Colleges'!$H17-3)),"n/a")) | T17: =FALSE() -> FALSE | U17: =IF(OR($A17="",NOT(ISNUMBER($B17))),"",IF(LEFT('My Colleges'!$AB17,8)="Required",MAX($B17-7,MIN(Summary!$B$8+7,$B17-3)),"n/a")) | V17: =FALSE() -> FALSE | W17: =IF(OR($A17="",NOT(ISNUMBER($B17))),"",IF(TRUE(),$B17+10,"n/a")) | X17: =FALSE() -> FALSE | Y17: =IF(OR($A17="",NOT(ISNUMBER($B17))),"",IF('My Colleges'!$AC17<>"",$B17+21,"n/a")) | Z17: =FALSE() -> FALSE | AA17: =IF($A17="","",AB17-COUNT($AE17:$AO17)) | AB17: =IF($A17="","",SUMPRODUCT((MOD(COLUMN($C17:$X17)-COLUMN($C17),2)=0)*ISNUMBER($C17:$X17))) | AC17: =IF($A17="","",IF($B17="Dropped","Dropped",IF(NOT(ISNUMBER($B17)),"Set a deadline on My Colleges",IF(COUNT($AE17:$AP17)=0,"All steps done",INDEX($AE$6:$AP$6,MATCH(MIN($AE17:$AP17),$AE17:$AP17,0)))))) | AD17: =IF(COUNT($AE17:$AP17)=0,"",INT(MIN($AE17:$AP17))) | AE17: =IF(AND(ISNUMBER(C17),D17<>TRUE(),'My Colleges'!$T17<>"Submitted",'My Colleges'!$T17<>"Complete in portal"),C17+ROW()/1000+1/100000,"") | AF17: =IF(AND(ISNUMBER(E17),F17<>TRUE(),'My Colleges'!$T17<>"Submitted",'My Colleges'!$T17<>"Complete in portal"),E17+ROW()/1000+2/100000,"") | AG17: =IF(AND(ISNUMBER(G17),H17<>TRUE(),'My Colleges'!$T17<>"Submitted",'My Colleges'!$T17<>"Complete in portal"),G17+ROW()/1000+3/100000,"") | AH17: =IF(AND(ISNUMBER(I17),J17<>TRUE(),'My Colleges'!$T17<>"Submitted",'My Colleges'!$T17<>"Complete in portal"),I17+ROW()/1000+4/100000,"") | AI17: =IF(AND(ISNUMBER(K17),L17<>TRUE(),'My Colleges'!$T17<>"Submitted",'My Colleges'!$T17<>"Complete in portal"),K17+ROW()/1000+5/100000,"") | AJ17: =IF(AND(ISNUMBER(M17),N17<>TRUE(),'My Colleges'!$T17<>"Submitted",'My Colleges'!$T17<>"Complete in portal"),M17+ROW()/1000+6/100000,"") | AK17: =IF(AND(ISNUMBER(O17),P17<>TRUE(),'My Colleges'!$T17<>"Submitted",'My Colleges'!$T17<>"Complete in portal"),O17+ROW()/1000+7/100000,"") | AL17: =IF(AND(ISNUMBER(Q17),R17<>TRUE(),'My Colleges'!$T17<>"Submitted",'My Colleges'!$T17<>"Complete in portal"),Q17+ROW()/1000+8/100000,"") | AM17: =IF(AND(ISNUMBER(S17),T17<>TRUE()),S17+ROW()/1000+9/100000,"") | AN17: =IF(AND(ISNUMBER(U17),V17<>TRUE()),U17+ROW()/1000+10/100000,"") | AO17: =IF(AND(ISNUMBER(W17),X17<>TRUE()),W17+ROW()/1000+11/100000,"") | AP17: =IF(AND(ISNUMBER(Y17),Z17<>TRUE(),ISNUMBER(SEARCH("requir",'My Colleges'!$AC17))+ISNUMBER(SEARCH("evaluat",'My Colleges'!$AC17))>0),Y17+ROW()/1000+12/100000,"")
A18: =IF('My Colleges'!$B18="","",'My Colleges'!$B18) | B18: =IF($A18="","",IF('My Colleges'!$V18="No","Dropped",'My Colleges'!$I18)) | C18: =IF(OR($A18="",NOT(ISNUMBER($B18))),"",IF(TRUE(),MAX($B18-35,MIN(Summary!$B$8+7,$B18-3)),"n/a")) | D18: =FALSE() -> FALSE | E18: =IF(OR($A18="",NOT(ISNUMBER($B18))),"",IF(NOT(OR('My Colleges'!$O18="None",'My Colleges'!$O18="None required")),MAX($B18-21,MIN(Summary!$B$8+7,$B18-3)),"n/a")) | F18: =FALSE() -> FALSE | G18: =IF(OR($A18="",NOT(ISNUMBER($B18))),"",IF(NOT(AND(ISNUMBER('My Colleges'!$P18),'My Colleges'!$P18=0)),MAX($B18-28,MIN(Summary!$B$8+7,$B18-3)),"n/a")) | H18: =FALSE() -> FALSE | I18: =IF(OR($A18="",NOT(ISNUMBER($B18))),"",IF(NOT(AND(ISNUMBER('My Colleges'!$P18),'My Colleges'!$P18=0)),MAX($B18-10,MIN(Summary!$B$8+7,$B18-3)),"n/a")) | J18: =FALSE() -> FALSE | K18: =IF(OR($A18="",NOT(ISNUMBER($B18))),"",IF(TRUE(),MAX($B18-14,MIN(Summary!$B$8+7,$B18-3)),"n/a")) | L18: =FALSE() -> FALSE | M18: =IF(OR($A18="",NOT(ISNUMBER($B18))),"",IF(AND('My Colleges'!$N18<>"Blind",OR('My Colleges'!$N18="Required",ISNUMBER(Me!$B$13),ISNUMBER(Me!$B$14))),MAX($B18-14,MIN(Summary!$B$8+7,$B18-3)),"n/a")) | N18: =FALSE() -> FALSE | O18: =IF(OR($A18="",NOT(ISNUMBER($B18))),"",IF(NOT(AND(ISNUMBER('My Colleges'!$L18),'My Colleges'!$L18=0)),MAX($B18-5,MIN(Summary!$B$8+7,$B18-3)),"n/a")) | P18: =FALSE() -> FALSE | Q18: =IF(OR($A18="",NOT(ISNUMBER($B18))),"",IF(TRUE(),$B18-3,"n/a")) | R18: =FALSE() -> FALSE | S18: =IF(OR($A18="",NOT(ISNUMBER($B18))),"",IF(ISNUMBER('My Colleges'!$H18),MAX('My Colleges'!$H18-7,MIN(Summary!$B$8+7,'My Colleges'!$H18-3)),"n/a")) | T18: =FALSE() -> FALSE | U18: =IF(OR($A18="",NOT(ISNUMBER($B18))),"",IF(LEFT('My Colleges'!$AB18,8)="Required",MAX($B18-7,MIN(Summary!$B$8+7,$B18-3)),"n/a")) | V18: =FALSE() -> FALSE | W18: =IF(OR($A18="",NOT(ISNUMBER($B18))),"",IF(TRUE(),$B18+10,"n/a")) | X18: =FALSE() -> FALSE | Y18: =IF(OR($A18="",NOT(ISNUMBER($B18))),"",IF('My Colleges'!$AC18<>"",$B18+21,"n/a")) | Z18: =FALSE() -> FALSE | AA18: =IF($A18="","",AB18-COUNT($AE18:$AO18)) | AB18: =IF($A18="","",SUMPRODUCT((MOD(COLUMN($C18:$X18)-COLUMN($C18),2)=0)*ISNUMBER($C18:$X18))) | AC18: =IF($A18="","",IF($B18="Dropped","Dropped",IF(NOT(ISNUMBER($B18)),"Set a deadline on My Colleges",IF(COUNT($AE18:$AP18)=0,"All steps done",INDEX($AE$6:$AP$6,MATCH(MIN($AE18:$AP18),$AE18:$AP18,0)))))) | AD18: =IF(COUNT($AE18:$AP18)=0,"",INT(MIN($AE18:$AP18))) | AE18: =IF(AND(ISNUMBER(C18),D18<>TRUE(),'My Colleges'!$T18<>"Submitted",'My Colleges'!$T18<>"Complete in portal"),C18+ROW()/1000+1/100000,"") | AF18: =IF(AND(ISNUMBER(E18),F18<>TRUE(),'My Colleges'!$T18<>"Submitted",'My Colleges'!$T18<>"Complete in portal"),E18+ROW()/1000+2/100000,"") | AG18: =IF(AND(ISNUMBER(G18),H18<>TRUE(),'My Colleges'!$T18<>"Submitted",'My Colleges'!$T18<>"Complete in portal"),G18+ROW()/1000+3/100000,"") | AH18: =IF(AND(ISNUMBER(I18),J18<>TRUE(),'My Colleges'!$T18<>"Submitted",'My Colleges'!$T18<>"Complete in portal"),I18+ROW()/1000+4/100000,"") | AI18: =IF(AND(ISNUMBER(K18),L18<>TRUE(),'My Colleges'!$T18<>"Submitted",'My Colleges'!$T18<>"Complete in portal"),K18+ROW()/1000+5/100000,"") | AJ18: =IF(AND(ISNUMBER(M18),N18<>TRUE(),'My Colleges'!$T18<>"Submitted",'My Colleges'!$T18<>"Complete in portal"),M18+ROW()/1000+6/100000,"") | AK18: =IF(AND(ISNUMBER(O18),P18<>TRUE(),'My Colleges'!$T18<>"Submitted",'My Colleges'!$T18<>"Complete in portal"),O18+ROW()/1000+7/100000,"") | AL18: =IF(AND(ISNUMBER(Q18),R18<>TRUE(),'My Colleges'!$T18<>"Submitted",'My Colleges'!$T18<>"Complete in portal"),Q18+ROW()/1000+8/100000,"") | AM18: =IF(AND(ISNUMBER(S18),T18<>TRUE()),S18+ROW()/1000+9/100000,"") | AN18: =IF(AND(ISNUMBER(U18),V18<>TRUE()),U18+ROW()/1000+10/100000,"") | AO18: =IF(AND(ISNUMBER(W18),X18<>TRUE()),W18+ROW()/1000+11/100000,"") | AP18: =IF(AND(ISNUMBER(Y18),Z18<>TRUE(),ISNUMBER(SEARCH("requir",'My Colleges'!$AC18))+ISNUMBER(SEARCH("evaluat",'My Colleges'!$AC18))>0),Y18+ROW()/1000+12/100000,"")
A19: =IF('My Colleges'!$B19="","",'My Colleges'!$B19) | B19: =IF($A19="","",IF('My Colleges'!$V19="No","Dropped",'My Colleges'!$I19)) | C19: =IF(OR($A19="",NOT(ISNUMBER($B19))),"",IF(TRUE(),MAX($B19-35,MIN(Summary!$B$8+7,$B19-3)),"n/a")) | D19: =FALSE() -> FALSE | E19: =IF(OR($A19="",NOT(ISNUMBER($B19))),"",IF(NOT(OR('My Colleges'!$O19="None",'My Colleges'!$O19="None required")),MAX($B19-21,MIN(Summary!$B$8+7,$B19-3)),"n/a")) | F19: =FALSE() -> FALSE | G19: =IF(OR($A19="",NOT(ISNUMBER($B19))),"",IF(NOT(AND(ISNUMBER('My Colleges'!$P19),'My Colleges'!$P19=0)),MAX($B19-28,MIN(Summary!$B$8+7,$B19-3)),"n/a")) | H19: =FALSE() -> FALSE | I19: =IF(OR($A19="",NOT(ISNUMBER($B19))),"",IF(NOT(AND(ISNUMBER('My Colleges'!$P19),'My Colleges'!$P19=0)),MAX($B19-10,MIN(Summary!$B$8+7,$B19-3)),"n/a")) | J19: =FALSE() -> FALSE | K19: =IF(OR($A19="",NOT(ISNUMBER($B19))),"",IF(TRUE(),MAX($B19-14,MIN(Summary!$B$8+7,$B19-3)),"n/a")) | L19: =FALSE() -> FALSE | M19: =IF(OR($A19="",NOT(ISNUMBER($B19))),"",IF(AND('My Colleges'!$N19<>"Blind",OR('My Colleges'!$N19="Required",ISNUMBER(Me!$B$13),ISNUMBER(Me!$B$14))),MAX($B19-14,MIN(Summary!$B$8+7,$B19-3)),"n/a")) | N19: =FALSE() -> FALSE | O19: =IF(OR($A19="",NOT(ISNUMBER($B19))),"",IF(NOT(AND(ISNUMBER('My Colleges'!$L19),'My Colleges'!$L19=0)),MAX($B19-5,MIN(Summary!$B$8+7,$B19-3)),"n/a")) | P19: =FALSE() -> FALSE | Q19: =IF(OR($A19="",NOT(ISNUMBER($B19))),"",IF(TRUE(),$B19-3,"n/a")) | R19: =FALSE() -> FALSE | S19: =IF(OR($A19="",NOT(ISNUMBER($B19))),"",IF(ISNUMBER('My Colleges'!$H19),MAX('My Colleges'!$H19-7,MIN(Summary!$B$8+7,'My Colleges'!$H19-3)),"n/a")) | T19: =FALSE() -> FALSE | U19: =IF(OR($A19="",NOT(ISNUMBER($B19))),"",IF(LEFT('My Colleges'!$AB19,8)="Required",MAX($B19-7,MIN(Summary!$B$8+7,$B19-3)),"n/a")) | V19: =FALSE() -> FALSE | W19: =IF(OR($A19="",NOT(ISNUMBER($B19))),"",IF(TRUE(),$B19+10,"n/a")) | X19: =FALSE() -> FALSE | Y19: =IF(OR($A19="",NOT(ISNUMBER($B19))),"",IF('My Colleges'!$AC19<>"",$B19+21,"n/a")) | Z19: =FALSE() -> FALSE | AA19: =IF($A19="","",AB19-COUNT($AE19:$AO19)) | AB19: =IF($A19="","",SUMPRODUCT((MOD(COLUMN($C19:$X19)-COLUMN($C19),2)=0)*ISNUMBER($C19:$X19))) | AC19: =IF($A19="","",IF($B19="Dropped","Dropped",IF(NOT(ISNUMBER($B19)),"Set a deadline on My Colleges",IF(COUNT($AE19:$AP19)=0,"All steps done",INDEX($AE$6:$AP$6,MATCH(MIN($AE19:$AP19),$AE19:$AP19,0)))))) | AD19: =IF(COUNT($AE19:$AP19)=0,"",INT(MIN($AE19:$AP19))) | AE19: =IF(AND(ISNUMBER(C19),D19<>TRUE(),'My Colleges'!$T19<>"Submitted",'My Colleges'!$T19<>"Complete in portal"),C19+ROW()/1000+1/100000,"") | AF19: =IF(AND(ISNUMBER(E19),F19<>TRUE(),'My Colleges'!$T19<>"Submitted",'My Colleges'!$T19<>"Complete in portal"),E19+ROW()/1000+2/100000,"") | AG19: =IF(AND(ISNUMBER(G19),H19<>TRUE(),'My Colleges'!$T19<>"Submitted",'My Colleges'!$T19<>"Complete in portal"),G19+ROW()/1000+3/100000,"") | AH19: =IF(AND(ISNUMBER(I19),J19<>TRUE(),'My Colleges'!$T19<>"Submitted",'My Colleges'!$T19<>"Complete in portal"),I19+ROW()/1000+4/100000,"") | AI19: =IF(AND(ISNUMBER(K19),L19<>TRUE(),'My Colleges'!$T19<>"Submitted",'My Colleges'!$T19<>"Complete in portal"),K19+ROW()/1000+5/100000,"") | AJ19: =IF(AND(ISNUMBER(M19),N19<>TRUE(),'My Colleges'!$T19<>"Submitted",'My Colleges'!$T19<>"Complete in portal"),M19+ROW()/1000+6/100000,"") | AK19: =IF(AND(ISNUMBER(O19),P19<>TRUE(),'My Colleges'!$T19<>"Submitted",'My Colleges'!$T19<>"Complete in portal"),O19+ROW()/1000+7/100000,"") | AL19: =IF(AND(ISNUMBER(Q19),R19<>TRUE(),'My Colleges'!$T19<>"Submitted",'My Colleges'!$T19<>"Complete in portal"),Q19+ROW()/1000+8/100000,"") | AM19: =IF(AND(ISNUMBER(S19),T19<>TRUE()),S19+ROW()/1000+9/100000,"") | AN19: =IF(AND(ISNUMBER(U19),V19<>TRUE()),U19+ROW()/1000+10/100000,"") | AO19: =IF(AND(ISNUMBER(W19),X19<>TRUE()),W19+ROW()/1000+11/100000,"") | AP19: =IF(AND(ISNUMBER(Y19),Z19<>TRUE(),ISNUMBER(SEARCH("requir",'My Colleges'!$AC19))+ISNUMBER(SEARCH("evaluat",'My Colleges'!$AC19))>0),Y19+ROW()/1000+12/100000,"")
... A27: =IF('My Colleges'!$B27="","",'My Colleges'!$B27) | B27: =IF($A27="","",IF('My Colleges'!$V27="No","Dropped",'My Colleges'!$I27)) | C27: =IF(OR($A27="",NOT(ISNUMBER($B27))),"",IF(TRUE(),MAX($B27-35,MIN(Summary!$B$8+7,$B27-3)),"n/a")) | D27: =FALSE() -> FALSE | E27: =IF(OR($A27="",NOT(ISNUMBER($B27))),"",IF(NOT(OR('My Colleges'!$O27="None",'My Colleges'!$O27="None required")),MAX($B27-21,MIN(Summary!$B$8+7,$B27-3)),"n/a")) | F27: =FALSE() -> FALSE | G27: =IF(OR($A27="",NOT(ISNUMBER($B27))),"",IF(NOT(AND(ISNUMBER('My Colleges'!$P27),'My Colleges'!$P27=0)),MAX($B27-28,MIN(Summary!$B$8+7,$B27-3)),"n/a")) | H27: =FALSE() -> FALSE | I27: =IF(OR($A27="",NOT(ISNUMBER($B27))),"",IF(NOT(AND(ISNUMBER('My Colleges'!$P27),'My Colleges'!$P27=0)),MAX($B27-10,MIN(Summary!$B$8+7,$B27-3)),"n/a")) | J27: =FALSE() -> FALSE | K27: =IF(OR($A27="",NOT(ISNUMBER($B27))),"",IF(TRUE(),MAX($B27-14,MIN(Summary!$B$8+7,$B27-3)),"n/a")) | L27: =FALSE() -> FALSE | M27: =IF(OR($A27="",NOT(ISNUMBER($B27))),"",IF(AND('My Colleges'!$N27<>"Blind",OR('My Colleges'!$N27="Required",ISNUMBER(Me!$B$13),ISNUMBER(Me!$B$14))),MAX($B27-14,MIN(Summary!$B$8+7,$B27-3)),"n/a")) | N27: =FALSE() -> FALSE | O27: =IF(OR($A27="",NOT(ISNUMBER($B27))),"",IF(NOT(AND(ISNUMBER('My Colleges'!$L27),'My Colleges'!$L27=0)),MAX($B27-5,MIN(Summary!$B$8+7,$B27-3)),"n/a")) | P27: =FALSE() -> FALSE | Q27: =IF(OR($A27="",NOT(ISNUMBER($B27))),"",IF(TRUE(),$B27-3,"n/a")) | R27: =FALSE() -> FALSE | S27: =IF(OR($A27="",NOT(ISNUMBER($B27))),"",IF(ISNUMBER('My Colleges'!$H27),MAX('My Colleges'!$H27-7,MIN(Summary!$B$8+7,'My Colleges'!$H27-3)),"n/a")) | T27: =FALSE() -> FALSE | U27: =IF(OR($A27="",NOT(ISNUMBER($B27))),"",IF(LEFT('My Colleges'!$AB27,8)="Required",MAX($B27-7,MIN(Summary!$B$8+7,$B27-3)),"n/a")) | V27: =FALSE() -> FALSE | W27: =IF(OR($A27="",NOT(ISNUMBER($B27))),"",IF(TRUE(),$B27+10,"n/a")) | X27: =FALSE() -> FALSE | Y27: =IF(OR($A27="",NOT(ISNUMBER($B27))),"",IF('My Colleges'!$AC27<>"",$B27+21,"n/a")) | Z27: =FALSE() -> FALSE | AA27: =IF($A27="","",AB27-COUNT($AE27:$AO27)) | AB27: =IF($A27="","",SUMPRODUCT((MOD(COLUMN($C27:$X27)-COLUMN($C27),2)=0)*ISNUMBER($C27:$X27))) | AC27: =IF($A27="","",IF($B27="Dropped","Dropped",IF(NOT(ISNUMBER($B27)),"Set a deadline on My Colleges",IF(COUNT($AE27:$AP27)=0,"All steps done",INDEX($AE$6:$AP$6,MATCH(MIN($AE27:$AP27),$AE27:$AP27,0)))))) | AD27: =IF(COUNT($AE27:$AP27)=0,"",INT(MIN($AE27:$AP27))) | AE27: =IF(AND(ISNUMBER(C27),D27<>TRUE(),'My Colleges'!$T27<>"Submitted",'My Colleges'!$T27<>"Complete in portal"),C27+ROW()/1000+1/100000,"") | AF27: =IF(AND(ISNUMBER(E27),F27<>TRUE(),'My Colleges'!$T27<>"Submitted",'My Colleges'!$T27<>"Complete in portal"),E27+ROW()/1000+2/100000,"") | AG27: =IF(AND(ISNUMBER(G27),H27<>TRUE(),'My Colleges'!$T27<>"Submitted",'My Colleges'!$T27<>"Complete in portal"),G27+ROW()/1000+3/100000,"") | AH27: =IF(AND(ISNUMBER(I27),J27<>TRUE(),'My Colleges'!$T27<>"Submitted",'My Colleges'!$T27<>"Complete in portal"),I27+ROW()/1000+4/100000,"") | AI27: =IF(AND(ISNUMBER(K27),L27<>TRUE(),'My Colleges'!$T27<>"Submitted",'My Colleges'!$T27<>"Complete in portal"),K27+ROW()/1000+5/100000,"") | AJ27: =IF(AND(ISNUMBER(M27),N27<>TRUE(),'My Colleges'!$T27<>"Submitted",'My Colleges'!$T27<>"Complete in portal"),M27+ROW()/1000+6/100000,"") | AK27: =IF(AND(ISNUMBER(O27),P27<>TRUE(),'My Colleges'!$T27<>"Submitted",'My Colleges'!$T27<>"Complete in portal"),O27+ROW()/1000+7/100000,"") | AL27: =IF(AND(ISNUMBER(Q27),R27<>TRUE(),'My Colleges'!$T27<>"Submitted",'My Colleges'!$T27<>"Complete in portal"),Q27+ROW()/1000+8/100000,"") | AM27: =IF(AND(ISNUMBER(S27),T27<>TRUE()),S27+ROW()/1000+9/100000,"") | AN27: =IF(AND(ISNUMBER(U27),V27<>TRUE()),U27+ROW()/1000+10/100000,"") | AO27: =IF(AND(ISNUMBER(W27),X27<>TRUE()),W27+ROW()/1000+11/100000,"") | AP27: =IF(AND(ISNUMBER(Y27),Z27<>TRUE(),ISNUMBER(SEARCH("requir",'My Colleges'!$AC27))+ISNUMBER(SEARCH("evaluat",'My Colleges'!$AC27))>0),Y27+ROW()/1000+12/100000,"")
A29: Due dates: confirm requirements 5 weeks out, start essays 4 weeks out, ask recommenders 3 weeks out, transcript and scores 2 weeks out, final essays 10 days out, fee 5 days out, submit 3 days before the deadline, scholarship application a week before its own deadline, then confirm everything shows received in the portal 10 days after.

Sheet Essays
A1: Essays | Written by Type, Not by College
A2: Most extra essays ask one of two things: why this college, or who you are. Write one long version of each first (your two main drafts), then cut every college's essay down from them. Prompts for the colleges on your list appear below by themselves.
A4: Prompts on my list | C4: Final | E4: Main drafts done
A5: =COUNTIF(G12:G111,"?*") -> 0 | C5: =COUNTIF(H8:H111,"Final") -> 0 | E5: =COUNTIF(H9:H10,"Final")&" of 2" -> 0 of 2
A7: College | B7: # | C7: Prompt | D7: Word Limit | E7: Type | F7: Write It As | G7: Required | H7: Status | I7: Target Date | J7: Link to My Draft | K7: Notes
A8: ALL COLLEGES | B8: 0 | C8: Personal statement (Common App: choose one of the seven prompts) | D8: 650 words | F8: Own track | G8: Yes | H8: Not Started | I8: 46317
A9: MAIN DRAFT 1 | B9: 1 | C9: Why this college / why this major: your longest version. Every why-this-college essay is cut from it. | D9: Longest on your list | F9: Main draft | G9: Yes | H9: Not Started | I9: 46317
A10: MAIN DRAFT 2 | B10: 2 | C10: Who I am / what I will contribute: your longest version. Every identity or community essay is cut from it. | D10: Longest on your list | F10: Main draft | G10: Yes | H10: Not Started | I10: 46317
A11: From your colleges (fills in automatically)
A12: =IF(OR('My Colleges'!$B$8="",'My Colleges'!$V$8="No"),"",'My Colleges'!$B$8) | B12: =IF($A12="","",1) | C12: =IF($A12="","",IF(ISNUMBER(MATCH('My Colleges'!$B$8&"|1",DB_Prompts!$A$2:$A$800,0)),INDEX(DB_Prompts!$D$2:$D$800,MATCH('My Colleges'!$B$8&"|1",DB_Prompts!$A$2:$A$800,0)),IF('My Colleges'!$P$8=0,"No extra essays required.","Prompts not loaded yet: check this college's Admissions Page (last column on Explore) or its Common App page, and copy any prompts into Notes."))) | D12: =IF(AND($A12<>"",ISNUMBER(MATCH('My Colleges'!$B$8&"|1",DB_Prompts!$A$2:$A$800,0))),INDEX(DB_Prompts!$E$2:$E$800,MATCH('My Colleges'!$B$8&"|1",DB_Prompts!$A$2:$A$800,0)),"") | E12: =IF(AND($A12<>"",ISNUMBER(MATCH('My Colleges'!$B$8&"|1",DB_Prompts!$A$2:$A$800,0))),INDEX(DB_Prompts!$F$2:$F$800,MATCH('My Colleges'!$B$8&"|1",DB_Prompts!$A$2:$A$800,0)),"") | F12: =IF(AND($A12<>"",ISNUMBER(MATCH('My Colleges'!$B$8&"|1",DB_Prompts!$A$2:$A$800,0))),INDEX(DB_Prompts!$H$2:$H$800,MATCH('My Colleges'!$B$8&"|1",DB_Prompts!$A$2:$A$800,0)),"") | G12: =IF(AND($A12<>"",ISNUMBER(MATCH('My Colleges'!$B$8&"|1",DB_Prompts!$A$2:$A$800,0))),INDEX(DB_Prompts!$G$2:$G$800,MATCH('My Colleges'!$B$8&"|1",DB_Prompts!$A$2:$A$800,0)),"") | I12: =IF(AND($C12<>"",ISNUMBER('My Colleges'!$I$8)),'My Colleges'!$I$8-10,"")
A13: =IF(AND(ISNUMBER(MATCH('My Colleges'!$B$8&"|2",DB_Prompts!$A$2:$A$800,0)),'My Colleges'!$V$8<>"No"),'My Colleges'!$B$8,"") | B13: =IF($A13="","",2) | C13: =IF(AND($A13<>"",ISNUMBER(MATCH('My Colleges'!$B$8&"|2",DB_Prompts!$A$2:$A$800,0))),INDEX(DB_Prompts!$D$2:$D$800,MATCH('My Colleges'!$B$8&"|2",DB_Prompts!$A$2:$A$800,0)),"") | D13: =IF(AND($A13<>"",ISNUMBER(MATCH('My Colleges'!$B$8&"|2",DB_Prompts!$A$2:$A$800,0))),INDEX(DB_Prompts!$E$2:$E$800,MATCH('My Colleges'!$B$8&"|2",DB_Prompts!$A$2:$A$800,0)),"") | E13: =IF(AND($A13<>"",ISNUMBER(MATCH('My Colleges'!$B$8&"|2",DB_Prompts!$A$2:$A$800,0))),INDEX(DB_Prompts!$F$2:$F$800,MATCH('My Colleges'!$B$8&"|2",DB_Prompts!$A$2:$A$800,0)),"") | F13: =IF(AND($A13<>"",ISNUMBER(MATCH('My Colleges'!$B$8&"|2",DB_Prompts!$A$2:$A$800,0))),INDEX(DB_Prompts!$H$2:$H$800,MATCH('My Colleges'!$B$8&"|2",DB_Prompts!$A$2:$A$800,0)),"") | G13: =IF(AND($A13<>"",ISNUMBER(MATCH('My Colleges'!$B$8&"|2",DB_Prompts!$A$2:$A$800,0))),INDEX(DB_Prompts!$G$2:$G$800,MATCH('My Colleges'!$B$8&"|2",DB_Prompts!$A$2:$A$800,0)),"") | I13: =IF(AND($C13<>"",ISNUMBER('My Colleges'!$I$8)),'My Colleges'!$I$8-10,"")
A14: =IF(AND(ISNUMBER(MATCH('My Colleges'!$B$8&"|3",DB_Prompts!$A$2:$A$800,0)),'My Colleges'!$V$8<>"No"),'My Colleges'!$B$8,"") | B14: =IF($A14="","",3) | C14: =IF(AND($A14<>"",ISNUMBER(MATCH('My Colleges'!$B$8&"|3",DB_Prompts!$A$2:$A$800,0))),INDEX(DB_Prompts!$D$2:$D$800,MATCH('My Colleges'!$B$8&"|3",DB_Prompts!$A$2:$A$800,0)),"") | D14: =IF(AND($A14<>"",ISNUMBER(MATCH('My Colleges'!$B$8&"|3",DB_Prompts!$A$2:$A$800,0))),INDEX(DB_Prompts!$E$2:$E$800,MATCH('My Colleges'!$B$8&"|3",DB_Prompts!$A$2:$A$800,0)),"") | E14: =IF(AND($A14<>"",ISNUMBER(MATCH('My Colleges'!$B$8&"|3",DB_Prompts!$A$2:$A$800,0))),INDEX(DB_Prompts!$F$2:$F$800,MATCH('My Colleges'!$B$8&"|3",DB_Prompts!$A$2:$A$800,0)),"") | F14: =IF(AND($A14<>"",ISNUMBER(MATCH('My Colleges'!$B$8&"|3",DB_Prompts!$A$2:$A$800,0))),INDEX(DB_Prompts!$H$2:$H$800,MATCH('My Colleges'!$B$8&"|3",DB_Prompts!$A$2:$A$800,0)),"") | G14: =IF(AND($A14<>"",ISNUMBER(MATCH('My Colleges'!$B$8&"|3",DB_Prompts!$A$2:$A$800,0))),INDEX(DB_Prompts!$G$2:$G$800,MATCH('My Colleges'!$B$8&"|3",DB_Prompts!$A$2:$A$800,0)),"") | I14: =IF(AND($C14<>"",ISNUMBER('My Colleges'!$I$8)),'My Colleges'!$I$8-10,"")
A15: =IF(AND(ISNUMBER(MATCH('My Colleges'!$B$8&"|4",DB_Prompts!$A$2:$A$800,0)),'My Colleges'!$V$8<>"No"),'My Colleges'!$B$8,"") | B15: =IF($A15="","",4) | C15: =IF(AND($A15<>"",ISNUMBER(MATCH('My Colleges'!$B$8&"|4",DB_Prompts!$A$2:$A$800,0))),INDEX(DB_Prompts!$D$2:$D$800,MATCH('My Colleges'!$B$8&"|4",DB_Prompts!$A$2:$A$800,0)),"") | D15: =IF(AND($A15<>"",ISNUMBER(MATCH('My Colleges'!$B$8&"|4",DB_Prompts!$A$2:$A$800,0))),INDEX(DB_Prompts!$E$2:$E$800,MATCH('My Colleges'!$B$8&"|4",DB_Prompts!$A$2:$A$800,0)),"") | E15: =IF(AND($A15<>"",ISNUMBER(MATCH('My Colleges'!$B$8&"|4",DB_Prompts!$A$2:$A$800,0))),INDEX(DB_Prompts!$F$2:$F$800,MATCH('My Colleges'!$B$8&"|4",DB_Prompts!$A$2:$A$800,0)),"") | F15: =IF(AND($A15<>"",ISNUMBER(MATCH('My Colleges'!$B$8&"|4",DB_Prompts!$A$2:$A$800,0))),INDEX(DB_Prompts!$H$2:$H$800,MATCH('My Colleges'!$B$8&"|4",DB_Prompts!$A$2:$A$800,0)),"") | G15: =IF(AND($A15<>"",ISNUMBER(MATCH('My Colleges'!$B$8&"|4",DB_Prompts!$A$2:$A$800,0))),INDEX(DB_Prompts!$G$2:$G$800,MATCH('My Colleges'!$B$8&"|4",DB_Prompts!$A$2:$A$800,0)),"") | I15: =IF(AND($C15<>"",ISNUMBER('My Colleges'!$I$8)),'My Colleges'!$I$8-10,"")
A16: =IF(AND(ISNUMBER(MATCH('My Colleges'!$B$8&"|5",DB_Prompts!$A$2:$A$800,0)),'My Colleges'!$V$8<>"No"),'My Colleges'!$B$8,"") | B16: =IF($A16="","",5) | C16: =IF(AND($A16<>"",ISNUMBER(MATCH('My Colleges'!$B$8&"|5",DB_Prompts!$A$2:$A$800,0))),INDEX(DB_Prompts!$D$2:$D$800,MATCH('My Colleges'!$B$8&"|5",DB_Prompts!$A$2:$A$800,0)),"") | D16: =IF(AND($A16<>"",ISNUMBER(MATCH('My Colleges'!$B$8&"|5",DB_Prompts!$A$2:$A$800,0))),INDEX(DB_Prompts!$E$2:$E$800,MATCH('My Colleges'!$B$8&"|5",DB_Prompts!$A$2:$A$800,0)),"") | E16: =IF(AND($A16<>"",ISNUMBER(MATCH('My Colleges'!$B$8&"|5",DB_Prompts!$A$2:$A$800,0))),INDEX(DB_Prompts!$F$2:$F$800,MATCH('My Colleges'!$B$8&"|5",DB_Prompts!$A$2:$A$800,0)),"") | F16: =IF(AND($A16<>"",ISNUMBER(MATCH('My Colleges'!$B$8&"|5",DB_Prompts!$A$2:$A$800,0))),INDEX(DB_Prompts!$H$2:$H$800,MATCH('My Colleges'!$B$8&"|5",DB_Prompts!$A$2:$A$800,0)),"") | G16: =IF(AND($A16<>"",ISNUMBER(MATCH('My Colleges'!$B$8&"|5",DB_Prompts!$A$2:$A$800,0))),INDEX(DB_Prompts!$G$2:$G$800,MATCH('My Colleges'!$B$8&"|5",DB_Prompts!$A$2:$A$800,0)),"") | I16: =IF(AND($C16<>"",ISNUMBER('My Colleges'!$I$8)),'My Colleges'!$I$8-10,"")
A17: =IF(OR('My Colleges'!$B$9="",'My Colleges'!$V$9="No"),"",'My Colleges'!$B$9) | B17: =IF($A17="","",1) | C17: =IF($A17="","",IF(ISNUMBER(MATCH('My Colleges'!$B$9&"|1",DB_Prompts!$A$2:$A$800,0)),INDEX(DB_Prompts!$D$2:$D$800,MATCH('My Colleges'!$B$9&"|1",DB_Prompts!$A$2:$A$800,0)),IF('My Colleges'!$P$9=0,"No extra essays required.","Prompts not loaded yet: check this college's Admissions Page (last column on Explore) or its Common App page, and copy any prompts into Notes."))) | D17: =IF(AND($A17<>"",ISNUMBER(MATCH('My Colleges'!$B$9&"|1",DB_Prompts!$A$2:$A$800,0))),INDEX(DB_Prompts!$E$2:$E$800,MATCH('My Colleges'!$B$9&"|1",DB_Prompts!$A$2:$A$800,0)),"") | E17: =IF(AND($A17<>"",ISNUMBER(MATCH('My Colleges'!$B$9&"|1",DB_Prompts!$A$2:$A$800,0))),INDEX(DB_Prompts!$F$2:$F$800,MATCH('My Colleges'!$B$9&"|1",DB_Prompts!$A$2:$A$800,0)),"") | F17: =IF(AND($A17<>"",ISNUMBER(MATCH('My Colleges'!$B$9&"|1",DB_Prompts!$A$2:$A$800,0))),INDEX(DB_Prompts!$H$2:$H$800,MATCH('My Colleges'!$B$9&"|1",DB_Prompts!$A$2:$A$800,0)),"") | G17: =IF(AND($A17<>"",ISNUMBER(MATCH('My Colleges'!$B$9&"|1",DB_Prompts!$A$2:$A$800,0))),INDEX(DB_Prompts!$G$2:$G$800,MATCH('My Colleges'!$B$9&"|1",DB_Prompts!$A$2:$A$800,0)),"") | I17: =IF(AND($C17<>"",ISNUMBER('My Colleges'!$I$9)),'My Colleges'!$I$9-10,"")
A18: =IF(AND(ISNUMBER(MATCH('My Colleges'!$B$9&"|2",DB_Prompts!$A$2:$A$800,0)),'My Colleges'!$V$9<>"No"),'My Colleges'!$B$9,"") | B18: =IF($A18="","",2) | C18: =IF(AND($A18<>"",ISNUMBER(MATCH('My Colleges'!$B$9&"|2",DB_Prompts!$A$2:$A$800,0))),INDEX(DB_Prompts!$D$2:$D$800,MATCH('My Colleges'!$B$9&"|2",DB_Prompts!$A$2:$A$800,0)),"") | D18: =IF(AND($A18<>"",ISNUMBER(MATCH('My Colleges'!$B$9&"|2",DB_Prompts!$A$2:$A$800,0))),INDEX(DB_Prompts!$E$2:$E$800,MATCH('My Colleges'!$B$9&"|2",DB_Prompts!$A$2:$A$800,0)),"") | E18: =IF(AND($A18<>"",ISNUMBER(MATCH('My Colleges'!$B$9&"|2",DB_Prompts!$A$2:$A$800,0))),INDEX(DB_Prompts!$F$2:$F$800,MATCH('My Colleges'!$B$9&"|2",DB_Prompts!$A$2:$A$800,0)),"") | F18: =IF(AND($A18<>"",ISNUMBER(MATCH('My Colleges'!$B$9&"|2",DB_Prompts!$A$2:$A$800,0))),INDEX(DB_Prompts!$H$2:$H$800,MATCH('My Colleges'!$B$9&"|2",DB_Prompts!$A$2:$A$800,0)),"") | G18: =IF(AND($A18<>"",ISNUMBER(MATCH('My Colleges'!$B$9&"|2",DB_Prompts!$A$2:$A$800,0))),INDEX(DB_Prompts!$G$2:$G$800,MATCH('My Colleges'!$B$9&"|2",DB_Prompts!$A$2:$A$800,0)),"") | I18: =IF(AND($C18<>"",ISNUMBER('My Colleges'!$I$9)),'My Colleges'!$I$9-10,"")
A19: =IF(AND(ISNUMBER(MATCH('My Colleges'!$B$9&"|3",DB_Prompts!$A$2:$A$800,0)),'My Colleges'!$V$9<>"No"),'My Colleges'!$B$9,"") | B19: =IF($A19="","",3) | C19: =IF(AND($A19<>"",ISNUMBER(MATCH('My Colleges'!$B$9&"|3",DB_Prompts!$A$2:$A$800,0))),INDEX(DB_Prompts!$D$2:$D$800,MATCH('My Colleges'!$B$9&"|3",DB_Prompts!$A$2:$A$800,0)),"") | D19: =IF(AND($A19<>"",ISNUMBER(MATCH('My Colleges'!$B$9&"|3",DB_Prompts!$A$2:$A$800,0))),INDEX(DB_Prompts!$E$2:$E$800,MATCH('My Colleges'!$B$9&"|3",DB_Prompts!$A$2:$A$800,0)),"") | E19: =IF(AND($A19<>"",ISNUMBER(MATCH('My Colleges'!$B$9&"|3",DB_Prompts!$A$2:$A$800,0))),INDEX(DB_Prompts!$F$2:$F$800,MATCH('My Colleges'!$B$9&"|3",DB_Prompts!$A$2:$A$800,0)),"") | F19: =IF(AND($A19<>"",ISNUMBER(MATCH('My Colleges'!$B$9&"|3",DB_Prompts!$A$2:$A$800,0))),INDEX(DB_Prompts!$H$2:$H$800,MATCH('My Colleges'!$B$9&"|3",DB_Prompts!$A$2:$A$800,0)),"") | G19: =IF(AND($A19<>"",ISNUMBER(MATCH('My Colleges'!$B$9&"|3",DB_Prompts!$A$2:$A$800,0))),INDEX(DB_Prompts!$G$2:$G$800,MATCH('My Colleges'!$B$9&"|3",DB_Prompts!$A$2:$A$800,0)),"") | I19: =IF(AND($C19<>"",ISNUMBER('My Colleges'!$I$9)),'My Colleges'!$I$9-10,"")
A20: =IF(AND(ISNUMBER(MATCH('My Colleges'!$B$9&"|4",DB_Prompts!$A$2:$A$800,0)),'My Colleges'!$V$9<>"No"),'My Colleges'!$B$9,"") | B20: =IF($A20="","",4) | C20: =IF(AND($A20<>"",ISNUMBER(MATCH('My Colleges'!$B$9&"|4",DB_Prompts!$A$2:$A$800,0))),INDEX(DB_Prompts!$D$2:$D$800,MATCH('My Colleges'!$B$9&"|4",DB_Prompts!$A$2:$A$800,0)),"") | D20: =IF(AND($A20<>"",ISNUMBER(MATCH('My Colleges'!$B$9&"|4",DB_Prompts!$A$2:$A$800,0))),INDEX(DB_Prompts!$E$2:$E$800,MATCH('My Colleges'!$B$9&"|4",DB_Prompts!$A$2:$A$800,0)),"") | E20: =IF(AND($A20<>"",ISNUMBER(MATCH('My Colleges'!$B$9&"|4",DB_Prompts!$A$2:$A$800,0))),INDEX(DB_Prompts!$F$2:$F$800,MATCH('My Colleges'!$B$9&"|4",DB_Prompts!$A$2:$A$800,0)),"") | F20: =IF(AND($A20<>"",ISNUMBER(MATCH('My Colleges'!$B$9&"|4",DB_Prompts!$A$2:$A$800,0))),INDEX(DB_Prompts!$H$2:$H$800,MATCH('My Colleges'!$B$9&"|4",DB_Prompts!$A$2:$A$800,0)),"") | G20: =IF(AND($A20<>"",ISNUMBER(MATCH('My Colleges'!$B$9&"|4",DB_Prompts!$A$2:$A$800,0))),INDEX(DB_Prompts!$G$2:$G$800,MATCH('My Colleges'!$B$9&"|4",DB_Prompts!$A$2:$A$800,0)),"") | I20: =IF(AND($C20<>"",ISNUMBER('My Colleges'!$I$9)),'My Colleges'!$I$9-10,"")
A21: =IF(AND(ISNUMBER(MATCH('My Colleges'!$B$9&"|5",DB_Prompts!$A$2:$A$800,0)),'My Colleges'!$V$9<>"No"),'My Colleges'!$B$9,"") | B21: =IF($A21="","",5) | C21: =IF(AND($A21<>"",ISNUMBER(MATCH('My Colleges'!$B$9&"|5",DB_Prompts!$A$2:$A$800,0))),INDEX(DB_Prompts!$D$2:$D$800,MATCH('My Colleges'!$B$9&"|5",DB_Prompts!$A$2:$A$800,0)),"") | D21: =IF(AND($A21<>"",ISNUMBER(MATCH('My Colleges'!$B$9&"|5",DB_Prompts!$A$2:$A$800,0))),INDEX(DB_Prompts!$E$2:$E$800,MATCH('My Colleges'!$B$9&"|5",DB_Prompts!$A$2:$A$800,0)),"") | E21: =IF(AND($A21<>"",ISNUMBER(MATCH('My Colleges'!$B$9&"|5",DB_Prompts!$A$2:$A$800,0))),INDEX(DB_Prompts!$F$2:$F$800,MATCH('My Colleges'!$B$9&"|5",DB_Prompts!$A$2:$A$800,0)),"") | F21: =IF(AND($A21<>"",ISNUMBER(MATCH('My Colleges'!$B$9&"|5",DB_Prompts!$A$2:$A$800,0))),INDEX(DB_Prompts!$H$2:$H$800,MATCH('My Colleges'!$B$9&"|5",DB_Prompts!$A$2:$A$800,0)),"") | G21: =IF(AND($A21<>"",ISNUMBER(MATCH('My Colleges'!$B$9&"|5",DB_Prompts!$A$2:$A$800,0))),INDEX(DB_Prompts!$G$2:$G$800,MATCH('My Colleges'!$B$9&"|5",DB_Prompts!$A$2:$A$800,0)),"") | I21: =IF(AND($C21<>"",ISNUMBER('My Colleges'!$I$9)),'My Colleges'!$I$9-10,"")
A22: =IF(OR('My Colleges'!$B$10="",'My Colleges'!$V$10="No"),"",'My Colleges'!$B$10) | B22: =IF($A22="","",1) | C22: =IF($A22="","",IF(ISNUMBER(MATCH('My Colleges'!$B$10&"|1",DB_Prompts!$A$2:$A$800,0)),INDEX(DB_Prompts!$D$2:$D$800,MATCH('My Colleges'!$B$10&"|1",DB_Prompts!$A$2:$A$800,0)),IF('My Colleges'!$P$10=0,"No extra essays required.","Prompts not loaded yet: check this college's Admissions Page (last column on Explore) or its Common App page, and copy any prompts into Notes."))) | D22: =IF(AND($A22<>"",ISNUMBER(MATCH('My Colleges'!$B$10&"|1",DB_Prompts!$A$2:$A$800,0))),INDEX(DB_Prompts!$E$2:$E$800,MATCH('My Colleges'!$B$10&"|1",DB_Prompts!$A$2:$A$800,0)),"") | E22: =IF(AND($A22<>"",ISNUMBER(MATCH('My Colleges'!$B$10&"|1",DB_Prompts!$A$2:$A$800,0))),INDEX(DB_Prompts!$F$2:$F$800,MATCH('My Colleges'!$B$10&"|1",DB_Prompts!$A$2:$A$800,0)),"") | F22: =IF(AND($A22<>"",ISNUMBER(MATCH('My Colleges'!$B$10&"|1",DB_Prompts!$A$2:$A$800,0))),INDEX(DB_Prompts!$H$2:$H$800,MATCH('My Colleges'!$B$10&"|1",DB_Prompts!$A$2:$A$800,0)),"") | G22: =IF(AND($A22<>"",ISNUMBER(MATCH('My Colleges'!$B$10&"|1",DB_Prompts!$A$2:$A$800,0))),INDEX(DB_Prompts!$G$2:$G$800,MATCH('My Colleges'!$B$10&"|1",DB_Prompts!$A$2:$A$800,0)),"") | I22: =IF(AND($C22<>"",ISNUMBER('My Colleges'!$I$10)),'My Colleges'!$I$10-10,"")
A23: =IF(AND(ISNUMBER(MATCH('My Colleges'!$B$10&"|2",DB_Prompts!$A$2:$A$800,0)),'My Colleges'!$V$10<>"No"),'My Colleges'!$B$10,"") | B23: =IF($A23="","",2) | C23: =IF(AND($A23<>"",ISNUMBER(MATCH('My Colleges'!$B$10&"|2",DB_Prompts!$A$2:$A$800,0))),INDEX(DB_Prompts!$D$2:$D$800,MATCH('My Colleges'!$B$10&"|2",DB_Prompts!$A$2:$A$800,0)),"") | D23: =IF(AND($A23<>"",ISNUMBER(MATCH('My Colleges'!$B$10&"|2",DB_Prompts!$A$2:$A$800,0))),INDEX(DB_Prompts!$E$2:$E$800,MATCH('My Colleges'!$B$10&"|2",DB_Prompts!$A$2:$A$800,0)),"") | E23: =IF(AND($A23<>"",ISNUMBER(MATCH('My Colleges'!$B$10&"|2",DB_Prompts!$A$2:$A$800,0))),INDEX(DB_Prompts!$F$2:$F$800,MATCH('My Colleges'!$B$10&"|2",DB_Prompts!$A$2:$A$800,0)),"") | F23: =IF(AND($A23<>"",ISNUMBER(MATCH('My Colleges'!$B$10&"|2",DB_Prompts!$A$2:$A$800,0))),INDEX(DB_Prompts!$H$2:$H$800,MATCH('My Colleges'!$B$10&"|2",DB_Prompts!$A$2:$A$800,0)),"") | G23: =IF(AND($A23<>"",ISNUMBER(MATCH('My Colleges'!$B$10&"|2",DB_Prompts!$A$2:$A$800,0))),INDEX(DB_Prompts!$G$2:$G$800,MATCH('My Colleges'!$B$10&"|2",DB_Prompts!$A$2:$A$800,0)),"") | I23: =IF(AND($C23<>"",ISNUMBER('My Colleges'!$I$10)),'My Colleges'!$I$10-10,"")
A24: =IF(AND(ISNUMBER(MATCH('My Colleges'!$B$10&"|3",DB_Prompts!$A$2:$A$800,0)),'My Colleges'!$V$10<>"No"),'My Colleges'!$B$10,"") | B24: =IF($A24="","",3) | C24: =IF(AND($A24<>"",ISNUMBER(MATCH('My Colleges'!$B$10&"|3",DB_Prompts!$A$2:$A$800,0))),INDEX(DB_Prompts!$D$2:$D$800,MATCH('My Colleges'!$B$10&"|3",DB_Prompts!$A$2:$A$800,0)),"") | D24: =IF(AND($A24<>"",ISNUMBER(MATCH('My Colleges'!$B$10&"|3",DB_Prompts!$A$2:$A$800,0))),INDEX(DB_Prompts!$E$2:$E$800,MATCH('My Colleges'!$B$10&"|3",DB_Prompts!$A$2:$A$800,0)),"") | E24: =IF(AND($A24<>"",ISNUMBER(MATCH('My Colleges'!$B$10&"|3",DB_Prompts!$A$2:$A$800,0))),INDEX(DB_Prompts!$F$2:$F$800,MATCH('My Colleges'!$B$10&"|3",DB_Prompts!$A$2:$A$800,0)),"") | F24: =IF(AND($A24<>"",ISNUMBER(MATCH('My Colleges'!$B$10&"|3",DB_Prompts!$A$2:$A$800,0))),INDEX(DB_Prompts!$H$2:$H$800,MATCH('My Colleges'!$B$10&"|3",DB_Prompts!$A$2:$A$800,0)),"") | G24: =IF(AND($A24<>"",ISNUMBER(MATCH('My Colleges'!$B$10&"|3",DB_Prompts!$A$2:$A$800,0))),INDEX(DB_Prompts!$G$2:$G$800,MATCH('My Colleges'!$B$10&"|3",DB_Prompts!$A$2:$A$800,0)),"") | I24: =IF(AND($C24<>"",ISNUMBER('My Colleges'!$I$10)),'My Colleges'!$I$10-10,"")
A25: =IF(AND(ISNUMBER(MATCH('My Colleges'!$B$10&"|4",DB_Prompts!$A$2:$A$800,0)),'My Colleges'!$V$10<>"No"),'My Colleges'!$B$10,"") | B25: =IF($A25="","",4) | C25: =IF(AND($A25<>"",ISNUMBER(MATCH('My Colleges'!$B$10&"|4",DB_Prompts!$A$2:$A$800,0))),INDEX(DB_Prompts!$D$2:$D$800,MATCH('My Colleges'!$B$10&"|4",DB_Prompts!$A$2:$A$800,0)),"") | D25: =IF(AND($A25<>"",ISNUMBER(MATCH('My Colleges'!$B$10&"|4",DB_Prompts!$A$2:$A$800,0))),INDEX(DB_Prompts!$E$2:$E$800,MATCH('My Colleges'!$B$10&"|4",DB_Prompts!$A$2:$A$800,0)),"") | E25: =IF(AND($A25<>"",ISNUMBER(MATCH('My Colleges'!$B$10&"|4",DB_Prompts!$A$2:$A$800,0))),INDEX(DB_Prompts!$F$2:$F$800,MATCH('My Colleges'!$B$10&"|4",DB_Prompts!$A$2:$A$800,0)),"") | F25: =IF(AND($A25<>"",ISNUMBER(MATCH('My Colleges'!$B$10&"|4",DB_Prompts!$A$2:$A$800,0))),INDEX(DB_Prompts!$H$2:$H$800,MATCH('My Colleges'!$B$10&"|4",DB_Prompts!$A$2:$A$800,0)),"") | G25: =IF(AND($A25<>"",ISNUMBER(MATCH('My Colleges'!$B$10&"|4",DB_Prompts!$A$2:$A$800,0))),INDEX(DB_Prompts!$G$2:$G$800,MATCH('My Colleges'!$B$10&"|4",DB_Prompts!$A$2:$A$800,0)),"") | I25: =IF(AND($C25<>"",ISNUMBER('My Colleges'!$I$10)),'My Colleges'!$I$10-10,"")
A26: =IF(AND(ISNUMBER(MATCH('My Colleges'!$B$10&"|5",DB_Prompts!$A$2:$A$800,0)),'My Colleges'!$V$10<>"No"),'My Colleges'!$B$10,"") | B26: =IF($A26="","",5) | C26: =IF(AND($A26<>"",ISNUMBER(MATCH('My Colleges'!$B$10&"|5",DB_Prompts!$A$2:$A$800,0))),INDEX(DB_Prompts!$D$2:$D$800,MATCH('My Colleges'!$B$10&"|5",DB_Prompts!$A$2:$A$800,0)),"") | D26: =IF(AND($A26<>"",ISNUMBER(MATCH('My Colleges'!$B$10&"|5",DB_Prompts!$A$2:$A$800,0))),INDEX(DB_Prompts!$E$2:$E$800,MATCH('My Colleges'!$B$10&"|5",DB_Prompts!$A$2:$A$800,0)),"") | E26: =IF(AND($A26<>"",ISNUMBER(MATCH('My Colleges'!$B$10&"|5",DB_Prompts!$A$2:$A$800,0))),INDEX(DB_Prompts!$F$2:$F$800,MATCH('My Colleges'!$B$10&"|5",DB_Prompts!$A$2:$A$800,0)),"") | F26: =IF(AND($A26<>"",ISNUMBER(MATCH('My Colleges'!$B$10&"|5",DB_Prompts!$A$2:$A$800,0))),INDEX(DB_Prompts!$H$2:$H$800,MATCH('My Colleges'!$B$10&"|5",DB_Prompts!$A$2:$A$800,0)),"") | G26: =IF(AND($A26<>"",ISNUMBER(MATCH('My Colleges'!$B$10&"|5",DB_Prompts!$A$2:$A$800,0))),INDEX(DB_Prompts!$G$2:$G$800,MATCH('My Colleges'!$B$10&"|5",DB_Prompts!$A$2:$A$800,0)),"") | I26: =IF(AND($C26<>"",ISNUMBER('My Colleges'!$I$10)),'My Colleges'!$I$10-10,"")
A27: =IF(OR('My Colleges'!$B$11="",'My Colleges'!$V$11="No"),"",'My Colleges'!$B$11) | B27: =IF($A27="","",1) | C27: =IF($A27="","",IF(ISNUMBER(MATCH('My Colleges'!$B$11&"|1",DB_Prompts!$A$2:$A$800,0)),INDEX(DB_Prompts!$D$2:$D$800,MATCH('My Colleges'!$B$11&"|1",DB_Prompts!$A$2:$A$800,0)),IF('My Colleges'!$P$11=0,"No extra essays required.","Prompts not loaded yet: check this college's Admissions Page (last column on Explore) or its Common App page, and copy any prompts into Notes."))) | D27: =IF(AND($A27<>"",ISNUMBER(MATCH('My Colleges'!$B$11&"|1",DB_Prompts!$A$2:$A$800,0))),INDEX(DB_Prompts!$E$2:$E$800,MATCH('My Colleges'!$B$11&"|1",DB_Prompts!$A$2:$A$800,0)),"") | E27: =IF(AND($A27<>"",ISNUMBER(MATCH('My Colleges'!$B$11&"|1",DB_Prompts!$A$2:$A$800,0))),INDEX(DB_Prompts!$F$2:$F$800,MATCH('My Colleges'!$B$11&"|1",DB_Prompts!$A$2:$A$800,0)),"") | F27: =IF(AND($A27<>"",ISNUMBER(MATCH('My Colleges'!$B$11&"|1",DB_Prompts!$A$2:$A$800,0))),INDEX(DB_Prompts!$H$2:$H$800,MATCH('My Colleges'!$B$11&"|1",DB_Prompts!$A$2:$A$800,0)),"") | G27: =IF(AND($A27<>"",ISNUMBER(MATCH('My Colleges'!$B$11&"|1",DB_Prompts!$A$2:$A$800,0))),INDEX(DB_Prompts!$G$2:$G$800,MATCH('My Colleges'!$B$11&"|1",DB_Prompts!$A$2:$A$800,0)),"") | I27: =IF(AND($C27<>"",ISNUMBER('My Colleges'!$I$11)),'My Colleges'!$I$11-10,"")
A28: =IF(AND(ISNUMBER(MATCH('My Colleges'!$B$11&"|2",DB_Prompts!$A$2:$A$800,0)),'My Colleges'!$V$11<>"No"),'My Colleges'!$B$11,"") | B28: =IF($A28="","",2) | C28: =IF(AND($A28<>"",ISNUMBER(MATCH('My Colleges'!$B$11&"|2",DB_Prompts!$A$2:$A$800,0))),INDEX(DB_Prompts!$D$2:$D$800,MATCH('My Colleges'!$B$11&"|2",DB_Prompts!$A$2:$A$800,0)),"") | D28: =IF(AND($A28<>"",ISNUMBER(MATCH('My Colleges'!$B$11&"|2",DB_Prompts!$A$2:$A$800,0))),INDEX(DB_Prompts!$E$2:$E$800,MATCH('My Colleges'!$B$11&"|2",DB_Prompts!$A$2:$A$800,0)),"") | E28: =IF(AND($A28<>"",ISNUMBER(MATCH('My Colleges'!$B$11&"|2",DB_Prompts!$A$2:$A$800,0))),INDEX(DB_Prompts!$F$2:$F$800,MATCH('My Colleges'!$B$11&"|2",DB_Prompts!$A$2:$A$800,0)),"") | F28: =IF(AND($A28<>"",ISNUMBER(MATCH('My Colleges'!$B$11&"|2",DB_Prompts!$A$2:$A$800,0))),INDEX(DB_Prompts!$H$2:$H$800,MATCH('My Colleges'!$B$11&"|2",DB_Prompts!$A$2:$A$800,0)),"") | G28: =IF(AND($A28<>"",ISNUMBER(MATCH('My Colleges'!$B$11&"|2",DB_Prompts!$A$2:$A$800,0))),INDEX(DB_Prompts!$G$2:$G$800,MATCH('My Colleges'!$B$11&"|2",DB_Prompts!$A$2:$A$800,0)),"") | I28: =IF(AND($C28<>"",ISNUMBER('My Colleges'!$I$11)),'My Colleges'!$I$11-10,"")
A29: =IF(AND(ISNUMBER(MATCH('My Colleges'!$B$11&"|3",DB_Prompts!$A$2:$A$800,0)),'My Colleges'!$V$11<>"No"),'My Colleges'!$B$11,"") | B29: =IF($A29="","",3) | C29: =IF(AND($A29<>"",ISNUMBER(MATCH('My Colleges'!$B$11&"|3",DB_Prompts!$A$2:$A$800,0))),INDEX(DB_Prompts!$D$2:$D$800,MATCH('My Colleges'!$B$11&"|3",DB_Prompts!$A$2:$A$800,0)),"") | D29: =IF(AND($A29<>"",ISNUMBER(MATCH('My Colleges'!$B$11&"|3",DB_Prompts!$A$2:$A$800,0))),INDEX(DB_Prompts!$E$2:$E$800,MATCH('My Colleges'!$B$11&"|3",DB_Prompts!$A$2:$A$800,0)),"") | E29: =IF(AND($A29<>"",ISNUMBER(MATCH('My Colleges'!$B$11&"|3",DB_Prompts!$A$2:$A$800,0))),INDEX(DB_Prompts!$F$2:$F$800,MATCH('My Colleges'!$B$11&"|3",DB_Prompts!$A$2:$A$800,0)),"") | F29: =IF(AND($A29<>"",ISNUMBER(MATCH('My Colleges'!$B$11&"|3",DB_Prompts!$A$2:$A$800,0))),INDEX(DB_Prompts!$H$2:$H$800,MATCH('My Colleges'!$B$11&"|3",DB_Prompts!$A$2:$A$800,0)),"") | G29: =IF(AND($A29<>"",ISNUMBER(MATCH('My Colleges'!$B$11&"|3",DB_Prompts!$A$2:$A$800,0))),INDEX(DB_Prompts!$G$2:$G$800,MATCH('My Colleges'!$B$11&"|3",DB_Prompts!$A$2:$A$800,0)),"") | I29: =IF(AND($C29<>"",ISNUMBER('My Colleges'!$I$11)),'My Colleges'!$I$11-10,"")
A30: =IF(AND(ISNUMBER(MATCH('My Colleges'!$B$11&"|4",DB_Prompts!$A$2:$A$800,0)),'My Colleges'!$V$11<>"No"),'My Colleges'!$B$11,"") | B30: =IF($A30="","",4) | C30: =IF(AND($A30<>"",ISNUMBER(MATCH('My Colleges'!$B$11&"|4",DB_Prompts!$A$2:$A$800,0))),INDEX(DB_Prompts!$D$2:$D$800,MATCH('My Colleges'!$B$11&"|4",DB_Prompts!$A$2:$A$800,0)),"") | D30: =IF(AND($A30<>"",ISNUMBER(MATCH('My Colleges'!$B$11&"|4",DB_Prompts!$A$2:$A$800,0))),INDEX(DB_Prompts!$E$2:$E$800,MATCH('My Colleges'!$B$11&"|4",DB_Prompts!$A$2:$A$800,0)),"") | E30: =IF(AND($A30<>"",ISNUMBER(MATCH('My Colleges'!$B$11&"|4",DB_Prompts!$A$2:$A$800,0))),INDEX(DB_Prompts!$F$2:$F$800,MATCH('My Colleges'!$B$11&"|4",DB_Prompts!$A$2:$A$800,0)),"") | F30: =IF(AND($A30<>"",ISNUMBER(MATCH('My Colleges'!$B$11&"|4",DB_Prompts!$A$2:$A$800,0))),INDEX(DB_Prompts!$H$2:$H$800,MATCH('My Colleges'!$B$11&"|4",DB_Prompts!$A$2:$A$800,0)),"") | G30: =IF(AND($A30<>"",ISNUMBER(MATCH('My Colleges'!$B$11&"|4",DB_Prompts!$A$2:$A$800,0))),INDEX(DB_Prompts!$G$2:$G$800,MATCH('My Colleges'!$B$11&"|4",DB_Prompts!$A$2:$A$800,0)),"") | I30: =IF(AND($C30<>"",ISNUMBER('My Colleges'!$I$11)),'My Colleges'!$I$11-10,"")
A31: =IF(AND(ISNUMBER(MATCH('My Colleges'!$B$11&"|5",DB_Prompts!$A$2:$A$800,0)),'My Colleges'!$V$11<>"No"),'My Colleges'!$B$11,"") | B31: =IF($A31="","",5) | C31: =IF(AND($A31<>"",ISNUMBER(MATCH('My Colleges'!$B$11&"|5",DB_Prompts!$A$2:$A$800,0))),INDEX(DB_Prompts!$D$2:$D$800,MATCH('My Colleges'!$B$11&"|5",DB_Prompts!$A$2:$A$800,0)),"") | D31: =IF(AND($A31<>"",ISNUMBER(MATCH('My Colleges'!$B$11&"|5",DB_Prompts!$A$2:$A$800,0))),INDEX(DB_Prompts!$E$2:$E$800,MATCH('My Colleges'!$B$11&"|5",DB_Prompts!$A$2:$A$800,0)),"") | E31: =IF(AND($A31<>"",ISNUMBER(MATCH('My Colleges'!$B$11&"|5",DB_Prompts!$A$2:$A$800,0))),INDEX(DB_Prompts!$F$2:$F$800,MATCH('My Colleges'!$B$11&"|5",DB_Prompts!$A$2:$A$800,0)),"") | F31: =IF(AND($A31<>"",ISNUMBER(MATCH('My Colleges'!$B$11&"|5",DB_Prompts!$A$2:$A$800,0))),INDEX(DB_Prompts!$H$2:$H$800,MATCH('My Colleges'!$B$11&"|5",DB_Prompts!$A$2:$A$800,0)),"") | G31: =IF(AND($A31<>"",ISNUMBER(MATCH('My Colleges'!$B$11&"|5",DB_Prompts!$A$2:$A$800,0))),INDEX(DB_Prompts!$G$2:$G$800,MATCH('My Colleges'!$B$11&"|5",DB_Prompts!$A$2:$A$800,0)),"") | I31: =IF(AND($C31<>"",ISNUMBER('My Colleges'!$I$11)),'My Colleges'!$I$11-10,"")
A32: =IF(OR('My Colleges'!$B$12="",'My Colleges'!$V$12="No"),"",'My Colleges'!$B$12) | B32: =IF($A32="","",1) | C32: =IF($A32="","",IF(ISNUMBER(MATCH('My Colleges'!$B$12&"|1",DB_Prompts!$A$2:$A$800,0)),INDEX(DB_Prompts!$D$2:$D$800,MATCH('My Colleges'!$B$12&"|1",DB_Prompts!$A$2:$A$800,0)),IF('My Colleges'!$P$12=0,"No extra essays required.","Prompts not loaded yet: check this college's Admissions Page (last column on Explore) or its Common App page, and copy any prompts into Notes."))) | D32: =IF(AND($A32<>"",ISNUMBER(MATCH('My Colleges'!$B$12&"|1",DB_Prompts!$A$2:$A$800,0))),INDEX(DB_Prompts!$E$2:$E$800,MATCH('My Colleges'!$B$12&"|1",DB_Prompts!$A$2:$A$800,0)),"") | E32: =IF(AND($A32<>"",ISNUMBER(MATCH('My Colleges'!$B$12&"|1",DB_Prompts!$A$2:$A$800,0))),INDEX(DB_Prompts!$F$2:$F$800,MATCH('My Colleges'!$B$12&"|1",DB_Prompts!$A$2:$A$800,0)),"") | F32: =IF(AND($A32<>"",ISNUMBER(MATCH('My Colleges'!$B$12&"|1",DB_Prompts!$A$2:$A$800,0))),INDEX(DB_Prompts!$H$2:$H$800,MATCH('My Colleges'!$B$12&"|1",DB_Prompts!$A$2:$A$800,0)),"") | G32: =IF(AND($A32<>"",ISNUMBER(MATCH('My Colleges'!$B$12&"|1",DB_Prompts!$A$2:$A$800,0))),INDEX(DB_Prompts!$G$2:$G$800,MATCH('My Colleges'!$B$12&"|1",DB_Prompts!$A$2:$A$800,0)),"") | I32: =IF(AND($C32<>"",ISNUMBER('My Colleges'!$I$12)),'My Colleges'!$I$12-10,"")
A33: =IF(AND(ISNUMBER(MATCH('My Colleges'!$B$12&"|2",DB_Prompts!$A$2:$A$800,0)),'My Colleges'!$V$12<>"No"),'My Colleges'!$B$12,"") | B33: =IF($A33="","",2) | C33: =IF(AND($A33<>"",ISNUMBER(MATCH('My Colleges'!$B$12&"|2",DB_Prompts!$A$2:$A$800,0))),INDEX(DB_Prompts!$D$2:$D$800,MATCH('My Colleges'!$B$12&"|2",DB_Prompts!$A$2:$A$800,0)),"") | D33: =IF(AND($A33<>"",ISNUMBER(MATCH('My Colleges'!$B$12&"|2",DB_Prompts!$A$2:$A$800,0))),INDEX(DB_Prompts!$E$2:$E$800,MATCH('My Colleges'!$B$12&"|2",DB_Prompts!$A$2:$A$800,0)),"") | E33: =IF(AND($A33<>"",ISNUMBER(MATCH('My Colleges'!$B$12&"|2",DB_Prompts!$A$2:$A$800,0))),INDEX(DB_Prompts!$F$2:$F$800,MATCH('My Colleges'!$B$12&"|2",DB_Prompts!$A$2:$A$800,0)),"") | F33: =IF(AND($A33<>"",ISNUMBER(MATCH('My Colleges'!$B$12&"|2",DB_Prompts!$A$2:$A$800,0))),INDEX(DB_Prompts!$H$2:$H$800,MATCH('My Colleges'!$B$12&"|2",DB_Prompts!$A$2:$A$800,0)),"") | G33: =IF(AND($A33<>"",ISNUMBER(MATCH('My Colleges'!$B$12&"|2",DB_Prompts!$A$2:$A$800,0))),INDEX(DB_Prompts!$G$2:$G$800,MATCH('My Colleges'!$B$12&"|2",DB_Prompts!$A$2:$A$800,0)),"") | I33: =IF(AND($C33<>"",ISNUMBER('My Colleges'!$I$12)),'My Colleges'!$I$12-10,"")
A34: =IF(AND(ISNUMBER(MATCH('My Colleges'!$B$12&"|3",DB_Prompts!$A$2:$A$800,0)),'My Colleges'!$V$12<>"No"),'My Colleges'!$B$12,"") | B34: =IF($A34="","",3) | C34: =IF(AND($A34<>"",ISNUMBER(MATCH('My Colleges'!$B$12&"|3",DB_Prompts!$A$2:$A$800,0))),INDEX(DB_Prompts!$D$2:$D$800,MATCH('My Colleges'!$B$12&"|3",DB_Prompts!$A$2:$A$800,0)),"") | D34: =IF(AND($A34<>"",ISNUMBER(MATCH('My Colleges'!$B$12&"|3",DB_Prompts!$A$2:$A$800,0))),INDEX(DB_Prompts!$E$2:$E$800,MATCH('My Colleges'!$B$12&"|3",DB_Prompts!$A$2:$A$800,0)),"") | E34: =IF(AND($A34<>"",ISNUMBER(MATCH('My Colleges'!$B$12&"|3",DB_Prompts!$A$2:$A$800,0))),INDEX(DB_Prompts!$F$2:$F$800,MATCH('My Colleges'!$B$12&"|3",DB_Prompts!$A$2:$A$800,0)),"") | F34: =IF(AND($A34<>"",ISNUMBER(MATCH('My Colleges'!$B$12&"|3",DB_Prompts!$A$2:$A$800,0))),INDEX(DB_Prompts!$H$2:$H$800,MATCH('My Colleges'!$B$12&"|3",DB_Prompts!$A$2:$A$800,0)),"") | G34: =IF(AND($A34<>"",ISNUMBER(MATCH('My Colleges'!$B$12&"|3",DB_Prompts!$A$2:$A$800,0))),INDEX(DB_Prompts!$G$2:$G$800,MATCH('My Colleges'!$B$12&"|3",DB_Prompts!$A$2:$A$800,0)),"") | I34: =IF(AND($C34<>"",ISNUMBER('My Colleges'!$I$12)),'My Colleges'!$I$12-10,"")
A35: =IF(AND(ISNUMBER(MATCH('My Colleges'!$B$12&"|4",DB_Prompts!$A$2:$A$800,0)),'My Colleges'!$V$12<>"No"),'My Colleges'!$B$12,"") | B35: =IF($A35="","",4) | C35: =IF(AND($A35<>"",ISNUMBER(MATCH('My Colleges'!$B$12&"|4",DB_Prompts!$A$2:$A$800,0))),INDEX(DB_Prompts!$D$2:$D$800,MATCH('My Colleges'!$B$12&"|4",DB_Prompts!$A$2:$A$800,0)),"") | D35: =IF(AND($A35<>"",ISNUMBER(MATCH('My Colleges'!$B$12&"|4",DB_Prompts!$A$2:$A$800,0))),INDEX(DB_Prompts!$E$2:$E$800,MATCH('My Colleges'!$B$12&"|4",DB_Prompts!$A$2:$A$800,0)),"") | E35: =IF(AND($A35<>"",ISNUMBER(MATCH('My Colleges'!$B$12&"|4",DB_Prompts!$A$2:$A$800,0))),INDEX(DB_Prompts!$F$2:$F$800,MATCH('My Colleges'!$B$12&"|4",DB_Prompts!$A$2:$A$800,0)),"") | F35: =IF(AND($A35<>"",ISNUMBER(MATCH('My Colleges'!$B$12&"|4",DB_Prompts!$A$2:$A$800,0))),INDEX(DB_Prompts!$H$2:$H$800,MATCH('My Colleges'!$B$12&"|4",DB_Prompts!$A$2:$A$800,0)),"") | G35: =IF(AND($A35<>"",ISNUMBER(MATCH('My Colleges'!$B$12&"|4",DB_Prompts!$A$2:$A$800,0))),INDEX(DB_Prompts!$G$2:$G$800,MATCH('My Colleges'!$B$12&"|4",DB_Prompts!$A$2:$A$800,0)),"") | I35: =IF(AND($C35<>"",ISNUMBER('My Colleges'!$I$12)),'My Colleges'!$I$12-10,"")
A36: =IF(AND(ISNUMBER(MATCH('My Colleges'!$B$12&"|5",DB_Prompts!$A$2:$A$800,0)),'My Colleges'!$V$12<>"No"),'My Colleges'!$B$12,"") | B36: =IF($A36="","",5) | C36: =IF(AND($A36<>"",ISNUMBER(MATCH('My Colleges'!$B$12&"|5",DB_Prompts!$A$2:$A$800,0))),INDEX(DB_Prompts!$D$2:$D$800,MATCH('My Colleges'!$B$12&"|5",DB_Prompts!$A$2:$A$800,0)),"") | D36: =IF(AND($A36<>"",ISNUMBER(MATCH('My Colleges'!$B$12&"|5",DB_Prompts!$A$2:$A$800,0))),INDEX(DB_Prompts!$E$2:$E$800,MATCH('My Colleges'!$B$12&"|5",DB_Prompts!$A$2:$A$800,0)),"") | E36: =IF(AND($A36<>"",ISNUMBER(MATCH('My Colleges'!$B$12&"|5",DB_Prompts!$A$2:$A$800,0))),INDEX(DB_Prompts!$F$2:$F$800,MATCH('My Colleges'!$B$12&"|5",DB_Prompts!$A$2:$A$800,0)),"") | F36: =IF(AND($A36<>"",ISNUMBER(MATCH('My Colleges'!$B$12&"|5",DB_Prompts!$A$2:$A$800,0))),INDEX(DB_Prompts!$H$2:$H$800,MATCH('My Colleges'!$B$12&"|5",DB_Prompts!$A$2:$A$800,0)),"") | G36: =IF(AND($A36<>"",ISNUMBER(MATCH('My Colleges'!$B$12&"|5",DB_Prompts!$A$2:$A$800,0))),INDEX(DB_Prompts!$G$2:$G$800,MATCH('My Colleges'!$B$12&"|5",DB_Prompts!$A$2:$A$800,0)),"") | I36: =IF(AND($C36<>"",ISNUMBER('My Colleges'!$I$12)),'My Colleges'!$I$12-10,"")
A37: =IF(OR('My Colleges'!$B$13="",'My Colleges'!$V$13="No"),"",'My Colleges'!$B$13) | B37: =IF($A37="","",1) | C37: =IF($A37="","",IF(ISNUMBER(MATCH('My Colleges'!$B$13&"|1",DB_Prompts!$A$2:$A$800,0)),INDEX(DB_Prompts!$D$2:$D$800,MATCH('My Colleges'!$B$13&"|1",DB_Prompts!$A$2:$A$800,0)),IF('My Colleges'!$P$13=0,"No extra essays required.","Prompts not loaded yet: check this college's Admissions Page (last column on Explore) or its Common App page, and copy any prompts into Notes."))) | D37: =IF(AND($A37<>"",ISNUMBER(MATCH('My Colleges'!$B$13&"|1",DB_Prompts!$A$2:$A$800,0))),INDEX(DB_Prompts!$E$2:$E$800,MATCH('My Colleges'!$B$13&"|1",DB_Prompts!$A$2:$A$800,0)),"") | E37: =IF(AND($A37<>"",ISNUMBER(MATCH('My Colleges'!$B$13&"|1",DB_Prompts!$A$2:$A$800,0))),INDEX(DB_Prompts!$F$2:$F$800,MATCH('My Colleges'!$B$13&"|1",DB_Prompts!$A$2:$A$800,0)),"") | F37: =IF(AND($A37<>"",ISNUMBER(MATCH('My Colleges'!$B$13&"|1",DB_Prompts!$A$2:$A$800,0))),INDEX(DB_Prompts!$H$2:$H$800,MATCH('My Colleges'!$B$13&"|1",DB_Prompts!$A$2:$A$800,0)),"") | G37: =IF(AND($A37<>"",ISNUMBER(MATCH('My Colleges'!$B$13&"|1",DB_Prompts!$A$2:$A$800,0))),INDEX(DB_Prompts!$G$2:$G$800,MATCH('My Colleges'!$B$13&"|1",DB_Prompts!$A$2:$A$800,0)),"") | I37: =IF(AND($C37<>"",ISNUMBER('My Colleges'!$I$13)),'My Colleges'!$I$13-10,"")
A38: =IF(AND(ISNUMBER(MATCH('My Colleges'!$B$13&"|2",DB_Prompts!$A$2:$A$800,0)),'My Colleges'!$V$13<>"No"),'My Colleges'!$B$13,"") | B38: =IF($A38="","",2) | C38: =IF(AND($A38<>"",ISNUMBER(MATCH('My Colleges'!$B$13&"|2",DB_Prompts!$A$2:$A$800,0))),INDEX(DB_Prompts!$D$2:$D$800,MATCH('My Colleges'!$B$13&"|2",DB_Prompts!$A$2:$A$800,0)),"") | D38: =IF(AND($A38<>"",ISNUMBER(MATCH('My Colleges'!$B$13&"|2",DB_Prompts!$A$2:$A$800,0))),INDEX(DB_Prompts!$E$2:$E$800,MATCH('My Colleges'!$B$13&"|2",DB_Prompts!$A$2:$A$800,0)),"") | E38: =IF(AND($A38<>"",ISNUMBER(MATCH('My Colleges'!$B$13&"|2",DB_Prompts!$A$2:$A$800,0))),INDEX(DB_Prompts!$F$2:$F$800,MATCH('My Colleges'!$B$13&"|2",DB_Prompts!$A$2:$A$800,0)),"") | F38: =IF(AND($A38<>"",ISNUMBER(MATCH('My Colleges'!$B$13&"|2",DB_Prompts!$A$2:$A$800,0))),INDEX(DB_Prompts!$H$2:$H$800,MATCH('My Colleges'!$B$13&"|2",DB_Prompts!$A$2:$A$800,0)),"") | G38: =IF(AND($A38<>"",ISNUMBER(MATCH('My Colleges'!$B$13&"|2",DB_Prompts!$A$2:$A$800,0))),INDEX(DB_Prompts!$G$2:$G$800,MATCH('My Colleges'!$B$13&"|2",DB_Prompts!$A$2:$A$800,0)),"") | I38: =IF(AND($C38<>"",ISNUMBER('My Colleges'!$I$13)),'My Colleges'!$I$13-10,"")
A39: =IF(AND(ISNUMBER(MATCH('My Colleges'!$B$13&"|3",DB_Prompts!$A$2:$A$800,0)),'My Colleges'!$V$13<>"No"),'My Colleges'!$B$13,"") | B39: =IF($A39="","",3) | C39: =IF(AND($A39<>"",ISNUMBER(MATCH('My Colleges'!$B$13&"|3",DB_Prompts!$A$2:$A$800,0))),INDEX(DB_Prompts!$D$2:$D$800,MATCH('My Colleges'!$B$13&"|3",DB_Prompts!$A$2:$A$800,0)),"") | D39: =IF(AND($A39<>"",ISNUMBER(MATCH('My Colleges'!$B$13&"|3",DB_Prompts!$A$2:$A$800,0))),INDEX(DB_Prompts!$E$2:$E$800,MATCH('My Colleges'!$B$13&"|3",DB_Prompts!$A$2:$A$800,0)),"") | E39: =IF(AND($A39<>"",ISNUMBER(MATCH('My Colleges'!$B$13&"|3",DB_Prompts!$A$2:$A$800,0))),INDEX(DB_Prompts!$F$2:$F$800,MATCH('My Colleges'!$B$13&"|3",DB_Prompts!$A$2:$A$800,0)),"") | F39: =IF(AND($A39<>"",ISNUMBER(MATCH('My Colleges'!$B$13&"|3",DB_Prompts!$A$2:$A$800,0))),INDEX(DB_Prompts!$H$2:$H$800,MATCH('My Colleges'!$B$13&"|3",DB_Prompts!$A$2:$A$800,0)),"") | G39: =IF(AND($A39<>"",ISNUMBER(MATCH('My Colleges'!$B$13&"|3",DB_Prompts!$A$2:$A$800,0))),INDEX(DB_Prompts!$G$2:$G$800,MATCH('My Colleges'!$B$13&"|3",DB_Prompts!$A$2:$A$800,0)),"") | I39: =IF(AND($C39<>"",ISNUMBER('My Colleges'!$I$13)),'My Colleges'!$I$13-10,"")
A40: =IF(AND(ISNUMBER(MATCH('My Colleges'!$B$13&"|4",DB_Prompts!$A$2:$A$800,0)),'My Colleges'!$V$13<>"No"),'My Colleges'!$B$13,"") | B40: =IF($A40="","",4) | C40: =IF(AND($A40<>"",ISNUMBER(MATCH('My Colleges'!$B$13&"|4",DB_Prompts!$A$2:$A$800,0))),INDEX(DB_Prompts!$D$2:$D$800,MATCH('My Colleges'!$B$13&"|4",DB_Prompts!$A$2:$A$800,0)),"") | D40: =IF(AND($A40<>"",ISNUMBER(MATCH('My Colleges'!$B$13&"|4",DB_Prompts!$A$2:$A$800,0))),INDEX(DB_Prompts!$E$2:$E$800,MATCH('My Colleges'!$B$13&"|4",DB_Prompts!$A$2:$A$800,0)),"") | E40: =IF(AND($A40<>"",ISNUMBER(MATCH('My Colleges'!$B$13&"|4",DB_Prompts!$A$2:$A$800,0))),INDEX(DB_Prompts!$F$2:$F$800,MATCH('My Colleges'!$B$13&"|4",DB_Prompts!$A$2:$A$800,0)),"") | F40: =IF(AND($A40<>"",ISNUMBER(MATCH('My Colleges'!$B$13&"|4",DB_Prompts!$A$2:$A$800,0))),INDEX(DB_Prompts!$H$2:$H$800,MATCH('My Colleges'!$B$13&"|4",DB_Prompts!$A$2:$A$800,0)),"") | G40: =IF(AND($A40<>"",ISNUMBER(MATCH('My Colleges'!$B$13&"|4",DB_Prompts!$A$2:$A$800,0))),INDEX(DB_Prompts!$G$2:$G$800,MATCH('My Colleges'!$B$13&"|4",DB_Prompts!$A$2:$A$800,0)),"") | I40: =IF(AND($C40<>"",ISNUMBER('My Colleges'!$I$13)),'My Colleges'!$I$13-10,"")
A41: =IF(AND(ISNUMBER(MATCH('My Colleges'!$B$13&"|5",DB_Prompts!$A$2:$A$800,0)),'My Colleges'!$V$13<>"No"),'My Colleges'!$B$13,"") | B41: =IF($A41="","",5) | C41: =IF(AND($A41<>"",ISNUMBER(MATCH('My Colleges'!$B$13&"|5",DB_Prompts!$A$2:$A$800,0))),INDEX(DB_Prompts!$D$2:$D$800,MATCH('My Colleges'!$B$13&"|5",DB_Prompts!$A$2:$A$800,0)),"") | D41: =IF(AND($A41<>"",ISNUMBER(MATCH('My Colleges'!$B$13&"|5",DB_Prompts!$A$2:$A$800,0))),INDEX(DB_Prompts!$E$2:$E$800,MATCH('My Colleges'!$B$13&"|5",DB_Prompts!$A$2:$A$800,0)),"") | E41: =IF(AND($A41<>"",ISNUMBER(MATCH('My Colleges'!$B$13&"|5",DB_Prompts!$A$2:$A$800,0))),INDEX(DB_Prompts!$F$2:$F$800,MATCH('My Colleges'!$B$13&"|5",DB_Prompts!$A$2:$A$800,0)),"") | F41: =IF(AND($A41<>"",ISNUMBER(MATCH('My Colleges'!$B$13&"|5",DB_Prompts!$A$2:$A$800,0))),INDEX(DB_Prompts!$H$2:$H$800,MATCH('My Colleges'!$B$13&"|5",DB_Prompts!$A$2:$A$800,0)),"") | G41: =IF(AND($A41<>"",ISNUMBER(MATCH('My Colleges'!$B$13&"|5",DB_Prompts!$A$2:$A$800,0))),INDEX(DB_Prompts!$G$2:$G$800,MATCH('My Colleges'!$B$13&"|5",DB_Prompts!$A$2:$A$800,0)),"") | I41: =IF(AND($C41<>"",ISNUMBER('My Colleges'!$I$13)),'My Colleges'!$I$13-10,"")
A42: =IF(OR('My Colleges'!$B$14="",'My Colleges'!$V$14="No"),"",'My Colleges'!$B$14) | B42: =IF($A42="","",1) | C42: =IF($A42="","",IF(ISNUMBER(MATCH('My Colleges'!$B$14&"|1",DB_Prompts!$A$2:$A$800,0)),INDEX(DB_Prompts!$D$2:$D$800,MATCH('My Colleges'!$B$14&"|1",DB_Prompts!$A$2:$A$800,0)),IF('My Colleges'!$P$14=0,"No extra essays required.","Prompts not loaded yet: check this college's Admissions Page (last column on Explore) or its Common App page, and copy any prompts into Notes."))) | D42: =IF(AND($A42<>"",ISNUMBER(MATCH('My Colleges'!$B$14&"|1",DB_Prompts!$A$2:$A$800,0))),INDEX(DB_Prompts!$E$2:$E$800,MATCH('My Colleges'!$B$14&"|1",DB_Prompts!$A$2:$A$800,0)),"") | E42: =IF(AND($A42<>"",ISNUMBER(MATCH('My Colleges'!$B$14&"|1",DB_Prompts!$A$2:$A$800,0))),INDEX(DB_Prompts!$F$2:$F$800,MATCH('My Colleges'!$B$14&"|1",DB_Prompts!$A$2:$A$800,0)),"") | F42: =IF(AND($A42<>"",ISNUMBER(MATCH('My Colleges'!$B$14&"|1",DB_Prompts!$A$2:$A$800,0))),INDEX(DB_Prompts!$H$2:$H$800,MATCH('My Colleges'!$B$14&"|1",DB_Prompts!$A$2:$A$800,0)),"") | G42: =IF(AND($A42<>"",ISNUMBER(MATCH('My Colleges'!$B$14&"|1",DB_Prompts!$A$2:$A$800,0))),INDEX(DB_Prompts!$G$2:$G$800,MATCH('My Colleges'!$B$14&"|1",DB_Prompts!$A$2:$A$800,0)),"") | I42: =IF(AND($C42<>"",ISNUMBER('My Colleges'!$I$14)),'My Colleges'!$I$14-10,"")
A43: =IF(AND(ISNUMBER(MATCH('My Colleges'!$B$14&"|2",DB_Prompts!$A$2:$A$800,0)),'My Colleges'!$V$14<>"No"),'My Colleges'!$B$14,"") | B43: =IF($A43="","",2) | C43: =IF(AND($A43<>"",ISNUMBER(MATCH('My Colleges'!$B$14&"|2",DB_Prompts!$A$2:$A$800,0))),INDEX(DB_Prompts!$D$2:$D$800,MATCH('My Colleges'!$B$14&"|2",DB_Prompts!$A$2:$A$800,0)),"") | D43: =IF(AND($A43<>"",ISNUMBER(MATCH('My Colleges'!$B$14&"|2",DB_Prompts!$A$2:$A$800,0))),INDEX(DB_Prompts!$E$2:$E$800,MATCH('My Colleges'!$B$14&"|2",DB_Prompts!$A$2:$A$800,0)),"") | E43: =IF(AND($A43<>"",ISNUMBER(MATCH('My Colleges'!$B$14&"|2",DB_Prompts!$A$2:$A$800,0))),INDEX(DB_Prompts!$F$2:$F$800,MATCH('My Colleges'!$B$14&"|2",DB_Prompts!$A$2:$A$800,0)),"") | F43: =IF(AND($A43<>"",ISNUMBER(MATCH('My Colleges'!$B$14&"|2",DB_Prompts!$A$2:$A$800,0))),INDEX(DB_Prompts!$H$2:$H$800,MATCH('My Colleges'!$B$14&"|2",DB_Prompts!$A$2:$A$800,0)),"") | G43: =IF(AND($A43<>"",ISNUMBER(MATCH('My Colleges'!$B$14&"|2",DB_Prompts!$A$2:$A$800,0))),INDEX(DB_Prompts!$G$2:$G$800,MATCH('My Colleges'!$B$14&"|2",DB_Prompts!$A$2:$A$800,0)),"") | I43: =IF(AND($C43<>"",ISNUMBER('My Colleges'!$I$14)),'My Colleges'!$I$14-10,"")
A44: =IF(AND(ISNUMBER(MATCH('My Colleges'!$B$14&"|3",DB_Prompts!$A$2:$A$800,0)),'My Colleges'!$V$14<>"No"),'My Colleges'!$B$14,"") | B44: =IF($A44="","",3) | C44: =IF(AND($A44<>"",ISNUMBER(MATCH('My Colleges'!$B$14&"|3",DB_Prompts!$A$2:$A$800,0))),INDEX(DB_Prompts!$D$2:$D$800,MATCH('My Colleges'!$B$14&"|3",DB_Prompts!$A$2:$A$800,0)),"") | D44: =IF(AND($A44<>"",ISNUMBER(MATCH('My Colleges'!$B$14&"|3",DB_Prompts!$A$2:$A$800,0))),INDEX(DB_Prompts!$E$2:$E$800,MATCH('My Colleges'!$B$14&"|3",DB_Prompts!$A$2:$A$800,0)),"") | E44: =IF(AND($A44<>"",ISNUMBER(MATCH('My Colleges'!$B$14&"|3",DB_Prompts!$A$2:$A$800,0))),INDEX(DB_Prompts!$F$2:$F$800,MATCH('My Colleges'!$B$14&"|3",DB_Prompts!$A$2:$A$800,0)),"") | F44: =IF(AND($A44<>"",ISNUMBER(MATCH('My Colleges'!$B$14&"|3",DB_Prompts!$A$2:$A$800,0))),INDEX(DB_Prompts!$H$2:$H$800,MATCH('My Colleges'!$B$14&"|3",DB_Prompts!$A$2:$A$800,0)),"") | G44: =IF(AND($A44<>"",ISNUMBER(MATCH('My Colleges'!$B$14&"|3",DB_Prompts!$A$2:$A$800,0))),INDEX(DB_Prompts!$G$2:$G$800,MATCH('My Colleges'!$B$14&"|3",DB_Prompts!$A$2:$A$800,0)),"") | I44: =IF(AND($C44<>"",ISNUMBER('My Colleges'!$I$14)),'My Colleges'!$I$14-10,"")
A45: =IF(AND(ISNUMBER(MATCH('My Colleges'!$B$14&"|4",DB_Prompts!$A$2:$A$800,0)),'My Colleges'!$V$14<>"No"),'My Colleges'!$B$14,"") | B45: =IF($A45="","",4) | C45: =IF(AND($A45<>"",ISNUMBER(MATCH('My Colleges'!$B$14&"|4",DB_Prompts!$A$2:$A$800,0))),INDEX(DB_Prompts!$D$2:$D$800,MATCH('My Colleges'!$B$14&"|4",DB_Prompts!$A$2:$A$800,0)),"") | D45: =IF(AND($A45<>"",ISNUMBER(MATCH('My Colleges'!$B$14&"|4",DB_Prompts!$A$2:$A$800,0))),INDEX(DB_Prompts!$E$2:$E$800,MATCH('My Colleges'!$B$14&"|4",DB_Prompts!$A$2:$A$800,0)),"") | E45: =IF(AND($A45<>"",ISNUMBER(MATCH('My Colleges'!$B$14&"|4",DB_Prompts!$A$2:$A$800,0))),INDEX(DB_Prompts!$F$2:$F$800,MATCH('My Colleges'!$B$14&"|4",DB_Prompts!$A$2:$A$800,0)),"") | F45: =IF(AND($A45<>"",ISNUMBER(MATCH('My Colleges'!$B$14&"|4",DB_Prompts!$A$2:$A$800,0))),INDEX(DB_Prompts!$H$2:$H$800,MATCH('My Colleges'!$B$14&"|4",DB_Prompts!$A$2:$A$800,0)),"") | G45: =IF(AND($A45<>"",ISNUMBER(MATCH('My Colleges'!$B$14&"|4",DB_Prompts!$A$2:$A$800,0))),INDEX(DB_Prompts!$G$2:$G$800,MATCH('My Colleges'!$B$14&"|4",DB_Prompts!$A$2:$A$800,0)),"") | I45: =IF(AND($C45<>"",ISNUMBER('My Colleges'!$I$14)),'My Colleges'!$I$14-10,"")
A46: =IF(AND(ISNUMBER(MATCH('My Colleges'!$B$14&"|5",DB_Prompts!$A$2:$A$800,0)),'My Colleges'!$V$14<>"No"),'My Colleges'!$B$14,"") | B46: =IF($A46="","",5) | C46: =IF(AND($A46<>"",ISNUMBER(MATCH('My Colleges'!$B$14&"|5",DB_Prompts!$A$2:$A$800,0))),INDEX(DB_Prompts!$D$2:$D$800,MATCH('My Colleges'!$B$14&"|5",DB_Prompts!$A$2:$A$800,0)),"") | D46: =IF(AND($A46<>"",ISNUMBER(MATCH('My Colleges'!$B$14&"|5",DB_Prompts!$A$2:$A$800,0))),INDEX(DB_Prompts!$E$2:$E$800,MATCH('My Colleges'!$B$14&"|5",DB_Prompts!$A$2:$A$800,0)),"") | E46: =IF(AND($A46<>"",ISNUMBER(MATCH('My Colleges'!$B$14&"|5",DB_Prompts!$A$2:$A$800,0))),INDEX(DB_Prompts!$F$2:$F$800,MATCH('My Colleges'!$B$14&"|5",DB_Prompts!$A$2:$A$800,0)),"") | F46: =IF(AND($A46<>"",ISNUMBER(MATCH('My Colleges'!$B$14&"|5",DB_Prompts!$A$2:$A$800,0))),INDEX(DB_Prompts!$H$2:$H$800,MATCH('My Colleges'!$B$14&"|5",DB_Prompts!$A$2:$A$800,0)),"") | G46: =IF(AND($A46<>"",ISNUMBER(MATCH('My Colleges'!$B$14&"|5",DB_Prompts!$A$2:$A$800,0))),INDEX(DB_Prompts!$G$2:$G$800,MATCH('My Colleges'!$B$14&"|5",DB_Prompts!$A$2:$A$800,0)),"") | I46: =IF(AND($C46<>"",ISNUMBER('My Colleges'!$I$14)),'My Colleges'!$I$14-10,"")
A47: =IF(OR('My Colleges'!$B$15="",'My Colleges'!$V$15="No"),"",'My Colleges'!$B$15) | B47: =IF($A47="","",1) | C47: =IF($A47="","",IF(ISNUMBER(MATCH('My Colleges'!$B$15&"|1",DB_Prompts!$A$2:$A$800,0)),INDEX(DB_Prompts!$D$2:$D$800,MATCH('My Colleges'!$B$15&"|1",DB_Prompts!$A$2:$A$800,0)),IF('My Colleges'!$P$15=0,"No extra essays required.","Prompts not loaded yet: check this college's Admissions Page (last column on Explore) or its Common App page, and copy any prompts into Notes."))) | D47: =IF(AND($A47<>"",ISNUMBER(MATCH('My Colleges'!$B$15&"|1",DB_Prompts!$A$2:$A$800,0))),INDEX(DB_Prompts!$E$2:$E$800,MATCH('My Colleges'!$B$15&"|1",DB_Prompts!$A$2:$A$800,0)),"") | E47: =IF(AND($A47<>"",ISNUMBER(MATCH('My Colleges'!$B$15&"|1",DB_Prompts!$A$2:$A$800,0))),INDEX(DB_Prompts!$F$2:$F$800,MATCH('My Colleges'!$B$15&"|1",DB_Prompts!$A$2:$A$800,0)),"") | F47: =IF(AND($A47<>"",ISNUMBER(MATCH('My Colleges'!$B$15&"|1",DB_Prompts!$A$2:$A$800,0))),INDEX(DB_Prompts!$H$2:$H$800,MATCH('My Colleges'!$B$15&"|1",DB_Prompts!$A$2:$A$800,0)),"") | G47: =IF(AND($A47<>"",ISNUMBER(MATCH('My Colleges'!$B$15&"|1",DB_Prompts!$A$2:$A$800,0))),INDEX(DB_Prompts!$G$2:$G$800,MATCH('My Colleges'!$B$15&"|1",DB_Prompts!$A$2:$A$800,0)),"") | I47: =IF(AND($C47<>"",ISNUMBER('My Colleges'!$I$15)),'My Colleges'!$I$15-10,"")
A48: =IF(AND(ISNUMBER(MATCH('My Colleges'!$B$15&"|2",DB_Prompts!$A$2:$A$800,0)),'My Colleges'!$V$15<>"No"),'My Colleges'!$B$15,"") | B48: =IF($A48="","",2) | C48: =IF(AND($A48<>"",ISNUMBER(MATCH('My Colleges'!$B$15&"|2",DB_Prompts!$A$2:$A$800,0))),INDEX(DB_Prompts!$D$2:$D$800,MATCH('My Colleges'!$B$15&"|2",DB_Prompts!$A$2:$A$800,0)),"") | D48: =IF(AND($A48<>"",ISNUMBER(MATCH('My Colleges'!$B$15&"|2",DB_Prompts!$A$2:$A$800,0))),INDEX(DB_Prompts!$E$2:$E$800,MATCH('My Colleges'!$B$15&"|2",DB_Prompts!$A$2:$A$800,0)),"") | E48: =IF(AND($A48<>"",ISNUMBER(MATCH('My Colleges'!$B$15&"|2",DB_Prompts!$A$2:$A$800,0))),INDEX(DB_Prompts!$F$2:$F$800,MATCH('My Colleges'!$B$15&"|2",DB_Prompts!$A$2:$A$800,0)),"") | F48: =IF(AND($A48<>"",ISNUMBER(MATCH('My Colleges'!$B$15&"|2",DB_Prompts!$A$2:$A$800,0))),INDEX(DB_Prompts!$H$2:$H$800,MATCH('My Colleges'!$B$15&"|2",DB_Prompts!$A$2:$A$800,0)),"") | G48: =IF(AND($A48<>"",ISNUMBER(MATCH('My Colleges'!$B$15&"|2",DB_Prompts!$A$2:$A$800,0))),INDEX(DB_Prompts!$G$2:$G$800,MATCH('My Colleges'!$B$15&"|2",DB_Prompts!$A$2:$A$800,0)),"") | I48: =IF(AND($C48<>"",ISNUMBER('My Colleges'!$I$15)),'My Colleges'!$I$15-10,"")
A49: =IF(AND(ISNUMBER(MATCH('My Colleges'!$B$15&"|3",DB_Prompts!$A$2:$A$800,0)),'My Colleges'!$V$15<>"No"),'My Colleges'!$B$15,"") | B49: =IF($A49="","",3) | C49: =IF(AND($A49<>"",ISNUMBER(MATCH('My Colleges'!$B$15&"|3",DB_Prompts!$A$2:$A$800,0))),INDEX(DB_Prompts!$D$2:$D$800,MATCH('My Colleges'!$B$15&"|3",DB_Prompts!$A$2:$A$800,0)),"") | D49: =IF(AND($A49<>"",ISNUMBER(MATCH('My Colleges'!$B$15&"|3",DB_Prompts!$A$2:$A$800,0))),INDEX(DB_Prompts!$E$2:$E$800,MATCH('My Colleges'!$B$15&"|3",DB_Prompts!$A$2:$A$800,0)),"") | E49: =IF(AND($A49<>"",ISNUMBER(MATCH('My Colleges'!$B$15&"|3",DB_Prompts!$A$2:$A$800,0))),INDEX(DB_Prompts!$F$2:$F$800,MATCH('My Colleges'!$B$15&"|3",DB_Prompts!$A$2:$A$800,0)),"") | F49: =IF(AND($A49<>"",ISNUMBER(MATCH('My Colleges'!$B$15&"|3",DB_Prompts!$A$2:$A$800,0))),INDEX(DB_Prompts!$H$2:$H$800,MATCH('My Colleges'!$B$15&"|3",DB_Prompts!$A$2:$A$800,0)),"") | G49: =IF(AND($A49<>"",ISNUMBER(MATCH('My Colleges'!$B$15&"|3",DB_Prompts!$A$2:$A$800,0))),INDEX(DB_Prompts!$G$2:$G$800,MATCH('My Colleges'!$B$15&"|3",DB_Prompts!$A$2:$A$800,0)),"") | I49: =IF(AND($C49<>"",ISNUMBER('My Colleges'!$I$15)),'My Colleges'!$I$15-10,"")
A50: =IF(AND(ISNUMBER(MATCH('My Colleges'!$B$15&"|4",DB_Prompts!$A$2:$A$800,0)),'My Colleges'!$V$15<>"No"),'My Colleges'!$B$15,"") | B50: =IF($A50="","",4) | C50: =IF(AND($A50<>"",ISNUMBER(MATCH('My Colleges'!$B$15&"|4",DB_Prompts!$A$2:$A$800,0))),INDEX(DB_Prompts!$D$2:$D$800,MATCH('My Colleges'!$B$15&"|4",DB_Prompts!$A$2:$A$800,0)),"") | D50: =IF(AND($A50<>"",ISNUMBER(MATCH('My Colleges'!$B$15&"|4",DB_Prompts!$A$2:$A$800,0))),INDEX(DB_Prompts!$E$2:$E$800,MATCH('My Colleges'!$B$15&"|4",DB_Prompts!$A$2:$A$800,0)),"") | E50: =IF(AND($A50<>"",ISNUMBER(MATCH('My Colleges'!$B$15&"|4",DB_Prompts!$A$2:$A$800,0))),INDEX(DB_Prompts!$F$2:$F$800,MATCH('My Colleges'!$B$15&"|4",DB_Prompts!$A$2:$A$800,0)),"") | F50: =IF(AND($A50<>"",ISNUMBER(MATCH('My Colleges'!$B$15&"|4",DB_Prompts!$A$2:$A$800,0))),INDEX(DB_Prompts!$H$2:$H$800,MATCH('My Colleges'!$B$15&"|4",DB_Prompts!$A$2:$A$800,0)),"") | G50: =IF(AND($A50<>"",ISNUMBER(MATCH('My Colleges'!$B$15&"|4",DB_Prompts!$A$2:$A$800,0))),INDEX(DB_Prompts!$G$2:$G$800,MATCH('My Colleges'!$B$15&"|4",DB_Prompts!$A$2:$A$800,0)),"") | I50: =IF(AND($C50<>"",ISNUMBER('My Colleges'!$I$15)),'My Colleges'!$I$15-10,"")
